Workbook

Sheet README
A1: US Interfacility Transport: Sourced Evidence Master
A2: A complete, source-verified evidence base for the United States interfacility medical transport market: who moves, between which care settings, at what clinical acuity, paid by whom, at what price, and served by which suppliers. Built and verified 09 to 10 July 2026.
A4: What this workbook is, in one paragraph
A5: Every number in these 43 tabs comes from a named government dataset, a peer-reviewed study, or a published primary document, or is computed by a visible Excel formula from numbers that do. Nothing is modeled, blended, or assumed. Where a figure the market usually wants does not exist in any public source, this workbook says so and names exactly what would produce it. That refusal is deliberate: the analyses here are built to survive diligence questioning, so every claim can be walked back to its document in three steps.
A7: How to read any number in three steps
A8: Step 1: every tab tags its figures with Fact IDs (F01 to F165). Step 2: the Fact_Ledger resolves each ID to a source, tier, and locator down to the table or page. Step 3: the Source_Index identifies all 73 sources on one row each, with the full citation and URL on the Source_Register. If a figure is labeled DERIVED, the ledger names its inputs and the cell shows the arithmetic.
A10: The colour and label conventions
A11: Blue font: a value hardcoded from a source document. Black font: an Excel formula. Green font: a link to another tab. Tier A: verified against the primary document. Tier B: published but secondary, or a figure that moves over time. SOURCED: carried from an upstream dataset and not independently reopened. DERIVED: computed here, with inputs named. Every derived comparison prints its caveat in the same row it appears.
A13: The map: what each section answers
A14: Section | B14: Tabs | C14: The question it answers
A15: Governance | B15: Methodology, Findings, Charts, Verification_Log, Fact_Ledger, Source_Register, Source_Index | C15: Why every number is here, the 41 findings that matter, and the complete audit trail.
A16: Demand | B16: Demand_Drivers, Macro_Demand_Drivers, Demand_Stack, Acute_IFT_Series, Other_Transfer_Channels, Receiving_Side, EMS_Transports | C16: How many patients move, from which settings, driven by which measured forces.
A17: Medicare claims core | B17: Medicare_PSPS, Medicare_IFT_Series, Medicare_OD_Matrix, Utilization_Normalized, Acuity_by_Channel, Air_Ambulance_IFT, Dialysis_ESRD_Channel | C17: The only public origin-to-destination dollar map: volumes, dollars, acuity, and per-beneficiary rates, 2010 to 2024.
A18: Price and payment | B18: Payment_Rules, Payer_Rates_Commercial | C18: What Medicare pays and when it changes; what commercial payers and Medicaid pay, published figures only.
A19: Supply | B19: Supplier_Landscape, Supplier_Series_Raw, Supplier_Trend, Workforce_Supply, Supply_Stack | C19: Who provides transport: a decade of billing organizations, the paid and volunteer workforce, and every measured capacity constraint.
A20: Market structure | B20: State_Saturation_Raw, State_Saturation, MSA_Landscape, Imbalance_Ledger | C20: The state screen, the metro landscape, and demand-over-supply ratios including the whitespace register.
A21: Client alignment | B21: Sizing_Playbook, Engagement_Data_Map | C21: How the team converges on a defensible market number, and which source answers which question, with every awaited input named.
A22: Costs and reconciliation | B22: Cost_and_Capacity, MedPAC_2026_Mandated, Cross_Source_Recon | C22: What a transport costs to produce, and why four national sources give four different counts.
A23: Reference | B23: IFT_Alt_Measures, Code_Crosswalks, Dataset_Linkage_Map | C23: Every alternative counting route, every code system that records a transfer, and every dataset with its join keys.
A24: Integrity | B24: Fault_Audit, Data_Quality_Register, Clinical_Volumes_TierC, Excluded_Not_Sourced | C24: Every known threat to validity, and the quarantine of anything that failed the sourcing rule.
A26: What this workbook deliberately does not contain
A27: A single asserted total addressable market figure. A credible TAM requires a commercial transport volume, a Medicare Advantage transport volume, and an acuity-weighted price, and none of the three exists in any public source. A three-scenario TAM MODEL with an explicit assumption register now lives on TAM_Model_National; its outputs are scenario arithmetic under stated gates, never quoted as a single fact. The commercial and MA books are bounded here with published evidence (Payer_Rates_Commercial; the dark-share series on Imbalance_Ledger), and the exact datasets that would complete them are named on Dataset_Linkage_Map with access terms and cost.
A29: Revision summary
A30: Revision | B30: Date | C30: Contents
A31: 1 | B31: 09 July 2026 | C31: Initial evidence base: 20 tabs, facts F01 to F109, sources S01 to S38, findings 1 to 25, all verified against primary documents.
A32: 2 | B32: 10 July 2026 | C32: The complete Medicare origin-to-destination dollar map rebuilt from 392,409 raw claim rows (reconciling to the cent), the air and dialysis channels, commercial rates, macro drivers, code crosswalks, and the dataset linkage map. Facts through F135; sources through S58.
A33: 3 | B33: 10 July 2026 | C33: Per-beneficiary normalization, acuity by channel, the supplier landscape, and the payment add-on cliff. Facts through F147; sources through S61.
A34: 4 | B34: 10 July 2026 | C34: The demand and supply stacks, the imbalance ledger with the whitespace register, an eleven-year supplier series, workforce, state saturation, metro landscape, alternative counting routes, and the consolidated fault audit. Facts through F163; sources through S72.
A35: 5 | B35: 10 July 2026 | C35: Final consolidation: the official state-file cross-check (bounding the supplier-file suppression tail at 1.0%), corrections from independent external review, and full internal-consistency verification. Facts through F165; 73 sources; zero formula errors.
A37: Pending register: named enhancements, none assumed
A38: P1 HCUPnet condition-level transfer rates (point estimates; standard errors require licensed microdata under the published AHRQ variance method). P2 Ambulance-desert state and county tables. P3 Full ZCTA-to-CBSA crosswalk for complete metro coverage. P4 BLS OEWS state wage files, 2024 to 2025. P5 USRDS prevalent in-center hemodialysis counts by year. P6 NASEMSO 2020 National EMS Assessment. P7 Industry turnover and certification-pipeline measures. P8 Air-sector distress dockets. P9 SNF occupancy from the CMS Provider Information file. P10 PSPS carrier-dimension re-pull for regional origin-destination cuts, using the CMS ZIP-to-carrier-locality and rural or super-rural ZIP files. P11 Rural closure list parsed by state. P12 ECAT eCQM specifications. P13 The NHSN weekly hospital capacity series (mandated reporting resumed November 2024). P14 The CMS ZIP-to-carrier-locality and ambulance rural ZIP files themselves. P15 AHRQ Compendium hospital-to-system linkage joined to the Hospital Service Area File: the free within-system versus cross-system transfer test. P16 Completed with revision 5 (official state file, S73). P17 HCCI commercial ground brief and the Peterson-KFF out-of-network analysis. P18 The Health Affairs boarding series. P19 The published ED interfacility-transfer study and the current MedPAC Payment Basics vintage, whose organization count corroborates the supplier floor and whose transport headline, once pinned, bounds the institutional channel.
A40: Prepared with a deterministic pipeline: every dataset pull is specified to the endpoint and identifier on the Verification_Log so the entire workbook can be independently reproduced.

Sheet Methodology
A1: Why every number in this workbook is here, and why the ones that are not are not.
A2: The question here is simple: why should anyone trust this workbook? This tab is the decision record. It walks through the inclusion rule, why each evidence tab exists, the definitional choices that move the numbers, exactly how the data was pulled so it can be rerun, the rules for comparing figures, the corrections made along the way, and what the workbook still cannot do. Read this first.
A4: 1. The question this workbook answers, and the one it refuses to answer.
A5: The question. How large is US interfacility transport, who moves, between which settings, at what acuity, paid by whom, and at what price. Every tab answers one slice of that and cites the document that produced it.
A6: The refusal. This workbook does not size a total addressable market. A TAM requires a commercial-payer volume, a Medicare Advantage volume and an acuity-weighted price, none of which exists in any public source. The initial build carried three such assumptions (a 4.27x gross-up, a 2x to 4x commercial multiple, an acuity mix); all three were moved to Excluded_Not_Sourced and stayed there. revision 2 replaced two of them with published bounds rather than restoring the estimate.
A7: The consequence you must accept. Some cells on this workbook say the number does not exist. That is the finding. An analyst who needs a TAM must buy data (Dataset_Linkage_Map lists which), not blend a public one.
A9: 2. The inclusion rule, applied without exception.
A10: Rule | B10: Why | C10: What it prevents
A11: A number enters only if a named publisher document produced it, or an Excel formula computes it from numbers that did. | B11: Traceability must survive the analyst. Anyone opening a cell sees either a source-pinned constant or the arithmetic that made it. | C11: Numbers with no parent. The single most common failure in diligence workbooks is a figure that no one can source six weeks later.
A12: Blue font means hardcoded from a document. Black means a formula. Green means a link to another tab. | B12: The colour is the audit trail. A reader can see the provenance of a cell without clicking it. | C12: Hardcoded values masquerading as calculations, and stale pastes of numbers that should have updated.
A13: Every fact carries a Fact ID (F01-F147), a Tier, a Source ID and a locator down to the table or page. | B13: Tier separates what was verified against the primary document from what was asserted by an upstream workbook. | C13: Laundering. An assumption quoted twice does not become evidence.
A14: Anything labeled ILLUSTRATIVE, FRAMEWORK or INDUSTRY ESTIMATE is quarantined on Excluded_Not_Sourced. | B14: These labels are how modeled numbers enter a deck and never leave. | C14: A framework assumption being read off a chart axis as though it were measured.
A15: Derived figures are labeled DERIVED and show their inputs. | B15: A ratio of two published numbers is legitimate. A ratio of a published number and a guess is not. | C15: Same-source, same-year discipline on every multiple (see section 6).
A17: 3. Why each evidence tab exists.
A18: Tab | B18: The question it settles | C18: Why it had to be built | D18: Primary sources
A19: Acute_IFT_Series | B19: How many acute-to-acute transfers happen, from the ED and from inpatient beds. | C19: HCUP is the only national all-payer census of hospital discharges. Its two origin channels are mutually exclusive and must be added, not averaged. | D19: S01, S04
A20: Receiving_Side | B20: Does the receiving side of the ledger agree with the sending side. | C20: A transfer has two ends. NIS TRAN_IN counts arrivals independently of DISPUNIFORM departures. Agreement is the workbook internal validity test. | D20: S04
A21: EMS_Transports | B21: How many ambulance legs exist, and what share are interfacility. | C21: Hospital data counts patients moved; EMS data counts vehicles moving them. The two are different units and neither substitutes for the other. | D21: S12, S25, S55
A22: Medicare_PSPS | B22: What does Medicare fee-for-service actually pay, by acuity and by origin-destination pair. | C22: It is the only public file that carries dollars, acuity and endpoints on the same row. | D22: S13, S39
A23: Medicare_IFT_Series | B23: Is the Medicare hospital-to-hospital book growing or shrinking. | C23: No published table contains this series. It was built by pulling fifteen annual PSPS files and filtering the HH modifier. | D23: S32
A24: Medicare_OD_Matrix | B24: Where does the entire Medicare ambulance dollar go, pair by pair. | C24: revision 1 carried the HH pair only. Building the full matrix revealed that the SNF interface is 2.75x the hospital pair, which reframes the market definition. | D24: S39
A25: Utilization_Normalized | B25: Is the Medicare decline demand or denominator. | C25: FFS enrollment fell 15.5% over the same window. Without dividing by it, every trend on this workbook overstates decline by roughly a factor of two. | D25: S39, S60
A26: Acuity_by_Channel | B26: Are the interfacility channels one clinical product or several. | C26: Staffing, unit economics and payer strategy all follow acuity. SNF-to-hospital is 94% emergency; hospital-to-SNF is 99% non-emergency. One name, opposite products. | D26: S39
A27: Air_Ambulance_IFT | B27: Where does high-acuity interfacility volume actually sit. | C27: Rotary-wing is 65.6% hospital-to-hospital and grows per beneficiary while ground shrinks. Ground acuity mix cannot describe it. | D27: S40, S44
A28: Dialysis_ESRD_Channel | B28: What happens to a scheduled-transport book when a payer decides the volume is discretionary. | C28: The RSNAT rollout is a natural experiment with a date. The claims date-stamp the intervention, which makes it the template for Medicare Advantage behaviour elsewhere. | D28: S39, S41, S42
A29: Payment_Rules | B29: What governs the Medicare price, and when does it change. | C29: RVUs are frozen since 2002, geographic adjustments since 2008, and the statutory add-ons expire 1 January 2028. The price is legislative, not market. | D29: S14, S16, S28, S29, S61
... A36: Cross_Source_Recon | B36: Why do four sources give four different numbers. | C36: They measure different units on different universes. The wedge is enumerated driver by driver so the spread is explained rather than averaged away. | D36: S01, S04, S12, S13
A38: 4. Definitional choices that change the answer, and the choice this workbook made.
A39: Choice | B39: Options | C39: What was chosen and why
A40: What counts as interfacility | B40: (a) Hospital-to-hospital only. (b) Any facility-to-facility pair. (c) Any non-scene transport. | C40: (b), reported by pair. Restricting to (a) hides 2.4M SNF-interface transports; (c) sweeps in dialysis and discharge-home legs that behave nothing alike. Every tab reports pairs separately so the reader can pick.
A41: Ground base codes | B41: Six codes (A0426-A0429, A0433, A0434) or seven including paramedic intercept A0432. | C41: Six. A0432 is a rural intercept payment, not a transport (3,312 services in 2024). Stated on Acuity_by_Channel so counts tie.
A42: Service basis | B42: PSPS submitted services, or MUP-PHY final-action approved services. | C42: PSPS for all volumes and dollars; MUP only for supplier counts. The two differ by 1.10x in 2024 and must never be mixed. Data_Quality_Register #34.
A43: FFS denominator | B43: Original Medicare any part (33.9M in 2024) or Part A and B both (27.7M). | C43: A and B, the population that can generate a carrier ambulance claim. The choice moves every per-1,000 rate by about a fifth, so it is stated on the tab and in DQ #35.
A44: Fractional service counts | B44: Truncate to integers or sum as floats. | C44: Sum as floats. PSPS carries decimal service counts on shared services. The revision 1 truncation cost 39 services out of 10.6M. Correction #7.
A45: Rural closure count | B45: Sheps 154 since 2010, or Chartis 182. | C45: Sheps, with the Chartis number recorded beside it and a warning never to mix them. Different conventions on Rural Emergency Hospital conversions. DQ #31.
A46: Air interfacility inference | B46: Use O-D modifiers for both rotary and fixed-wing, or rotary only. | C46: Rotary only. Fixed-wing is 94.6% II (airport to airport), so its modifiers identify runways. DQ #29.
A48: 5. The data pipeline, stated so it can be rerun.
A49: PSPS. GET https://data.cms.gov/data-api/revision 1/dataset/{uuid}/data?filter[HCPCS_CD]={code}, paginated at 5,000 rows, one call per HCPCS per data year. Fifteen data years, twelve ambulance codes, 392,409 rows. Dataset UUIDs are printed on Verification_Log Panel F. Two schema traps: the PSPS_ field prefix begins with data year 2020 (not 2021), and service counts are decimal.
A50: MUP-PHY. Same host, filter[HCPCS_Cd]={code}, 2019 and 2024 datasets, eight base codes, 44,614 NPI-by-code rows. Rows with 10 or fewer beneficiaries are suppressed at source, so counts are floors.
A51: Enrollment. Same host, Medicare Monthly Enrollment, filter[BENE_GEO_LVL]=National and filter[MONTH]=Year, 2013 to 2025.
A52: Everything else was opened by hand: PDFs downloaded and parsed, HTML read, PubMed queried by PMID, NPPES and the Medicare Coverage Database queried live. Dates of access are on the Source_Index.
A53: Determinism. No sampling, no imputation, no model. Every figure is a sum, a ratio, or a value copied from a document. The workbook recalculates to zero formula errors across 1,111 formulas.
A55: 6. Rules for comparing numbers, which is where diligence workbooks usually break.
A56: Same source, same year, or say so. The 5.0x rotary air multiple divides FAIR Health commercial allowed by FAIR Health Medicare allowed, both 2020, both from one white paper. The ground multiple of roughly 1.6x divides FAIR 2020 commercial by a 2024 claims-derived Medicare figure and is therefore labeled CROSS-YEAR AND CROSS-BASIS on its own tab. It is bounding evidence, not a rate card.
A57: Never add a patient count to a vehicle count. HCUP counts discharges, NEMSIS counts activations, PSPS counts billed services. Cross_Source_Recon enumerates the wedge drivers instead of averaging four incompatible numbers into a fifth wrong one.
A58: Deflate before you interpret. Any Medicare fee-for-service series read as demand must first be divided by fee-for-service enrollment, which fell 15.5% over 2019 to 2024 (Utilization_Normalized).
A59: A suppressed cell is a floor, not a zero. CMS masks cells under 11 services in PSPS and under 11 beneficiaries in MUP. Every count in this workbook derived from those files is a floor and says so.
A60: A confidence interval that does not exist cannot be invented. HCUP weighted summary statistics carry no standard errors. HCUPnet does NOT supply them; they require licensed microdata and the AHRQ variance method (finding confirmed by independent external review, 10 July 2026). Until that route is taken, no HCUP trend in this workbook is called significant.
A62: 7. Corrections made to prior work, kept visible on purpose.
A63: # | B63: What was wrong | C63: What is right | D63: Where
A64: 1 | B64: CY2024 Ambulance Inflation Factor carried as 3.0% | C64: 2.6%, per the CMS manual and MedPAC | D64: Payment_Rules
A65: 2 | B65: Medicare FFS ambulance spend as $4.0B in 2023 | C65: $3.9B in 2022 program spending | D65: Payment_Rules
A66: 3 | B66: GADCS for-profit cost per transport as $1,778 | C66: $1,788 | D66: Cost_and_Capacity
A67: 4 | B67: GADCS mean of $2,673 quoted without its median | C67: Median is $1,340. The mean is skewed and MedPAC says the data cannot support a margin | D67: Cost_and_Capacity
A68: 5 | B68: Conversion factor assumed at $278.00 | C68: $272.44, CY2024, published | D68: Payment_Rules
A69: 6 | B69: 2007 NIS total omitted 16,542 records | C69: Restated | D69: Acute_IFT_Series
A70: 7 | B70: PSPS service counts truncated to integers | C70: Decimal counts summed as floats. 871,753 becomes 871,756 on the 2024 HH base set | D70: Medicare_OD_Matrix
A71: 8 | B71: PSPS_ field prefix said to begin in 2021 | C71: It begins with data year 2020 | D71: Verification_Log
A72: 9 | B72: Two draft read-notes overstated their own findings | C72: Corrected against computed values before release: HH per-capita decline is 8.0% (not flat) and the HH emergency-share shift is 2.4 points (not 5.0) | D72: Verification_Log Panel G
A74: 8. What this workbook still cannot do, and what would fix it.
A75: Gap | B75: Why it exists | C75: The fix | D75: Cost
A76: No confidence interval on any HCUP trend | B76: Weighted summary statistics ship without standard errors | C76: License NEDS or NIS microdata and apply AHRQ Methods 2015_09; HCUPnet is point estimates only | D76: Purchase plus DUA
A77: No hospital-pair transfer flows | B77: National HCUP files mask hospital identity | C77: Purchase one state SID/SEDD with hospital IDs | D77: Low four figures per state
A78: No corporate ownership roll-up | B78: An NPI is not a parent company | C78: Build the PECOS reassignment and ownership graph | D78: Free, engineering time
A79: No real commercial rate card | B79: FAIR Health publishes averages, not rates | C79: Parse Transparency in Coverage machine-readable files for A042x by NPI | D79: Free, heavy compute
A80: No Medicare Advantage transport volume | B80: MA encounter data is not public | C80: Encounter data via ResDAC DUA, or a licensed claims panel | D80: Months, or paid
A81: No activation-level IFT flag nationally | B81: NEMSIS public reports are aggregated | C81: Request the NEMSIS research dataset | D81: Free, paperwork
A82: No 2025 EMS data | B82: The NEMSIS 2025 annual report is not published | C82: Expected around August 2026 | D82: Wait
A83: No Medicare ambulance margin | B83: MedPAC found GADCS reporting errors severe enough to disqualify it | C83: MedPAC Recommendation 6 asks Congress to keep collecting, streamlined | D83: Years

Sheet Findings
A1: What the merged evidence actually supports
A2: The question: out of everything measured here, what actually matters to a decision? These are the 41 findings, each resting on a published count or arithmetic over published counts, each with its sources, its confidence, and, most importantly, the interpretation guardrail each one carries.
A4: # | B4: Finding | C4: The numbers | D4: Sources | E4: Confidence | F4: Interpretation guardrail
A5: 1 | B5: The IFT market is roughly 3 million acute-to-acute transfer episodes a year, and that level is stable. | C5: 2,929,273 episodes in 2022. Mean of 2019 to 2023 is 3,061,156, sample standard deviation 139,226. The five-year range runs 2,929,273 (2022) to 3,234,266 (2019). | D5: S01, S04 | E5: High | F5: Never quote a single year as the level. The COVID years sit inside the band.
A6: 2 | B6: Interfacility transfer is about 9.3% of US community hospital inpatient admissions, and the level is stable at that number. | C6: 9.28% in 2022. Mean 9.49% across 2019 to 2023, band 9.24% (2021) to 9.85% (2023), sample standard deviation 0.24 points. | D6: S01, S04, S05-S11 | E6: High | F6: The number is denominator-dependent to plus or minus 0.8 points. Disclose which denominator you used.
A7: 3 | B7: The famous near-doubling of the IFT ratio is a channel mix shift, not the market exploding. | C7: The ED-origin channel went from 3.85% of admissions in 2007 to 7.33% in 2022, a 90.5% relative gain. On the COMPLETE build (ED-origin plus inpatient-origin) the same ratio grew only +1.09% per year from 2012 to 2022, and total acute-to-acute episodes grew +0.86% per year from 2012 to 2023. | D7: S01, S04, S05-S11 | E7: High | F7: Never present the 90.5% figure as market growth. It is the ED channel only.
A8: 4 | B8: Transfers migrated out of the inpatient bed and into the ED. | C8: ED-origin share of acute-to-acute episodes: 74.4% (2012), 78.9% (2022), 80.2% (2023). Inpatient-origin episodes fell at -1.48% per year while ED-origin episodes grew at +1.55% per year, 2012 to 2023. | D8: S01, S04 | E8: High | F8: This is the single clearest structural trend in the data. It is also why an ED-only measurement overstates growth.
A9: 5 | B9: IFT is counter-cyclical to hospital admissions. Volume grows while the denominator shrinks. | C9: Total acute-to-acute episodes +0.86% per year, 2012 to 2023. AHA community hospital admissions -0.67% per year over the same window. NIS discharges -0.71% per year. The complete-build ratio therefore compounds at +1.54% per year, of which 56% is numerator growth and 44% is denominator shrinkage. | D9: S01, S04, S05-S11 | E9: High | F9: The often-quoted split of four fifths numerator and one fifth denominator applies only to the ED channel over 2007 to 2022, where transfer volume compounded at +3.48% against admissions at -0.87%. Never carry it onto the complete build.
A10: 6 | B10: Carrier-billed Medicare interfacility work is low-acuity scheduled transport. It is not critical care. | C10: Of 871,753 Medicare FFS hospital-to-hospital transports in 2024: non-emergency BLS 38.8% and non-emergency ALS1 23.5%, together 62.3% of transports. Specialty Care Transport is 6.6% of transports. Weighted by actual allowed dollars, SCT is 15.6% of base-rate revenue and non-emergency BLS and ALS1 are 46.1%. The volume-weighted RVU of the book is 1.45, not 3.25. | D10: S13, S14, S28 | E10: High for carrier-billed Medicare FFS. Unknown elsewhere. | F10: Scope it carefully. PSPS is carrier claims only, so hospital-owned ambulance departments, the ones most likely to run critical-care crews, are structurally absent, and Medicare Advantage is entirely absent. It says nothing about the commercial book. What it does kill is the excluded 56.4% high-acuity assumption applied to a Medicare-weighted book. Price weighting narrows the gap between volume and revenue mix. It does not close it.
A11: 7 | B11: Interfacility is gaining share of a shrinking Medicare fee-for-service book, but the book itself peaked in 2017. | C11: Medicare FFS hospital-to-hospital transports grew from 825,178 (2022) to 871,753 (2024), +2.78% per year, while all origin-destination-coded Medicare FFS ambulance volume fell -2.80% per year. Over fifteen years, however, the interfacility book peaked at 1,139,524 transports in 2017 and is now 23.5% smaller. | D11: S13 | E11: High | F11: Read the 2022 to 2024 rate as recovery off the COVID trough, NOT as trend. The 2017 to 2024 CAGR is -3.75% per year. Medicare Advantage enrolment crossing half of all beneficiaries is the dominant driver of the fee-for-service decline, not a fall in interfacility demand.
A12: 8 | B12: Three different objects are routinely conflated, and the factor between them is 1.7 to 1.9. | C12: 2022 sending-side episodes 2,929,273. 2022 receiving-side transfer admissions 2,205,490. 2024 hospital-to-hospital ambulance transports 5,510,664. 2024 all facility-to-facility transports 7,512,656. | D12: S01, S04, S12 | E12: High | F12: This is the largest source of error in the published IFT literature, larger than sampling, coding and denominator error combined.
A13: 9 | B13: About three quarters of transfers sent arrive as an inpatient admission at a receiving acute hospital. | C13: Conversion rate 75.3% in 2022, 77.4% in 2023. The residual went to a psychiatric, rehabilitation or LTACH hospital (all outside the NIS universe), was treated and released at the receiving ED, was placed in observation, or was not coded as a transfer in. | D13: S01, S04 | E13: High | F13: The receiving-side measurement is independent: a different UB-04 field, a different hospital, a different clerk. It confirms the sending-side count.
A14: 10 | B14: Medicare fee-for-service sees only about one sixth of national interfacility transport. | C14: 871,753 Medicare FFS hospital-to-hospital transports in 2024, against 5,510,664 hospital-to-hospital transports reported by NEMSIS, or 15.8%. | D14: S12, S13 | E14: Moderate-High | F14: A floor, twice over. Hospital-owned ambulance departments bill institutionally and never enter PSPS. NEMSIS is a voluntary census and is itself a floor.
A15: 11 | B15: The government cost benchmark that circulates is a mean. The median is half of it, and that changes the conclusion. | C15: GADCS mean cost per transport is $2,673 all-in. The MEDIAN is $1,340. For-profit organizations: mean $1,788, median $610. Government: mean $3,127, median $1,859. Very-high-volume organizations: mean $946. Labor is 69.4% of the $27.2 billion aggregated cost base. Cost per RVU is $1,624 mean and $811 median, against Medicare allowed of about $253 per RVU. | D15: S30 | E15: Moderate-High | F15: The mean is dragged up by thousands of tiny low-volume organizations (mean $3,652). Quote the median for a scaled platform. The excluded market study's modeled net revenue of $1,200 to $1,400 per transport sits just below the $1,340 median, not far below a $2,673 mean. The correct statement is that the fee schedule does not cover cost and scale is the entire game.
A16: 12 | B16: Reimbursement inflation is government-set, productivity-lagged, and volatile. | C16: Verified AIF: 0.9% (2020), 0.2% (2021), 5.1% (2022), 8.7% (2023), 2.6% (2024), 2.4% (2025), 2.0% (2026). Seven-year average 3.1%, trailing three-year average 2.3%, sample standard deviation 2.9 points. Statutory add-ons of +2% urban, +3% rural and +22.6% super-rural sit on the base rate and require repeated legislative extension. | D16: S15, S16 | E16: High | F16: The source workbook carried CY2024 at 3.0%. The CMS manual and MedPAC both print 2.6%. The 8.7% in 2023 is the post-COVID CPI peak. The AIF is CPI-U less a total factor productivity adjustment, so it structurally under-runs paramedic wage inflation.
... A29: 25 | B29: The naive link between transfer delay and patient harm runs backwards, because the sickest patients move fastest. | C29: In 1,535 elderly blunt-trauma interfacility transfers, SHORTER emergency department dwell time was associated with higher injury severity, lower Glasgow Coma Scale and higher mortality. In 5,859 ED-ICU patients, ED length of stay showed no significant association with mortality after adjustment. A systematic review of 34 studies covering 2.3 million patients found variable and heterogeneous associations between ED length of stay and outcomes. | D29: S36, S37, S38 | E29: Contested. State it honestly. | F29: Never use dwell time as an outcome proxy without adjusting for acuity: the correlation has the wrong sign. The case for faster transfer rests on throughput, capacity and cost, not on a clean mortality effect. Any deck that claims boarding kills, and cites raw dwell-time correlations, is wrong on the evidence.
A30: Every single-year change under about 3% in relative terms sits inside the combined coding and sampling noise. That covers the ratio declines in 2013, 2014, 2015, 2017, 2018, 2021 and 2022.
A31: Verification. Every underlying value was checked against its primary document on 09 July 2026. 233 values checked, 228 matched exactly. Six corrections, one of which corrects an earlier claim in this workbook.
A32: Confidence is stated against the counts as AHRQ, NHTSA, CMS, RAND, MedPAC and AHA published them. What remains unverifiable is AHRQ's weighting, which is calibrated to the non-public AHA hospital-level survey.
A33: No confidence interval can be attached to any HCUP volume CAGR. AHRQ publishes no standard errors. The +0.86% per year total-episode CAGR is not demonstrably different from zero on this evidence.
A34: Peer-reviewed evidence was retrieved from PubMed on 09 July 2026 and every claim carries its digital object identifier so it can be checked at source.
A36: Findings 26 to 31, revision 2 (10 July 2026). Same rule: every one rests on a published count or arithmetic over published counts.
A37: # | B37: Finding | C37: The numbers | D37: Sources | E37: Confidence | F37: Interpretation guardrail
A38: 26 | B38: The dialysis ambulance channel collapsed by policy design, and the claims date-stamp it. | C38: Dialysis-touching O-D pairs: 2,332,855 transports (2019) to 857,750 (2024), minus 63.2%, against minus 25.6% for the whole O-D coded book. Largest single-year drop, minus 34.2%, lands in 2022, the RSNAT national rollout year. Evaluation: minus 61% use, minus 77% RSNAT spend, quality held except a 19% relative rise in emergency dialysis. | D38: S39, S41, S42 | E38: High | F38: Never read the dialysis collapse as demand loss, and do not let it contaminate the H2H trend, which GREW 2022 to 2024. It is also the template for what payer prior authorization does to any scheduled-transport book.
A39: 27 | B39: Air is the high-acuity interfacility book that ground never was. | C39: Rotary-wing Medicare transports are 65.6% hospital-to-hospital in 2024; rotary HH volume grew 34,856 to 43,683 (2010 to 2024, +25%) while ground HH fell 7%. Fixed-wing is 94.6% transfer-point-to-transfer-point: airport-coded, endpoint-blind. | D39: S40 | E39: High for Medicare FFS carrier claims | F39: Never use ground acuity mix to describe air. Never use fixed-wing O-D modifiers for anything.
A40: 28 | B40: The SNF interface, not the hospital pair, is the largest facility-to-facility channel. | C40: NH plus HN carried 2,398,253 Medicare FFS transports in 2024, 2.75 times the HH book of 871,753, and NH (SNF to hospital) is GROWING at +3.6% per year 2022 to 2024 while HN shrinks. | D40: S39, S13 | E40: High | F40: An interfacility thesis scoped to hospital-to-hospital only ignores the majority of the facility-to-facility dollar. Part A bundling (Finding 15) governs which SNF legs are separately billable.
A41: 29 | B41: Commercial pays multiples of Medicare, and the wedge is measured, not assumed. | C41: Rotary air: commercial allowed $18,668 against Medicare $3,739, same source, same year (2020): 5.0x. Ground ALS-emergency commercial allowed rose 56% in three years ($486 to $758, 2017 to 2020) while Medicare rose 4.8%. State ALS-E allowed spans $836 (IL) to $1,461 (CA) in 2022. | D41: S43, S44, S45 | E41: High within FAIR Health scope (private claim lines; excludes Medicare FFS and Medicaid) | F41: The excluded 2x to 4x assumption (Excluded_Not_Sourced #20) is retired in favor of these published bounds. Never blend payers into one rate.
A42: 30 | B42: The external ambulance-arrival anchor is now 17.0%, carries a standard error, and is frozen forever. | C42: NHAMCS 2022, the final vintage of the survey: ambulance arrival 17.0% (SE 0.9) of 155,398,000 ED visits; 33.4% at 65 and over; 39.6% at 75 and over. NEMSIS 2022 coverage of EMS-to-ED transport (17.5% of NEDS visits) sits inside the 95% interval. | D42: S55, S12, S02 | E42: High | F42: At full participation NEMSIS is not a material undercount of EMS-to-ED transport. The anchor cannot be refreshed: NHAMCS ended with 2022.
A43: 31 | B43: Coordination moves transfer volume on a measured scale, and no local coverage discretion stands in the way. | C43: Statewide transfer coordination centers were associated with an immediate 35% rise in interhospital transfer rates (RR 1.35, 95% CI 1.05 to 1.74) across 441,709 transfers in eight states. The Medicare Coverage Database holds zero active ambulance LCDs; coverage is national regulation. | D43: S54, S56 | E43: Strong, external, pandemic-period | F43: Never treat throughput as fixed: the 287-minute median delay (Finding 22) responds to coordination infrastructure. Never hunt for MAC-level ambulance coverage risk; there is none to find.
A45: Findings 32 to 35, revision 3 (10 July 2026).
A46: # | B46: Finding | C46: The numbers | D46: Sources | E46: Confidence | F46: Interpretation guardrail
A47: 32 | B47: Half the Medicare decline is the denominator, not demand. | C47: A and B fee-for-service enrollment fell 15.5% (32.8M to 27.7M, 2019 to 2024). Per 1,000 beneficiaries, the whole O-D book fell 11.9% (against 25.6% raw) and HH fell 8.0% (against 22.3% raw). The dialysis collapse survives normalization at minus 56.5%. FFS enrollment ROSE in 2025 for the first time in the series. | D47: S39, S60 | E47: High | F47: Never quote a raw PSPS trend as a demand trend. Divide by enrollment first or the comparison should be omitted.
A48: 33 | B48: Interfacility is at least three clinical products wearing one name. | C48: SNF-to-hospital is 94% emergency-coded; hospital-to-SNF is 98% BLS non-emergency; hospital-to-hospital is 62% non-emergency with SCT at 6.6%; dialysis is 96% BLS non-emergency. The HH emergency share rose 2.4 points 2019 to 2024 as payers stripped scheduled volume. | D48: S39 | E48: High | F48: No single staffing model, unit economics, or payer strategy covers the IFT book. Segment by channel and direction or the analysis is wrong on arrival.
A49: 34 | B49: The supplier base is radically fragmented and consolidating slowly. | C49: 8,721 billing NPIs in 2024 (floor; MUP suppression). Largest NPI under 1% of national services; top 10 hold 6.2%; top 100 hold 24.6% (up from 21.9% in 2019). Median NPI bills 279 Medicare transports a year. BLS non-emergency billers fell 12.7%; air billers grew. | D49: S59 | E49: High for the floor; NPI-level only | F49: Never read NPI shares as corporate shares: consolidators bill through many subsidiary NPIs, so these are floors. Corporate roll-up requires the PECOS reassignment graph.
A50: 35 | B50: Medicare ground reimbursement carries a dated statutory cliff: 1 January 2028. | C50: The 2% urban, 3% rural and 22.6% super-rural add-ons lapsed 1 October 2025, were revived through 31 January 2026, lapsed three days, and are now extended through 31 December 2027 by CAA 2026 section 6203. RVUs unchanged since 2002; geographic adjustments since 2008. | D50: S61, S28 | E50: High | F50: No revenue model on a Medicare-heavy ground book may assume the add-ons past 2027 without a scenario. Congress has extended them through lapses, not ahead of them.
A52: Findings 36 to 41, revision 4 (10 July 2026).
A53: # | B53: Finding | C53: The numbers | D53: Sources | E53: Confidence | F53: Interpretation guardrail
A54: 36 | B54: The whitespace grows by arithmetic: the unmeasurable Medicare transport market went from about a third to about three fifths in twelve years. | C54: The share of beneficiaries outside A and B fee-for-service rose from 37% (2013) to 59% (2024), computed directly from the enrollment file, with CBO pointing at 63% by 2034. Every point of migration moves transport volume from the measured book to the unmeasured one. | D54: S60, S51 | E54: Certain (arithmetic on enrollment) | F54: No public-claims trend may be presented as the market trend. The dark share travels with every chart.
A55: 37 | B55: Need per supplier is rising even as measured volume falls. | C55: Medicare beneficiaries per ground billing NPI: 6,814 (2019) to 7,797 (2024), +14.4%. The supplier base fell 6.3% over the decade (9,305 to 8,721) while beneficiaries grew; BLS non-emergency billers fell 19.4%, every year down. FFS beneficiaries per supplier fell 12.5%: the measurable window shrank faster than suppliers exited. | D55: S60, S62 | E55: High, floors throughout | F55: Never read falling FFS volume per supplier as slack; the beneficiary-based ratio is the demand-side truth.
A56: 38 | B56: Ambulance competition is metro-by-metro oligopoly inside national fragmentation. | C56: Nationally the top 10 NPIs hold 6.2% of ground volume. Within single metros the top 3 local billers routinely hold a third to two thirds (MSA_Landscape, floors). Local density, not national scale, is the competitive unit. | D56: S62 | E56: Medium: 22% of volume mapped, top-10 metro ranks robust, lower ranks not | F56: No national-share argument in a local market memo, and no metro-to-metro ratios until the full crosswalk lands.
A57: 39 | B57: The wage-versus-update scissors did NOT cut on the 2019-2024 window. | C57: EMT median wage +16.8% against a compounded AIF of +18.6% (the 2023 update printed 8.7% off the CPI spike). The squeeze is real but lives in the sub-periods (AIF 0.9% and 0.2% in 2020-21 against a repricing labor market), in the unpriced paramedic tier ($58,410 median on 2002 RVUs), and in the AIF productivity haircut in normal-inflation years. | D57: S29, S67, S68 | E57: High | F57: No blanket Medicare-underpays-wages claim. Any version of the claim must state its window and its mechanism. This finding supersedes an initial working hypothesis; the test is recorded on Verification_Log Panel H.
A58: 40 | B58: Supply whitespace is physical, measured, and stated as floors. | C58: 4.5 million people live beyond 25 minutes from an ambulance station across only 41 measured states; 82% of measured counties hold a desert; California alone lost 13,365 crew-hours to ED offload delay beyond 30 minutes in six months, with 19.1% of offloads over standard; 154 rural hospitals closed or converted since 2010, lengthening every remaining transport. | D58: S65, S71, S52, S53 | E58: High as floors | F58: None of these is a trend claim except closures; the desert figure has no second vintage yet.
A59: 41 | B59: The paid EMS workforce is growing, not collapsing. | C59: 260,600 (2019) to 282,900 (2024) paid EMTs and paramedics, +8.6%, with BLS projecting +5% more by 2034 and about 19,000 openings a year, mostly replacement. The workforce story that survives the data is churn, volunteer decline, and composition, not headcount. | D59: S67, S68 | E59: High for paid heads; churn measures pending (P7) | F59: No EMS-workforce-collapse framing on headcount. The volunteer layer (53% of isolated rural agencies) is where fragility is real and measured.

Sheet Charts
A1: Charts
A2: Every series below is a live reference to the sheet that carries the data. Nothing is pasted. Change a source cell and the chart moves. Titles state what the chart is evidence for.
B4: 1. The IFT market is flat, but its share of admissions is not.
B5: Total acute-to-acute transfer episodes (bars, left axis) against IFT as a share of AHA community hospital admissions (line, right axis). The ratio rises mostly because the denominator falls. Source: Acute_IFT_Series.
B29: 2. Transfers migrated out of the inpatient bed and into the ED.
B30: ED-origin episodes (DISP_ED = 2) against inpatient-origin episodes (DISPUNIFORM = 2), 2007 to 2023. The two channels move in opposite directions. Source: Acute_IFT_Series.
B54: 3. The Medicare fee-for-service interfacility book peaked in 2017 and is a quarter smaller.
B55: Carrier-billed hospital-to-hospital ambulance transports, 2010 to 2024, rebuilt from raw CMS claims. The 2022 to 2024 recovery is a trough rebound, not trend. Source: Medicare_IFT_Series.
B79: 4. Realised Medicare rates grew below the statutory update.
B80: Allowed charges per interfacility transport and per loaded mile, 2010 to 2024. Per-transport growth is +1.90% per year against an average Ambulance Inflation Factor of 3.0% over the same window. Source: Medicare_IFT_Series.
B104: 5. Specialty Care Transport is 6.6% of the Medicare interfacility book by volume and 15.6% by revenue.
B105: Price weighting narrows the gap between volume mix and revenue mix. It does not make the book high-acuity. Source: Medicare_PSPS Panel D, 2024.
B129: 6. There is no acuity escalation, and there never was.
B130: Specialty Care Transport share of transports and the volume-weighted RVU of the whole book, 2010 to 2024. Fifteen years, essentially flat. Source: Medicare_IFT_Series.
... B201: MedPAC mean cost per transport by organisation transport-volume quartile, pooled 2022 and 2023, deflated to 2022 dollars. Average RVU per transport falls only 5% across the same range. Source: MedPAC_2026_Mandated Table 6-6.
T202: Mean cost per transport
S203: =MedPAC_2026_Mandated!A25 -> Lowest quartile of transports | T203: =MedPAC_2026_Mandated!D25 -> 2878
S204: =MedPAC_2026_Mandated!A26 -> Second quartile | T204: =MedPAC_2026_Mandated!D26 -> 1934
S205: =MedPAC_2026_Mandated!A27 -> Third quartile | T205: =MedPAC_2026_Mandated!D27 -> 1406
S206: =MedPAC_2026_Mandated!A28 -> Highest quartile | T206: =MedPAC_2026_Mandated!D28 -> 918
B223: 10. Independent community hospitals are the ones disappearing.
B224: Community hospitals in a system against independent community hospitals, AHA survey years 2018, 2023 and 2024. Independents fell 9.0% in six years. Source: Demand_Drivers Panel A.

Sheet Verification_Log
A1: Verification log
A2: The question: was every source actually opened and every extraction actually tested? This log records each verification pass, panel by panel, including the reconciliations that matched to the cent and the working hypotheses that were tested and rejected. The rejected ones stay visible on purpose: an audit trail that only records successes is not an audit trail.
A4: Panel A. Values carried in this workbook, checked against the document that published them.
A5: Evidence layer | B5: Values checked | C5: Matched exactly | D5: Corrections | E5: How it was checked | F5: Primary document opened | G5: Outcome
A6: CMS PSPS ambulance claims | B6: 60 | C6: 60 | D6: 0 | E6: Downloaded 110,568 raw claim-summary rows for 2022-2024 from the CMS data.cms.gov API and re-aggregated every origin-destination pair, every acuity HCPCS and every annual total from scratch. | F6: data.cms.gov/data-api/revision 1/dataset/{uuid}/data, Physician/Supplier Procedure Summary, 2022, 2023 and 2024 | G6: PERFECT. 12 origin-destination pairs across three years, the residual bucket, the annual totals, and all six hospital-to-hospital acuity codes across three years. Every cell matched to the unit.
A7: HCUP NEDS, DISP_ED | B7: 68 | C7: 67 | D7: 1 | E7: Downloaded 20 AHRQ weighted summary statistics PDFs (2007-2023, plus the revised 2007 and 2011 editions) and parsed the DISP_ED frequency table from each. | F7: hcup-us.ahrq.gov/db/nation/neds/stats/NEDS_{year}_MaskedStats_Core_Weighted.PDF | G7: 67 of 68 exact. The workbook correctly uses the REVISED (revision 2) editions for 2007 and 2011, where AHRQ restated transfers by up to 1.24%. The single gap is data year 2023 destination-unknown, and it is a source-mixing issue, not an error. See Cross_Source_Recon.
A8: HCUP NIS, DISPUNIFORM and TRAN_IN | B8: 74 | C8: 73 | D8: 1 | E8: Downloaded 17 AHRQ NIS weighted summary statistics PDFs and parsed DISPUNIFORM, TRAN_IN, TRAN_OUT and I10_BIRTH. | F8: hcup-us.ahrq.gov/db/nation/nis/tools/stats/ | G8: 73 of 74 exact. 2008 through 2023 is flawless. TRAN_OUT = 1 equals DISPUNIFORM = 2 in every single year, confirming it is a relabel and not independent evidence. The one gap: the 2007 NIS total omits 16,542 'discharged alive, destination unknown' records. 2007 is excluded from every trend statistic.
A9: AHA community hospital admissions | B9: 4 | C9: 4 | D9: 0 | E9: Downloaded the AHA Fast Facts PDFs and read the admissions lines directly. | F9: aha.org, Fast Facts on US Hospitals, 2025 and 2026 editions | G9: EXACT. 2023: total 34,426,650, community 32,345,846. 2024: total 35,658,583, community 33,553,725. The 2023 community figure is the denominator in the 2023 IFT ratio.
A10: NEMSIS 2024 interfacility counts | B10: 7 | C10: 7 | D10: 0 | E10: Downloaded the NEMSIS 2024 National EMS Data Report and parsed the eResponse.05 table. | F10: nemsis.org, NEMSIS End-of-Year Report 2024 | G10: EXACT. Total 60,298,684. Hospital-to-Hospital 5,510,664. Other Routine Medical Transport 4,467,204. Hospital to Non-Hospital 1,418,924. Non-Hospital to Non-Hospital 335,432. Non-Hospital to Hospital 247,636. Transports to a hospital ED 27,706,728.
A11: Ambulance Inflation Factor, CY2020-CY2025 | B11: 6 | C11: 5 | D11: 1 | E11: Read the full AIF history table in the CMS Claims Processing Manual. | F11: CMS Pub. 100-04, Ch.15 Sec.20.4, Transmittal 13464 (14 Nov 2025) | G11: CORRECTION. CY2024 is 2.6%, not the 3.0% the source market study carried. All other years match. CY2026 (2.0%) added as new.
A12: Ambulance RVUs, seven ground levels | B12: 7 | C12: 7 | D12: 0 | E12: Read the RVU table in both the CMS public use file description and the MedPAC fact sheet. | F12: CMS Ambulance Fee Schedule public use file; MedPAC Payment Basics (Ambulance), Oct 2024, Table 1 | G12: EXACT on all seven. BLS 1.00, BLS-emergency 1.60, ALS1 1.20, ALS1-emergency 1.90, paramedic intercept 1.75, ALS2 2.75, SCT 3.25. Upgraded from GOV-B to GOV-A.
A13: GADCS cost per transport | B13: 3 | C13: 2 | D13: 1 | E13: Downloaded the 201-page RAND report and read Table 6.1. | F13: RAND Corporation for CMS, GADCS Report: Year 1 and Year 2 Cohort Analysis, 19 Dec 2024 | G13: CORRECTION. Mean $2,673 and government $3,127 confirmed. Private for-profit is $1,788, NOT the $1,778 that circulates in the secondary coverage.
A14: GADCS crew labor share of cost | B14: 1 | C14: 1 | D14: 0 | E14: Read Figure 5.1 and Table 5.1. | F14: Same report | G14: CONFIRMED at 69.4%: labor is $18,869M of the $27.2B aggregated ground ambulance cost base. An earlier draft of this workbook flagged this as an unverifiable conflation. That flag was wrong and has been withdrawn.
A15: Medicare FFS ambulance spend | B15: 1 | C15: 0 | D15: 1 | E15: Read p.1 of the fact sheet, then cross-checked against the raw claims. | F15: MedPAC, Payment Basics: Ambulance Services Payment System, Oct 2024 | G15: CORRECTION. Source workbook said $4.0B for 2023. MedPAC reports $3.9B of program spending in 2022, excluding beneficiary cost sharing. Reconciled against claims: carrier-billed ground NCH payments were $3.72B in 2022; air and institutional claims close the gap.
A16: NEDS 2023 dual-table discrepancy | B16: 2 | C16: 2 | D16: 0 | E16: Downloaded the 2023 NEDS Introduction PDF (published 14 Jan 2026) and located both tables. | F16: hcup-us.ahrq.gov/db/nation/neds/NEDSIntroduction2023.pdf | G16: BOTH FIGURES CONFIRMED AS PRINTED. Table A7 reports 21,049,219 ED admissions and 2,552,895 transfers. Table D3, in the SAME document, reports 20,973,122, matching the Weighted Summary Statistics. Table A7's deltas sum to exactly zero: a reallocation, not a revision.
A17: CMS PSPS, 2010-2021 extension | B17: n/a | C17: n/a | D17: n/a | E17: Pulled every claim row carrying the HH origin-destination modifier for twelve additional data years, using the same API. Pre-2021 files drop the PSPS_ prefix on the amount fields. | F17: data.cms.gov, Physician/Supplier Procedure Summary, 2010 through 2021 | G17: NEW SERIES. No values to check: this evidence did not exist in any source workbook. Produces the fifteen-year Medicare interfacility series on Medicare_IFT_Series. The 2022-2024 overlap reproduces the verified figures exactly.
A18: MedPAC June 2026 mandated report | B18: n/a | C18: n/a | D18: n/a | E18: Downloaded the 325-page June 2026 Report to the Congress and read Chapter 6, including Tables 6-6, 6-10, 6-11 and Recommendation 6. | F18: MedPAC, Report to the Congress, June 2026, Chapter 6, published 15 June 2026 | G18: NEW SOURCE, PUBLISHED AFTER THE SOURCE WORKBOOKS. Supersedes the RAND GADCS unweighted means for operator benchmarking, quantifies the scale effect on cost, and states that GADCS-based revenue-to-cost ratios are not reliable indicators of payment adequacy today.
A19: CMS Timely and Effective Care | B19: n/a | C19: n/a | D19: n/a | E19: Queried the CMS provider-data API for the national, state and hospital files and re-derived every statistic from the returned rows (2,340 hospital records for OP-18d, 1,736 state records). | F19: data.cms.gov/provider-data, datasets isrn-hqyy, apyc-v239, yv7e-xc69 | G19: NEW SOURCE. Provides the only direct national measurement of interfacility transfer delay: OP-18d, median 287 minutes. Not present in any source workbook.
A20: AHA Fast Facts, 2020 edition | B20: n/a | C20: n/a | D20: n/a | E20: Downloaded and read the PDF for the survey-year 2018 baseline. | F20: aha.org, Fast Facts on U.S. Hospitals, 2020 edition | G20: NEW SOURCE. Community hospitals 5,198; in a system 3,491; staffed beds 792,417. Enables the 2018 to 2024 consolidation series.
A21: Peer-reviewed literature (PubMed) | B21: n/a | C21: n/a | D21: n/a | E21: Searched PubMed and retrieved article metadata and abstracts for four studies on interfacility transfer, travel time and ED boarding outcomes. | F21: PubMed. DOIs recorded on Source_Register S35 through S38. | G21: NEW SOURCE. Quantifies travel time as a transfer driver (aOR 1.32) and establishes that the naive dwell-time to mortality correlation runs backwards.
A22: TOTAL | B22: =SUM(B6:B16) -> 233 | C22: =SUM(C6:C16) -> 228 | D22: =SUM(D6:D16) -> 5 | E22: Match rate | F22: =C22/B22 -> 0.97854077 | G22: Five corrections, all applied in this file. Four are real errors in the source workbooks; the fifth is a source-mixing issue on one AHRQ cell.
A24: Panel B. The five corrections, stated plainly.
A25: # | B25: What the source workbook said | C25: What the primary document says | D25: Primary document | E25: Materiality
A26: 1 | B26: CY2024 Ambulance Inflation Factor = 3.0% | C26: CY2024 Ambulance Inflation Factor = 2.6% | D26: CMS Pub 100-04 Ch.15 Sec.20.4 | E26: Moves the trailing three-year average from 4.7% to 2.3%. Material to any rate-growth assumption.
A27: 2 | B27: Medicare FFS ambulance spend = $4.0B in 2023 | C27: $3.9B in 2022, program spending excluding beneficiary cost sharing | D27: MedPAC Payment Basics (Ambulance), Oct 2024, p.1 | E27: Wrong value and wrong year. A separate MedPAC figure of $5.3B for 2023 is TOTAL payments. Confusing the two is a 36% error.
A28: 3 | B28: GADCS private for-profit mean cost per transport = $1,778 | C28: $1,788 | D28: RAND GADCS Year 1 and Year 2 Cohort Analysis, Table 6.1 | E28: Small. But it propagated from secondary coverage into the source workbook, which is the point.
A29: 4 | B29: GADCS mean cost per transport of $2,673, quoted without its median | C29: Mean $2,673, MEDIAN $1,340 | D29: Same report, Table 6.1 | E29: Large. The mean is dragged up by thousands of tiny low-volume organizations. Quoting the mean as the operator benchmark is wrong.
A30: 5 | B30: NIS 2007 total discharges = 39,525,405 | C30: 39,541,947. The workbook omits 16,542 'destination unknown' records | D30: AHRQ NIS 2007 weighted summary statistics | E30: Immaterial. 2007 precedes the 2012 NIS redesign and is excluded from every trend statistic in this workbook.
A31: 6 | B31: This workbook claimed MedPAC's $3.9B and $5.3B ambulance spend figures 'both reconcile against the claims once air and institutional claims are added'. | C31: They do not. Carrier-billed ground plus air program payments were $4.20B in 2022, ABOVE MedPAC's $3.9B. Neither MedPAC document states the scope of its measure. | D31: CMS PSPS, air codes A0430, A0431, A0435, A0436 | E31: Material to anyone sizing the Medicare ambulance market. The claim is withdrawn and replaced with a bounded statement. See Medicare_PSPS Panel G.
A32: Panel C. Evidence obtained during verification that exists in NO source workbook.
A33: Item | B33: Value | C33: Where it came from | D33: Why it matters
A34: CY2024 ground ambulance conversion factor | B34: $272.44 | C34: MedPAC Payment Basics (Ambulance), Table 1 | D34: The source workbook ASSUMED $278.00 and labeled it ILLUSTRATIVE, which is why no dollar figure could survive.
A35: CY2024 ground mileage rate | B35: $8.76 per statute mile | C35: Same | D35: Confirmed independently by the claims: $8.79 allowed per loaded mile.
A36: Allowed charges, hospital-to-hospital base rate, 2024 | B36: $319,815,284 | C36: CMS PSPS, PSPS_ALLOWED_CHARGE_AMT | D36: Real Medicare dollars, not an RVU-times-conversion-factor estimate.
A37: Allowed charges, hospital-to-hospital mileage, 2024 | B37: $257,413,039 | C37: CMS PSPS, HCPCS A0425, modifier HH | D37: Mileage is 44.6% of the revenue on an interfacility transport.
A38: Loaded miles per hospital-to-hospital transport, 2024 | B38: 33.6 | C38: CMS PSPS | D38: Roughly three times a typical 911 scene run.
A39: Medicare payment as a share of allowed | B39: 77.7% | C39: CMS PSPS, PSPS_NCH_PAYMENT_AMT | D39: Statute sets Part B at 80% after the deductible. The realized 77.7% validates the entire extraction.
A40: GADCS median cost per transport | B40: $1,340 | C40: RAND GADCS Table 6.1 | D40: The mean of $2,673 is 1.99x the median. This changes the unit-economics conclusion.
A41: GADCS cost per RVU | B41: $1,624 mean, $811 median | C41: RAND GADCS Table 6.1 | D41: Directly comparable to the $253 per RVU that Medicare allows on the H2H book.
A42: GADCS cost composition | B42: Labor 69.4%, vehicles 10.0%, facilities 3.5% | C42: RAND GADCS Figure 5.1 and Table 5.1 | D42: Replaces the excluded trade-benchmark cost split.
A43: NEDS 2023 sampling structure | B43: 4,489 target EDs; 3,185 frame; 963 sampled | C43: NEDS Introduction 2023, Table A6 | D43: Quantifies the 2023 frame-coverage break.
A45: Panel D. What remains unverifiable, by anyone, at any effort.
A46: AHRQ's discharge weights are calibrated to the AHA Annual Survey Database, which is not public at the hospital level. The weighted counts in NEDS and NIS cannot be reproduced from public data by any external party. They are taken on AHRQ's authority, and everything downstream inherits that.
A47: AHRQ publishes no standard errors in the weighted summary statistics. NEDS clusters on emergency departments, and transfer propensity is a hospital-level attribute, so DISP_ED = 2 carries a large design effect. The +0.86% per year total-episode CAGR is NOT demonstrably different from zero on this evidence. HCUPnet returns design-based standard errors, free and without a data use agreement, and would settle it.
A48: NEMSIS has no sampling frame and no weights. It is a voluntary submission census. No national inference and no confidence interval is licensed from it, only mix and direction.
A49: CMS suppresses any PSPS cell with fewer than 11 services. In 2024, 24,781 origin-destination-coded rows are masked, hiding at most about 263,000 services, or 2.5% of the 10,637,727 counted. Every PSPS figure in this workbook is a floor by that margin.
A50: PSPS is carrier claims only. Hospital-owned ambulance departments bill institutionally and never appear, and Medicare Advantage is entirely absent. The commercial book is not measured by any source in this workbook.
A52: Panel E. The one authoritative source published after this evidence base was assembled.
A53: MedPAC delivered its Bipartisan Budget Act of 2018 mandated report on 15 June 2026: 'Chapter 6: Mandated report: Assessment of the Medicare Ground Ambulance Data Collection System', in the June 2026 Report to the Congress. It assesses the GADCS data and recommends continued but streamlined collection. It is the authoritative source on Medicare payment adequacy for ground ambulance. It is NOT reflected in this workbook. Pull it before any external use.
A55: Reproducibility. PSPS: GET https://data.cms.gov/data-api/revision 1/dataset/{uuid}/data?filter[HCPCS_CD]={code}. Dataset UUIDs: 2022 e4786716-10e9-40f2-b936-7444177474d5, 2023 b72adfb6-22cf-4241-9c64-050ad9061e03, 2024 164fc736-4179-4100-9f79-592b69e41975. Ground base codes A0426, A0427, A0428, A0429, A0433, A0434; ground mileage A0425. Suppressed cells are marked with an asterisk and were excluded from sums, not imputed.
A57: Panel F. Revision 2 verification (10 July 2026): new evidence opened, and the revision 1 extraction independently re-tested.
A58: Evidence layer | B58: What was done | C58: Outcome
A59: CMS PSPS full O-D rebuild (S39, S40) | B59: Pulled 392,409 raw rows across fifteen PSPS datasets (2019-2024 all twelve ambulance HCPCS; 2010-2018 air codes) and re-aggregated every origin-destination pair with dollars. | C59: PERFECT on dollars: 2022-2024 ground totals reproduce Medicare_PSPS Panel F to the cent (allowed 4,753,662,348 / 4,992,692,676 / 5,073,090,003; paid 3,722,057,066 / 3,892,079,508 / 3,957,457,371). HH 2024 base allowed and mileage allowed match to the cent.
A60: Fractional service counts | B60: Compared initial hospital-pair transport counts against float-summed rebuild; isolated the gap. | C60: Correction 7. PSPS SUBMITTED_SERVICE_CNT contains fractional values (8 rows in the 2024 HH base set). The initial pipeline truncated: 871,753 against a float sum of 871,756 (+0.0003%). All revision 2 tabs sum floats. original cells left as printed; immaterial.
A61: PSPS field-name boundary | B61: Tested the 2020 dataset schema directly. | C61: Correction 8, to an earlier reproducibility note. The PSPS_ field prefix begins with DATA YEAR 2020, not 2021 as an earlier note stated. 2010-2019 files carry unprefixed names.
A62: Census NP2023-T2 (S50) | B62: Downloaded and parsed the xlsx from www2.census.gov. | C62: EXACT values carried: 65+ 57,795k (2022), 71,183k (2030), 82,130k (2050), main series.
A63: NHAMCS 2022 Table 4 (S55) | B63: Downloaded the ED Summary Tables PDF and read Table 4. | C63: EXACT: 17.0% (SE 0.9) ambulance arrival on 155,398k visits; age gradient carried. Final survey vintage.
A64: Medicare Coverage Database (S56) | B64: Queried active LCDs and articles titled ambulance via the MCD connector. | C64: Zero active ambulance LCDs; one billing article, A52917 (Noridian Part A, rural air ambulance protocols, eff. 10/01/2015, updated 11/22/2023).
A65: NPPES (S58) | B65: Queried the registry live for ambulance taxonomy organizations. | C65: Taxonomy 341600000X and 3416L0300X confirmed on active records (example NPIs on Code_Crosswalks).
A66: PubMed retrievals (S42, S53, S54) | B66: Retrieved metadata and abstracts for the three studies carried in v2. | C66: PMIDs 35977218, 31989591, 41324958 with digital object identifiers recorded on the Source_Register.
A67: Documents opened (S41, S43-S49, S51, S52) | B67: CMS RSNAT page and press release; FAIR Health white papers and brief; GAPB report; Commonwealth Fund analysis; MACPAC Ch.5; HHS NEMT report; KFF 2026 enrollment brief; Sheps tracker. | C67: Figures carried as printed, with each locator on the Source_Register. The Sheps and Chartis closure counts use different conventions and are both recorded; DQ #31.
A69: Panel G. Revision 3 verification (10 July 2026).
A70: Evidence layer | B70: What was done | C70: Outcome
A71: Medicare Monthly Enrollment (S60) | B71: Pulled national annual-average rows 2013-2025 from the API and carried four enrollment measures. | C71: EXACT values carried; A and B FFS denominator convention stated on the tab. Per-1,000 rates recompute inside the workbook by formula.
A72: MUP-PHY supplier pull (S59) | B72: Pulled every NPI-by-code row for eight ambulance base HCPCS, 2019 and 2024 (44,614 rows), and aggregated counts, concentration and top billers. | C72: Cross-check: MUP 2024 approved ground services 9,542,103 against PSPS submitted 10,637,766: a 1.10x definitional gap (final-action against submitted; suppression), logged as DQ #34.
A73: Acuity by channel (S39) | B73: Re-aggregated the existing PSPS pull by base HCPCS within each O-D channel, 2019 and 2024, six-code convention. | C73: Totals tie to Medicare_OD_Matrix (A0432 intercept excluded, 3,312 services in 2024). Two draft read-notes were corrected against computed values before release (HH per-capita minus 8.0%; HH emergency share +2.4 points).
A74: Add-on statutory status (S61) | B74: Read the CMS AFS page and corroborating notices for the current expiration. | C74: CAA 2026 section 6203: extended through 31 December 2027; cliff 1 January 2028; Oct 2025 lapse history recorded on Payment_Rules.
A76: Panel H. Revision 4 verification (10 July 2026).
A77: Evidence layer | B77: What was done | C77: Outcome
A78: MUP-PHY decade series (S62) | B78: Pulled every NPI-by-code row, six ground base codes, data years 2014-2018 and 2020-2023, plus 2024 city, state and ZIP fields. Dataset identifiers by data year are recorded under source S62. | C78: Eleven-year supplier series on Supplier_Series_Raw. Endpoints reconcile exactly with the revision 3 two-point pull.
A79: Institutional ambulance route (Fault_Audit A) | B79: Probed the Medicare Outpatient Hospitals by Provider and Service PUF with HCPCS filters for all twelve ambulance codes. | C79: Tested and closed: the file is APC-level and the HCPCS filter is silently ignored (identical 116,799-row universe returned for every code). Hospital-billed ambulance remains publicly uncountable; recorded on IFT_Alt_Measures.
A80: OEWS May 2019 (S67) | B80: Read the 29-2040 occupation page: national, industry, state, metro tables. | C80: EXACT values carried. May 2024 taken from the OOH (S68). BLS bulk zips refused scripted access; full state files pending (P4).
A81: Scissors self-correction (Finding 39) | B81: The initial working hypothesis was that wages outran the AIF 2019-2024. Computed: EMT median +16.8% against AIF +18.6%. | C81: Hypothesis rejected on the five-year window and the finding rewritten to the sub-period and composition mechanisms. Rejected hypotheses are retained as part of the audit trail.
A82: California APOT (S71) | B82: Parsed the EMSA December 2024 commission report: statewide trend, LEMSA heat table, cumulative delay hours. | C82: EXACT: 19.1% of offloads over 30 minutes; 13,364:40:19 cumulative hours, Apr-Sep 2024; San Diego alone 738:54:57.
A83: Ambulance deserts (S65) | B83: Verified the national figures on the Rural Health Research Gateway; the full chartbook PDF is pending retrieval. | C83: Headline figures pinned including the nine-missing-states undercount caveat; state and county tables pending (P2).
A84: MSA mapping coverage | B84: Computed the share of national volume the principal-city method assigns to a CBSA. | C84: 21.8%. Printed on MSA_Landscape as the governing caveat; the full ZCTA crosswalk is pending item P3.
A85: Access failures, logged not hidden | B85: Four bulk files could not yet be retrieved programmatically: the BLS OEWS archives, the Census ZCTA relationship file, the NASEMSO assessment, and the deserts chartbook PDF. | C85: Each is named on Fault_Audit item L with its fallback source. Nothing was silently substituted.
A86: State cut cross-validation (S73) | B86: Pulled the official by-Geography state file and reconciled against the NPI-file aggregation. | C86: National gap +1.0% (9,637,009 vs 9,542,103), attributable to NPI-file small-cell suppression: the suppression tail is now BOUNDED, closing part of Fault_Audit item C and DQ #32. Official column carried on State_Saturation.
A87: Final consolidation, 10 July 2026 | B87: Confirmed the distributed copy is byte-identical to this build; recounted the Source_Index tiers programmatically; corrected the stale 61-source title; repaired one gap-table cost cell; refreshed the HCUPnet claims across all tabs after the independent external review. | C87: The master is internally consistent at 43 tabs, 73 sources, facts through F165, findings through 41, zero formula errors. Open items live only on the README pending register (P1-P19).
A88: Chart integrity audit | B88: Every chart series was programmatically resolved to its cell range and counted for numeric content; scale-mismatched two-series charts were rebuilt as dual-axis combinations so percentage series render visibly; all ten original charts received explicit titles. | C88: 29 charts, all series resolving, palette-consistent. Percentage series that previously flatlined against count axes now plot on a right-hand axis.
... A92: National TAM model | B92: Built the three-scenario national model on a fully measured Medicare spine (claims, MedPAC, enrollment, code mix, all green-linked), a residual-based payer-lives panel (S77), a nine-row assumption register with owners and replacement paths, four gates, and a driver-tree CAGR to 2030. The base case was sanity-gated against the MedPAC published spend to about 1.0x by construction. | C92: Outputs live on TAM_Model_National Panel A; Fault_Audit item T governs quotation.

Sheet Fact_Ledger
A1: Fact ledger
A2: The question: where does each number come from? Every fact in this workbook carries an ID here (F01 to F165) with its metric, year, value, evidence tier, source, and the exact locator inside the source document. This is step two of the three-step audit path described on the README.
A4: Fact ID | B4: Metric | C4: Year | D4: Value | E4: Unit | F4: Basis | G4: Tier | H4: Source ID | I4: Locator | J4: Lives on | K4: Cross-check
A5: F01 | B5: ED-origin acute-to-acute transfer episodes | C5: 2022 | D5: =Acute_IFT_Series!B20 -> 2311549 | E5: episodes | F5: GOV-A | G5: A | H5: S01 | I5: NEDS Summary Stats, DISP_ED = 2 | J5: Acute_IFT_Series | K5: VERIFIED against the AHRQ PDF. Agrees to the unit with NEDS Introduction 2022 Table A6
A6: F02 | B6: ED-origin acute-to-acute transfer episodes | C6: 2023 | D6: =Acute_IFT_Series!B21 -> 2554379 | E6: episodes | F6: GOV-A | G6: A | H6: S01 | I6: NEDS Summary Stats, DISP_ED = 2 | J6: Acute_IFT_Series | K6: VERIFIED. NEDS Introduction 2023 Table A7 prints 2,552,895. Gap of 1,484 (0.058%). See Cross_Source_Recon
A7: F03 | B7: Inpatient-origin acute-to-acute transfer episodes | C7: 2022 | D7: =Acute_IFT_Series!C20 -> 617724 | E7: episodes | F7: GOV-A | G7: A | H7: S04 | I7: NIS Summary Stats, DISPUNIFORM = 2 | J7: Acute_IFT_Series | K7: VERIFIED. TRAN_OUT = 1 equals this value in every year 2007-2023: a relabel, not independent evidence
A8: F04 | B8: Inpatient-origin acute-to-acute transfer episodes | C8: 2023 | D8: =Acute_IFT_Series!C21 -> 630765 | E8: episodes | F8: GOV-A | G8: A | H8: S04 | I8: NIS Summary Stats, DISPUNIFORM = 2 | J8: Acute_IFT_Series | K8: VERIFIED against the AHRQ PDF
A9: F05 | B9: Total acute-to-acute transfer episodes | C9: 2022 | D9: =Acute_IFT_Series!D20 -> 2929273 | E9: episodes | F9: DERIVED | G9: A | H9: S01, S04 | I9: Sum of F01 and F03 | J9: Acute_IFT_Series | K9: No overlap: an ED transfer-out is never also an inpatient discharge
A10: F06 | B10: Total acute-to-acute transfer episodes | C10: 2023 | D10: =Acute_IFT_Series!D21 -> 3185144 | E10: episodes | F10: DERIVED | G10: A | H10: S01, S04 | I10: Sum of F02 and F04 | J10: Acute_IFT_Series | K10: Memo year. NEDS break in series
A11: F07 | B11: Mean acute-to-acute transfer episodes, 2019 to 2023 | C11: 2023 | D11: =AVERAGE(Acute_IFT_Series!D17:D21) -> 3061155.8 | E11: episodes/yr | F11: DERIVED | G11: A | H11: S01, S04 | I11: Five-year mean | J11: Acute_IFT_Series | K11: Sample standard deviation 139,226. Range 2,929,273 (2022) to 3,234,266 (2019)
A12: F08 | B12: IFT as % of AHA community hospital admissions | C12: 2022 | D12: =Acute_IFT_Series!F20 -> 0.092828334 | E12: % | F12: DERIVED | G12: A | H12: S01, S04, S09 | I12: F05 over F18 | J12: Acute_IFT_Series | K12: Denominator choice moves this by 1.05 points. See Receiving_Side
A13: F09 | B13: IFT as % of AHA community hospital admissions | C13: 2023 | D13: =Acute_IFT_Series!F21 -> 0.098471501 | E13: % | F13: DERIVED | G13: A | H13: S01, S04, S10 | I13: F06 over 32,345,846 | J13: Acute_IFT_Series | K13: Memo year. Denominator verified in AHA Fast Facts 2025 edition
A14: F10 | B14: Mean IFT % of admissions, 2019 to 2023 | C14: 2023 | D14: =AVERAGE(Acute_IFT_Series!F17:F21) -> 0.094854988 | E14: % | F14: DERIVED | G14: A | H14: S01, S04, S06-S10 | I14: Five-year mean | J14: Acute_IFT_Series | K14: Band 9.24% (2021) to 9.85% (2023). Sample standard deviation 0.24 points
A15: F11 | B15: ED-origin share of acute-to-acute episodes | C15: 2012 | D15: =Acute_IFT_Series!G10 -> 0.74368192 | E15: % | F15: DERIVED | G15: A | H15: S01, S04 | J15: Acute_IFT_Series | K15: First comparable year after the 2012 NIS redesign
A16: F12 | B16: ED-origin share of acute-to-acute episodes | C16: 2022 | D16: =Acute_IFT_Series!G20 -> 0.78912037 | E16: % | F16: DERIVED | G16: A | H16: S01, S04 | J16: Acute_IFT_Series | K16: Rises 4.5 points over ten years
A17: F13 | B17: ED-origin share of acute-to-acute episodes | C17: 2023 | D17: =Acute_IFT_Series!G21 -> 0.80196657 | E17: % | F17: DERIVED | G17: A | H17: S01, S04 | J17: Acute_IFT_Series | K17: The clearest structural trend in the data
A18: F14 | B18: ED-origin episode CAGR, 2012 to 2023 | C18: 2023 | D18: =(Acute_IFT_Series!B21/Acute_IFT_Series!B10)^(1/11)-1 -> 0.015507851 | E18: %/yr | F18: DERIVED | G18: A | H18: S01 | I18: 11 compounding years | J18: Acute_IFT_Series | K18: 2012 is the first comparable year (NIS redesign)
A19: F15 | B19: Inpatient-origin episode CAGR, 2012 to 2023 | C19: 2023 | D19: =(Acute_IFT_Series!C21/Acute_IFT_Series!C10)^(1/11)-1 -> -0.014812798 | E19: %/yr | F19: DERIVED | G19: A | H19: S04 | J19: Acute_IFT_Series | K19: Negative. The inpatient channel is in structural decline
A20: F16 | B20: Total acute-to-acute episode CAGR, 2012 to 2023 | C20: 2023 | D20: =(Acute_IFT_Series!D21/Acute_IFT_Series!D10)^(1/11)-1 -> 0.0085659028 | E20: %/yr | F20: DERIVED | G20: A | H20: S01, S04 | J20: Acute_IFT_Series | K20: The measured market volume growth rate. NOT demonstrably different from zero: AHRQ publishes no standard errors
A21: F17 | B21: AHA community hospital admission CAGR, 2012 to 2023 | C21: 2023 | D21: =(Acute_IFT_Series!E21/Acute_IFT_Series!E10)^(1/11)-1 -> -0.0067009383 | E21: %/yr | F21: DERIVED | G21: A | H21: S05-S10 | J21: Acute_IFT_Series | K21: Negative. IFT grows as the denominator shrinks. This one is a hospital census, so it is real
A22: F18 | B22: AHA community hospital inpatient admissions | C22: 2022 | D22: =Acute_IFT_Series!E20 -> 31555807 | E22: admissions | F22: GOV-A | G22: A | H22: S09 | I22: Fast Facts, 2024 edition | J22: Acute_IFT_Series | K22: Identical in both uploaded AHA workbooks
A23: F19 | B23: AHA community hospital inpatient admissions | C23: 2024 | D23: =Cost_and_Capacity!C50 -> 33553725 | E23: admissions | F23: GOV-A | G23: A | H23: S11 | I23: Fast Facts, 2026 edition | J23: Cost_and_Capacity | K23: VERIFIED against the AHA PDF: 33,553,725. No NEDS 2024 file yet, so no 2024 ratio
A24: F20 | B24: Total admissions, all US hospitals | C24: 2024 | D24: =Cost_and_Capacity!B50 -> 35658583 | E24: admissions | F24: GOV-A | G24: A | H24: S11 | I24: Fast Facts, 2026 edition | J24: Cost_and_Capacity | K24: VERIFIED: 35,658,583. Still 1.9% below the 2018 peak of 36,353,946
A25: F21 | B25: Receiving-side transfer admissions (NIS TRAN_IN = 1) | C25: 2022 | D25: =Receiving_Side!C15 -> 2205490 | E25: admissions | F25: GOV-A | G25: A | H25: S04 | I25: NIS Summary Stats, TRAN_IN = 1 | J25: Receiving_Side | K25: VERIFIED. Derived from UB-04 Point of Origin, independent of the sending-side field
A26: F22 | B26: Receiving-side transfer admissions (NIS TRAN_IN = 1) | C26: 2023 | D26: =Receiving_Side!C16 -> 2463771 | E26: admissions | F26: GOV-A | G26: A | H26: S04 | I26: NIS Summary Stats, TRAN_IN = 1 | J26: Receiving_Side | K26: VERIFIED against the AHRQ PDF
A27: F23 | B27: Sending-to-receiving conversion rate | C27: 2022 | D27: =Receiving_Side!D15 -> 0.75291378 | E27: % | F27: DERIVED | G27: A | H27: S01, S04 | I27: F21 over F05 | J27: Receiving_Side | K27: Residual goes to psych, rehab, LTACH, ED treat-and-release, or observation
A28: F24 | B28: Sending-to-receiving conversion rate | C28: 2023 | D28: =Receiving_Side!D16 -> 0.7735195 | E28: % | F28: DERIVED | G28: A | H28: S01, S04 | J28: Receiving_Side
A29: F25 | B29: NEMSIS total EMS activations | C29: 2024 | D29: =EMS_Transports!G6 -> 60298684 | E29: activations | F29: GOV-A | G29: A | H29: S12 | I29: 2024 report, eResponse.05 table | J29: EMS_Transports | K29: VERIFIED against the NEMSIS PDF: 60,298,684. Cover box ties exactly only in 2024
A30: F26 | B30: NEMSIS Hospital-to-Hospital Transfer activations | C30: 2024 | D30: =EMS_Transports!B27 -> 5510664 | E30: transports | F30: GOV-A | G30: A | H30: S12 | I30: 2024 report, eResponse.05, v3.5 | J30: EMS_Transports | K30: VERIFIED: 5,510,664. Includes psych, rehab and LTACH destinations plus return legs. Not the HCUP definition
A31: F27 | B31: NEMSIS all facility-to-facility transfer activations | C31: 2024 | D31: =EMS_Transports!B49 -> 7512656 | E31: transports | F31: DERIVED | G31: A | H31: S12 | I31: Four v3.5 transfer categories | J31: EMS_Transports | K31: All four components verified. Excludes Other Routine Medical Transport
A32: F28 | B32: NEMSIS Other Routine Medical Transport activations | C32: 2024 | D32: =EMS_Transports!B28 -> 4467204 | E32: transports | F32: GOV-A | G32: A | H32: S12 | I32: 2024 report, eResponse.05 | J32: EMS_Transports | K32: VERIFIED: 4,467,204. Dialysis, appointments, return home. NOT interfacility transfer
A33: F29 | B33: NEMSIS Interfacility Transport activations (v3.4) | C33: 2019 | D33: =EMS_Transports!B17 -> 3309316 | E33: activations | F33: GOV-A | G33: B | H33: S12 | I33: 2019 report, eResponse.05, v3.4 | J33: EMS_Transports | K33: Coverage was 47 states. Not comparable to 2024
A34: F30 | B34: NEMSIS Interfacility Transport activations (v3.4) | C34: 2023 | D34: =EMS_Transports!F17 -> 4179580 | E34: activations | F34: GOV-A | G34: B | H34: S12 | I34: 2023 report, eResponse.05, v3.4 | J34: EMS_Transports | K34: 2023 NEMSIS denominator is understated. See Data_Quality_Register
A35: F31 | B35: NEMSIS transports to a hospital ED | C35: 2022 | D35: =EMS_Transports!E56 -> 24016095 | E35: transports | F35: GOV-A | G35: B | H35: S12 | I35: 2022 report, eDisposition.21 | J35: EMS_Transports | K35: 17.5% of NEDS weighted ED visits, against the NHAMCS anchor of 16.2%
A36: F32 | B36: NEDS weighted national ED visits | C36: 2022 | D36: =EMS_Transports!C75 -> 136974618 | E36: visits | F36: GOV-A | G36: A | H36: S02 | I36: NEDS Introduction 2022, Table 1 | J36: EMS_Transports | K36: AHA Annual Survey reports the identical figure; it is the NEDS control total
A37: F33 | B37: NEDS weighted national ED visits | C37: 2023 | D37: =EMS_Transports!C76 -> 142193558 | E37: visits | F37: GOV-A | G37: A | H37: S03 | I37: NEDS Introduction 2023, Table A6 | J37: EMS_Transports | K37: VERIFIED: 142,193,558. The nine DISP_ED categories sum to this exactly
A38: F34 | B38: NHAMCS ambulance-arrival share of ED visits | C38: 2016 | D38: =EMS_Transports!D78 -> 0.1615143 | E38: % | F38: DERIVED | G38: B | H38: S25 | I38: NHAMCS 2016 ED Summary Tables, Table 5 | J38: EMS_Transports | K38: The only external anchor. NEDS carries no arrival-mode element
A39: F35 | B39: Medicare FFS hospital-to-hospital ambulance transports | C39: 2022 | D39: =Medicare_PSPS!C10 -> 825178 | E39: transports | F39: GOV-A | G39: A | H39: S13 | I39: PSPS 2022, modifier HH | J39: Medicare_PSPS | K39: REBUILT from raw CMS claims and matched to the unit. Carrier claims only
A40: F36 | B40: Medicare FFS hospital-to-hospital ambulance transports | C40: 2024 | D40: =Medicare_PSPS!E10 -> 871753 | E40: transports | F40: GOV-A | G40: A | H40: S13 | I40: PSPS 2024, modifier HH | J40: Medicare_PSPS | K40: REBUILT from raw CMS claims and matched to the unit
A41: F37 | B41: Medicare FFS hospital-to-hospital transport CAGR, 2022 to 2024 | C41: 2024 | D41: =Medicare_PSPS!B39 -> 0.027833823 | E41: %/yr | F41: DERIVED | G41: A | H41: S13 | J41: Medicare_PSPS | K41: Positive while total FFS ambulance volume is negative
A42: F38 | B42: All Medicare FFS ambulance transport CAGR, 2022 to 2024 | C42: 2024 | D42: =Medicare_PSPS!B40 -> -0.027980984 | E42: %/yr | F42: DERIVED | G42: A | H42: S13 | J42: Medicare_PSPS | K42: Enrollment shift to Medicare Advantage
A43: F39 | B43: Non-emergency BLS and ALS1 share of Medicare H2H transports | C43: 2024 | D43: =Medicare_PSPS!B34 -> 0.62335891 | E43: % | F43: DERIVED | G43: A | H43: S13 | I43: A0428 + A0426 over total | J43: Medicare_PSPS | K43: Contradicts the excluded 56.4% high-acuity assumption
A44: F40 | B44: Specialty Care Transport share of Medicare H2H transports | C44: 2024 | D44: =Medicare_PSPS!B35 -> 0.066424779 | E44: % | F44: DERIVED | G44: A | H44: S13 | I44: A0434 over total | J44: Medicare_PSPS | K44: 6.6% of transports. See F60 for the share of allowed dollars
A45: F41 | B45: ALS2 share of Medicare H2H transports | C45: 2024 | D45: =Medicare_PSPS!B36 -> 0.006827622 | E45: % | F45: DERIVED | G45: A | H45: S13 | I45: A0433 over total | J45: Medicare_PSPS | K45: The only H2H acuity tier declining in absolute volume
A46: F42 | B46: Emergent share of Medicare H2H transports | C46: 2024 | D46: =Medicare_PSPS!B37 -> 0.30338869 | E46: % | F46: DERIVED | G46: A | H46: S13 | I46: A0427 + A0429 over total | J46: Medicare_PSPS | K46: Fastest-growing acuity tiers, still under a third of volume
A47: F43 | B47: Volume-weighted RVU of the Medicare H2H book | C47: 2024 | D47: =Medicare_PSPS!B38 -> 1.449965 | E47: RVU | F47: DERIVED | G47: A | H47: S13, S14 | I47: SUMPRODUCT of RVU and volume | J47: Medicare_PSPS | K47: The book prices at 1.45 BLS runs, not 3.25
A48: F44 | B48: Ambulance Inflation Factor, latest (CY2026) | C48: 2026 | D48: =Payment_Rules!B23 -> 0.02 | E48: %/yr | F48: GOV-A | G48: A | H48: S29 | I48: CMS Pub 100-04, Ch.15 Sec.20.4, Transmittal 13464 | J48: Payment_Rules | K48: VERIFIED 09 Jul 2026 against the CMS manual
A49: F45 | B49: Ambulance Inflation Factor, trailing 3-year average (2024 to 2026) | C49: 2026 | D49: =Payment_Rules!B24 -> 0.023333333 | E49: %/yr | F49: DERIVED | G49: A | H49: S29 | J49: Payment_Rules | K49: Source workbook had CY2024 at 3.0%. Actual is 2.6%. Corrected
A50: F46 | B50: Ambulance Inflation Factor, 2020 to 2026 average | C50: 2026 | D50: =Payment_Rules!B25 -> 0.031285714 | E50: %/yr | F50: DERIVED | G50: A | H50: S29 | J50: Payment_Rules | K50: Sample standard deviation 2.9 points. The AIF is volatile
A51: F47 | B51: Specialty Care Transport RVU (A0434) | C51: 2026 | D51: =Payment_Rules!C12 -> 3.25 | E51: RVU | F51: GOV-A | G51: A | H51: S14, S28 | I51: CMS AFS public use file; MedPAC Table 1 | J51: Payment_Rules | K51: VERIFIED. 3.25 times the BLS base of 1.00. All seven ground RVUs matched
A52: F48 | B52: Mean ground ambulance cost per transport, all-in | C52: 2024 | D52: =Cost_and_Capacity!B6 -> 2673 | E52: $/transport | F52: GOV-A | G52: A | H52: S30 | I52: GADCS Table 6.1, all NPIs, N = 5,000 | J52: Cost_and_Capacity | K52: VERIFIED. The MEDIAN is $1,340 (F73) and is the number to quote for a scaled operator
A53: F49 | B53: Mean cost per transport, private for-profit | C53: 2024 | D53: =Cost_and_Capacity!B7 -> 1788 | E53: $/transport | F53: GOV-A | G53: A | H53: S30 | I53: GADCS Table 6.1 | J53: Cost_and_Capacity | K53: CORRECTED to $1,788. The $1,778 in circulation is a secondary-source transcription error
A54: F50 | B54: Crew labor share of aggregated ground ambulance cost | C54: 2024 | D54: =Cost_and_Capacity!B10 -> 0.694 | E54: % | F54: GOV-A | G54: A | H54: S30 | I54: GADCS Figure 5.1 and Table 5.1 | J54: Cost_and_Capacity | K54: VERIFIED at 69.4%: $18,869M of $27.2B. Distinct from the 70% labor-related portion of the base payment
A55: F51 | B55: Crew labor share of cost, for-profit organizations | C55: 2024 | D55: =Cost_and_Capacity!B11 -> 0.605 | E55: % | F55: GOV-A | G55: A | H55: S30 | I55: GADCS Table 5.1 | J55: Cost_and_Capacity | K55: Government-owned run 73.6%. Ownership drives the cost structure
A56: F52 | B56: National hospital inpatient occupancy | C56: 2022 | D56: =Cost_and_Capacity!B17 -> 0.654927 | E56: % | F56: SOURCED | G56: C | H56: S23 | I56: HCRIS 2552-10, 5,888 filers | J56: Cost_and_Capacity | K56: Analyst computation on a vendored CMS panel, not a published figure. Not externally verifiable
A57: F53 | B57: Inpatient occupancy change, FY2020 to FY2022 | C57: 2022 | D57: =Cost_and_Capacity!B18 -> 3.4204 | E57: pp | F57: DERIVED | G57: C | H57: S23 | J57: Cost_and_Capacity | K57: A lagging throughput proxy, not a transfer count
A58: F54 | B58: Total certified post-acute destinations | C58: 2024 | D58: =Cost_and_Capacity!B40 -> 35481 | E58: providers | F58: SOURCED | G58: C | H58: S24 | I58: CMS provider rolls | J58: Cost_and_Capacity | K58: SNF 14,699; HHA 12,392; hospice 6,852; IRF 1,221; LTACH 317
A59: F55 | B59: ICD-10-CM codes in the clinical spine validated as real | C59: 2026 | D59: 92 | E59: codes | F59: SOURCED | G59: B | H59: S27 | I59: NLM Clinical Tables | J59: Clinical_Volumes_TierC | K59: A coding-integrity check. It validates no volume figure
A60: F56 | B60: CY2024 ground ambulance conversion factor | C60: 2024 | D60: =Payment_Rules!B32 -> 272.44 | E60: $/RVU | F60: GOV-A | G60: A | H60: S28 | I60: MedPAC Payment Basics (Ambulance), Oct 2024, Table 1 | J60: Payment_Rules | K60: VERIFIED. The source workbook assumed $278.00 and labeled it ILLUSTRATIVE
A61: F57 | B61: CY2024 ground mileage rate | C61: 2024 | D61: =Payment_Rules!B33 -> 8.76 | E61: $/statute mile | F61: GOV-A | G61: A | H61: S28 | I61: MedPAC Payment Basics (Ambulance), Oct 2024 | J61: Payment_Rules | K61: Corroborated by the claims: $8.79 allowed per loaded mile (F69)
A62: F58 | B62: Base-rate allowed charges, Medicare FFS hospital-to-hospital | C62: 2024 | D62: =Medicare_PSPS!D58 -> 3.1981528e+08 | E62: $ | F62: GOV-A | G62: A | H62: S13 | I62: PSPS 2024, PSPS_ALLOWED_CHARGE_AMT, modifier HH | J62: Medicare_PSPS | K62: Pulled from the CMS claims API. Not present in any source workbook
A63: F59 | B63: TOTAL allowed charges (base + mileage), Medicare FFS hospital-to-hospital | C63: 2024 | D63: =Medicare_PSPS!D61 -> 5.7722832e+08 | E63: $ | F63: DERIVED | G63: A | H63: S13 | I63: Base rate plus A0425 mileage | J63: Medicare_PSPS | K63: $577.2M in 2024. The only assumption-free dollar figure in this workbook
A64: F60 | B64: Specialty Care Transport share of H2H base-rate ALLOWED DOLLARS | C64: 2024 | D64: =Medicare_PSPS!H50 -> 0.15589572 | E64: % | F64: DERIVED | G64: A | H64: S13 | I64: A0434 allowed over total allowed | J64: Medicare_PSPS | K64: 6.6% of transports, 15.6% of base-rate allowed dollars. Price weighting narrows the gap, it does not close it
A65: F61 | B65: Ambulance Inflation Factor, CY2026 | C65: 2026 | D65: =Payment_Rules!B22 -> 0.02 | E65: %/yr | F65: GOV-A | G65: A | H65: S29 | I65: Transmittal 13464, 14 Nov 2025 | J65: Payment_Rules | K65: CPI-U 2.7% less a total factor productivity adjustment of 0.7%
A66: F62 | B66: Non-emergency BLS ESRD dialysis payment reduction | C66: 2024 | D66: 0.23 | E66: % | F66: GOV-A | G66: A | H66: S28 | I66: MedPAC Payment Basics (Ambulance), Oct 2024 | J66: Payment_Rules | K66: Applies to the RJ, JR, NJ and JN modifier volumes on Medicare_PSPS Panel A, not to HH
A67: F63 | B67: Transfers to another facility type, ED plus inpatient origin | C67: 2022 | D67: =Other_Transfer_Channels!B24 -> 6509053 | E67: legs | F67: DERIVED | G67: A | H67: S01, S04 | I67: DISP_ED = 5 plus DISPUNIFORM = 5 | J67: Other_Transfer_Channels | K67: 2.2 times the acute-to-acute count. Not all move by ambulance
A68: F64 | B68: Total transfers out, all destinations | C68: 2022 | D68: =Other_Transfer_Channels!B25 -> 9438326 | E68: legs | F68: DERIVED | G68: A | H68: S01, S04 | J68: Other_Transfer_Channels | K68: The widest sending-side count HCUP supports
A69: F65 | B69: ED-originated share of all community hospital admissions | C69: 2022 | D69: =Other_Transfer_Channels!B27 -> 0.63479441 | E69: % | F69: DERIVED | G69: A | H69: S01, S05-S09 | I69: DISP_ED = 9 over AHA admissions | J69: Other_Transfer_Channels | K69: 52.9% in 2007 rising to 63.5% in 2022. Confirms NEDS and AHA describe the same hospital universe
A70: F66 | B70: Allowed charges per Medicare FFS hospital-to-hospital transport | C70: 2024 | D70: =Medicare_PSPS!D62 -> 662.14664 | E70: $/transport | F70: DERIVED | G70: A | H70: S13 | I70: Total allowed over transports | J70: Medicare_PSPS | K70: $662.15, against a GADCS median cost per transport of $1,340
A71: F67 | B71: Ground mileage allowed charges, hospital-to-hospital | C71: 2024 | D71: =Medicare_PSPS!D59 -> 2.5741304e+08 | E71: $ | F71: GOV-A | G71: A | H71: S13 | I71: PSPS 2024, HCPCS A0425, modifier HH | J71: Medicare_PSPS | K71: 44.6% of total allowed dollars on the book
A72: F68 | B72: Loaded miles per hospital-to-hospital transport | C72: 2024 | D72: =Medicare_PSPS!D63 -> 33.583723 | E72: miles | F72: DERIVED | G72: A | H72: S13 | I72: Mileage units over transports | J72: Medicare_PSPS | K72: 33.6 miles. Roughly three times a typical 911 scene run
A73: F69 | B73: Allowed per loaded mile | C73: 2024 | D73: =Medicare_PSPS!D64 -> 8.7924166 | E73: $/mile | F73: DERIVED | G73: A | H73: S13 | I73: Mileage allowed over mileage units | J73: Medicare_PSPS | K73: $8.79, against the published CY2024 rate of $8.76. Independent confirmation of both
A74: F70 | B74: Total Medicare FFS carrier-billed ground ambulance allowed charges | C74: 2024 | D74: =Medicare_PSPS!D70 -> 5073090003 | E74: $ | F74: GOV-A | G74: A | H74: S13 | I74: PSPS 2024, six base codes plus A0425, all modifiers | J74: Medicare_PSPS | K74: Reconciles with MedPAC's $5.3B (2023) once air and institutional claims are added
A75: F71 | B75: Total Medicare FFS carrier-billed ground ambulance payments (NCH) | C75: 2024 | D75: =Medicare_PSPS!D71 -> 3957457371 | E75: $ | F75: GOV-A | G75: A | H75: S13 | I75: PSPS 2024, PSPS_NCH_PAYMENT_AMT | J75: Medicare_PSPS | K75: The 2022 value of $3.72B reconciles with MedPAC's $3.9B program spending
A76: F72 | B76: Hospital-to-hospital share of all Medicare carrier ground ambulance dollars | C76: 2024 | D76: =Medicare_PSPS!D72 -> 0.11378239 | E76: % | F76: DERIVED | G76: A | H76: S13 | J76: Medicare_PSPS | K76: Dollar share (11.4%) exceeds volume share (8.2%): interfacility runs are longer and higher acuity
A77: F73 | B77: GADCS median total cost per ground ambulance transport | C77: 2024 | D77: =Cost_and_Capacity!C61 -> 1340 | E77: $/transport | F77: GOV-A | G77: A | H77: S30 | I77: GADCS Table 6.1 | J77: Cost_and_Capacity | K77: The mean of $2,673 is 1.99x the median. Quote the median for a scaled platform
A78: F74 | B78: GADCS median total cost per RVU | C78: 2024 | D78: =Cost_and_Capacity!C63 -> 811 | E78: $/RVU | F78: GOV-A | G78: A | H78: S30 | I78: GADCS Table 6.1 | J78: Cost_and_Capacity | K78: Mean $1,624. Medicare allowed is about $253 per RVU on the H2H book
A79: F75 | B79: GADCS mean cost per transport, very high Medicare volume | C79: 2024 | D79: =Cost_and_Capacity!B65 -> 946 | E79: $/transport | F79: GOV-A | G79: A | H79: S30 | I79: GADCS Table 6.1 | J79: Cost_and_Capacity | K79: $946 against $3,652 for low-volume organizations. Scale is the entire story
A80: F76 | B80: Medicare FFS ambulance program spending, excl. beneficiary cost sharing | C80: 2022 | D80: 3900000000 | E80: $ | F80: GOV-A | G80: A | H80: S28 | I80: MedPAC Payment Basics (Ambulance), Oct 2024, p.1 | J80: Payment_Rules | K80: CORRECTED. Source workbook said $4.0B for 2023. About 1% of FFS spend; about 13% of FFS beneficiaries used an ambulance. ALL ambulance, not IFT
A81: F77 | B81: Medicare FFS ambulance total payments | C81: 2023 | D81: 5300000000 | E81: $ | F81: GOV-B | G81: B | H81: S28 | I81: MedPAC ambulance session, Mar 2025 | J81: Payment_Rules | K81: Total payments INCLUDING beneficiary cost sharing, across 11.4M transports and about 10,500 organizations. Not the same measure as F76
A82: F78 | B82: NEDS target universe, hospital-owned EDs | C82: 2023 | D82: 4489 | E82: EDs | F82: GOV-A | G82: A | H82: S03 | I82: NEDS Introduction 2023, Table A6 | J82: Data_Quality_Register | K82: Sampling frame 3,185 EDs and 101,915,572 visits; the 2023 sample is 963 EDs and 31,003,348 visits
A83: F79 | B83: Medicare FFS hospital-to-hospital transports, peak year | C83: 2017 | D83: =Medicare_IFT_Series!B12 -> 1139524 | E83: transports | F83: GOV-A | G83: A | H83: S32 | I83: PSPS 2017, modifier HH | J83: Medicare_IFT_Series | K83: 1,139,524. Every year since has been lower
A84: F80 | B84: Medicare FFS hospital-to-hospital transports | C84: 2010 | D84: =Medicare_IFT_Series!B5 -> 937317 | E84: transports | F84: GOV-A | G84: A | H84: S32 | I84: PSPS 2010, modifier HH | J84: Medicare_IFT_Series | K84: Start of the fifteen-year series
A85: F81 | B85: Transport CAGR, 2010 to 2017 | C85: 2017 | D85: =Medicare_IFT_Series!B25 -> 0.028299368 | E85: %/yr | F85: DERIVED | G85: A | H85: S32 | J85: Medicare_IFT_Series | K85: Real pre-COVID growth
A86: F82 | B86: Transport CAGR, 2017 to 2024 | C86: 2024 | D86: =Medicare_IFT_Series!B26 -> -0.037542802 | E86: %/yr | F86: DERIVED | G86: A | H86: S32 | J86: Medicare_IFT_Series | K86: The reversal. Medicare Advantage enrolment is the dominant driver
A87: F83 | B87: Transports 2024 against the 2017 peak | C87: 2024 | D87: =Medicare_IFT_Series!B24 -> -0.23498496 | E87: % | F87: DERIVED | G87: A | H87: S32 | J87: Medicare_IFT_Series | K87: The Medicare FFS interfacility book is 23.5% smaller than at peak
A88: F84 | B88: Total allowed CAGR, 2010 to 2024 | C88: 2024 | D88: =Medicare_IFT_Series!B28 -> 0.01375837 | E88: %/yr | F88: DERIVED | G88: A | H88: S32 | J88: Medicare_IFT_Series | K88: Dollars grew while transports shrank
A89: F85 | B89: Allowed per transport CAGR, 2010 to 2024 | C89: 2024 | D89: =Medicare_IFT_Series!B30 -> 0.019022929 | E89: %/yr | F89: DERIVED | G89: A | H89: S32 | J89: Medicare_IFT_Series | K89: Below the 3.0% average AIF over the same window. Realised rate growth lags the statutory update
A90: F86 | B90: Volume-weighted RVU of the H2H book | C90: 2010 | D90: =Medicare_IFT_Series!B34 -> 1.4719377 | E90: RVU | F90: DERIVED | G90: A | H90: S32, S14 | J90: Medicare_IFT_Series | K90: 1.472. Compare 1.450 in 2024: a 1.5% move in fifteen years
A91: F87 | B91: Mileage share of allowed dollars | C91: 2010 | D91: =Medicare_IFT_Series!B32 -> 0.4304602 | E91: % | F91: DERIVED | G91: A | H91: S32 | J91: Medicare_IFT_Series | K91: 43.0%, against 44.6% in 2024. Stable for fifteen years
A92: F88 | B92: Medicare FFS ambulance transports, all types | C92: 2024 | D92: 11300000 | E92: transports | F92: GOV-A | G92: A | H92: S31 | I92: MedPAC June 2026, Ch.6 | J92: MedPAC_2026_Mandated | K92: Carrier-billed claims account for about 10.76M, or 95%. The residual is institutionally billed ambulance
A93: F89 | B93: Total Medicare payments, AFS-covered transports | C93: 2024 | D93: 5300000000 | E93: $ | F93: GOV-A | G93: A | H93: S31 | I93: MedPAC June 2026, Ch.6 | J93: MedPAC_2026_Mandated | K93: Sits between the claims-derived $4.47B program payment and $5.71B allowed charge. MedPAC does not state the scope
A94: F90 | B94: Mean cost per transport, lowest transport-volume quartile | C94: 2023 | D94: 2878 | E94: $/transport | F94: GOV-A | G94: A | H94: S31 | I94: MedPAC June 2026, Table 6-6 | J94: MedPAC_2026_Mandated | K94: Mean 148 transports a year. Against $918 in the highest quartile
A95: F91 | B95: Mean cost per transport, highest transport-volume quartile | C95: 2023 | D95: 918 | E95: $/transport | F95: GOV-A | G95: A | H95: S31 | I95: MedPAC June 2026, Table 6-6 | J95: MedPAC_2026_Mandated | K95: Mean 15,291 transports a year. Average RVU only 5% lower than the lowest quartile: the gap is scale, not case mix
A96: F92 | B96: Mean cost per transport, for-profit organizations | C96: 2023 | D96: 563 | E96: $/transport | F96: GOV-A | G96: A | H96: S31 | I96: MedPAC June 2026, Table 6-6 | J96: MedPAC_2026_Mandated | K96: Government-owned cost $1,626, or 2.9x. Supersedes the RAND unweighted means for operator benchmarking
A97: F93 | B97: Mean cost per transport, dynamic staffing model | C97: 2023 | D97: 636 | E97: $/transport | F97: GOV-A | G97: A | H97: S31 | I97: MedPAC June 2026, Table 6-6 | J97: MedPAC_2026_Mandated | K97: Static staffing costs $1,524. The single largest controllable cost lever MedPAC identifies
A98: F94 | B98: Median revenue-to-cost ratio, lowest volume quartile | C98: 2023 | D98: 0.77 | E98: ratio | F98: GOV-A | G98: A | H98: S31 | I98: MedPAC June 2026, Table 6-11 | J98: MedPAC_2026_Mandated | K98: Highest quartile 1.10. NOT a Medicare margin: revenue includes non-Medicare sources
A99: F95 | B99: Government organizations' non-billing revenue per transport | C99: 2023 | D99: 322 | E99: $/transport | F99: GOV-A | G99: A | H99: S31 | I99: MedPAC June 2026, Ch.6 | J99: MedPAC_2026_Mandated | K99: 30% of government organizations receive local funding. Nonprofit $32, for-profit $12
A100: F96 | B100: Carrier-billed AIR ambulance Medicare payments | C100: 2024 | D100: 510451782 | E100: $ | F100: GOV-A | G100: A | H100: S13 | I100: PSPS 2024, A0430, A0431, A0435, A0436, A0432 | J100: Medicare_PSPS | K100: Needed to test MedPAC's spend figures. See Panel G
A101: F97 | B101: Median ED time before transfer to another facility (OP-18d) | C101: 2025 | D101: =Demand_Drivers!C24 -> 287 | E101: minutes | F101: GOV-A | G101: A | H101: S33 | I101: CMS Timely and Effective Care, national | J101: Demand_Drivers | K101: 287 minutes. Measurement period 01 Jul 2024 to 30 Jun 2025
...

Sheet Source_Register
A1: Source register
A2: The full citations. Every source used anywhere in this workbook, written out with publisher, document, edition, locator, URL, and evidence tier. The one-row-per-source summary lives on Source_Index; this tab is the complete reference text.
A4: Source ID | B4: Publisher | C4: Document | D4: Edition / data year | E4: Locator | F4: What it supplies | G4: URL | H4: Tier
A5: S01 | B5: AHRQ (HCUP) | C5: NEDS Weighted Summary Statistics, Core File | D5: Data years 2007-2023 | E5: DISP_ED weighted frequency distribution | F5: ED disposition counts: transfer to short-term hospital (2), transfer to other facility (5), admitted same hospital (9), destination unknown (98+99) | G5: https://hcup-us.ahrq.gov/db/nation/neds/stats/ | H5: A
A6: S02 | B6: AHRQ (HCUP) | C6: Introduction to the NEDS, 2022 | D6: Published 18 Nov 2024 | E6: Table 1, Table A5, Table A6 | F6: Weighted and unweighted ED visits, EDs sampled, partner states, target universe, frame coverage, ED disposition totals | G6: https://hcup-us.ahrq.gov/db/nation/neds/ | H6: A
A7: S03 | B7: AHRQ (HCUP) | C7: Introduction to the NEDS, 2023 | D7: Published 14 Jan 2026 | E7: Table A6, Table A7, Table D4, p.7 | F7: Same as S02 for data year 2023, plus injury visits with 95% CI and the NEISS-AIP comparator | G7: https://hcup-us.ahrq.gov/db/nation/neds/ | H7: A
A8: S04 | B8: AHRQ (HCUP) | C8: NIS Weighted Summary Statistics, Core File | D8: Data years 2007-2023 | E8: DISPUNIFORM, TRAN_IN, TRAN_OUT, I10_BIRTH frequency distributions | F8: Inpatient discharge disposition (transfer to short-term hospital = 2, other facility = 5), transfers in by point of origin, total weighted discharges, in-hospital births | G8: https://hcup-us.ahrq.gov/db/nation/nis/ | H8: A
A9: S05 | B9: American Hospital Association | C9: TrendWatch Chartbook 2020, Appendix | D9: 2020 vintage, covers 1995-2018 | E9: Appendix Table 3.1 | F9: Inpatient admissions in community hospitals, 2007 to 2018 (restated vintage) | G9: https://www.aha.org/system/files/media/file/2020/10/TrendwatchChartbook-2020-Appendix.pdf | H9: A
A10: S06 | B10: American Hospital Association | C10: Fast Facts on U.S. Hospitals, 2021 edition | D10: FY2019 AHA Annual Survey | E10: Admissions line items | F10: Total admissions all hospitals; admissions in community hospitals | G10: https://www.aha.org/system/files/media/file/2021/01/Fast-Facts-2021-table-FY19-data-14jan21.pdf | H10: A
A11: S07 | B11: American Hospital Association | C11: Fast Facts on U.S. Hospitals, 2022 edition | D11: 2020 AHA Annual Survey | E11: Admissions line items | F11: Total and community hospital admissions, 2020 | G11: https://www.aha.org/system/files/media/file/2022/01/fast-facts-on-US-hospitals-2022.pdf | H11: A
A12: S08 | B12: American Hospital Association | C12: Fast Facts on U.S. Hospitals, 2023 edition | D12: 2021 AHA Annual Survey | E12: Admissions line items | F12: Total and community hospital admissions, 2021 | G12: https://www.aha.org/system/files/media/file/2023/05/Fast-Facts-on-US-Hospitals-2023.pdf | H12: A
A13: S09 | B13: American Hospital Association | C13: Fast Facts on U.S. Hospitals, 2024 edition | D13: 2022 AHA Annual Survey | E13: Admissions line items | F13: Total and community hospital admissions, 2022 | G13: https://www.aha.org/system/files/media/file/2024/01/fast-facts-on-us-hospitals-2024-20240112.pdf | H13: A
A14: S10 | B14: American Hospital Association | C14: Fast Facts on U.S. Hospitals, 2025 edition | D14: 2023 AHA Annual Survey | E14: Admissions line items | F14: Total and community hospital admissions, 2023 | G14: https://www.aha.org/system/files/media/file/2025/01/Fast-Facts-on-US-Hospitals-2025.pdf | H14: A
A15: S11 | B15: American Hospital Association | C15: Fast Facts on U.S. Hospitals, 2026 edition | D15: 2024 AHA Annual Survey | E15: Admissions line items | F15: Total and community hospital admissions, 2024 | G15: https://www.aha.org/system/files/media/file/2026/02/Fast-Facts-on-US-Hospitals-2026.pdf | H15: A
... A34: S30 | B34: RAND Corporation for CMS | C34: Medicare Ground Ambulance Data Collection System (GADCS) Report: Year 1 and Year 2 Cohort Analysis | D34: Released 19 December 2024 | E34: Cost per transport tables | F34: Mean cost per ground ambulance transport, overall and by ownership type. 3,694 responding organizations, 85% of those selected, 2022 and 2023 data | G34: https://www.cms.gov/files/document/medicare-ground-ambulance-data-collection-system-gadcs-report-year-1-and-year-2-cohort-analysis.pdf | H34: A
A36: Tier A = document and table or page both pinned. Tier B = document named, locator not pinned in the source workbooks; verify before external citation. SOURCED = analyst computation on a vendored CMS file, not a published figure.
A37: S28, S29 and S30 were opened and read on 09 July 2026. Every other source in this register is asserted by the uploaded workbooks and was not independently checked. See Verification_Log.
A39: Verification. S01 through S04 (HCUP), S05 through S11 (AHA), S12 (NEMSIS), S13 (CMS PSPS), S14 (RVUs), S28 (MedPAC), S29 (CMS manual) and S30 (RAND GADCS) were all opened and read on 09 July 2026. S13 was rebuilt from 110,568 raw claim rows via the CMS API.
A40: Direct locators. NEDS stats: hcup-us.ahrq.gov/db/nation/neds/stats/NEDS_{year}_MaskedStats_Core_Weighted.PDF. NIS stats: hcup-us.ahrq.gov/db/nation/nis/tools/stats/. NEDS Introduction 2023: hcup-us.ahrq.gov/db/nation/neds/NEDSIntroduction2023.pdf. PSPS: data.cms.gov/data-api/revision 1/dataset/164fc736-4179-4100-9f79-592b69e41975/data.
A41: S31. MedPAC, June 2026 Report to the Congress, Chapter 6: Mandated report: Assessment of the Medicare Ground Ambulance Data Collection System. Published 15 June 2026. NOT reflected in this workbook. It is the authoritative source on Medicare ground ambulance payment adequacy and should be pulled before external use.
A43: S31. MedPAC, Report to the Congress: Medicare and the Health Care Delivery System, June 2026. Chapter 6, Mandated report: Assessment of the Medicare Ground Ambulance Data Collection System. Published 15 June 2026. Tables 6-6, 6-10, 6-11 and Recommendation 6. Downloaded and read 09 July 2026. Lives on MedPAC_2026_Mandated.
A44: S32. CMS Physician/Supplier Procedure Summary, data years 2010 through 2024, fifteen annual datasets pulled from the data.cms.gov API on 09 July 2026 and filtered on the HH origin-destination modifier. Lives on Medicare_IFT_Series.
A46: S33. CMS, Timely and Effective Care, national, state and hospital files. Measures OP-18a, OP-18b, OP-18c, OP-18d and OP-22. Measurement period 01 July 2024 to 30 June 2025 (OP-22: calendar 2024). Retrieved from the CMS provider-data API on 09 July 2026. Dataset identifiers isrn-hqyy (national), apyc-v239 (state), yv7e-xc69 (hospital). Lives on Demand_Drivers.
A47: S34. American Hospital Association, Fast Facts on U.S. Hospitals, 2020 edition (survey year 2018). Opened and read 09 July 2026. Provides the 2018 baseline for community hospitals, staffed beds and system affiliation.
A48: S35. Clark NM, Hernandez AH, Bertalan MS, Wang V, Greenberg SLM, Ibrahim AM, Stewart BT, Scott JW. Travel Time as an Indicator of Poor Access to Care in Surgical Emergencies. JAMA Network Open. 2025;8(1):e2455258. doi:10.1001/jamanetworkopen.2024.55258. PMID 39836423. Retrieved from PubMed.
A49: S36. Quinn SA, Edwards JD, Buccini P, Parmley MK, Leonard K, Irish W, Toschlog EA. The Impact of Delays in Interfacility Transfer on Outcomes in Elderly Trauma Patients. The American Surgeon. 2022;88(7):1471-1474. doi:10.1177/00031348221082278. PMID 35324338. Retrieved from PubMed.
A50: S37. Puls HA, Haas NL, Cranford JA, Medlin RP, Bassin BS. Emergency department length of stay and outcomes of emergency department-based intensive care unit patients. JACEP Open. 2022;3(1):e12684. doi:10.1002/emp2.12684. PMID 35229083. Retrieved from PubMed.
... A96: S77. KFF, Health Policy 101: The Uninsured Population and Health Coverage (2023 data; updated 2025), with Census Bureau ACS 2023-2024 coverage estimates: employer coverage about 54% of the population, Medicaid about 20% (including about 12 million dual-eligibles classified as Medicaid), Medicare about 15%, non-group about 6%, military about 1%, uninsured 8.0% (about 26 million); Peterson-KFF companion analysis: about 3 million privately insured ED ambulance transports a year. Read 10 July 2026. Lives on TAM_Model_National. Tier A.

Sheet Source_Index
A1: All 77 sources, identified. One row each.
A2: The question: can every source be seen at a glance? All 73 sources, one row each, with publisher, document, vintage, locator, tier, date accessed, and the tabs each one powers. Tier counts at the bottom are recomputed programmatically, not typed.
A4: ID | B4: Publisher | C4: Document | D4: Vintage | E4: Locator | F4: Tier | G4: Accessed | H4: Powers
A5: S01 | B5: AHRQ (HCUP) | C5: NEDS Weighted Summary Statistics, Core File | D5: Data years 2007-2023 | E5: DISP_ED weighted frequency distribution | F5: A | G5: 09 Jul 2026 | H5: Acute_IFT_Series, Cross_Source_Recon, Code_Crosswalks
A6: S02 | B6: AHRQ (HCUP) | C6: Introduction to the NEDS, 2022 | D6: Published 18 Nov 2024 | E6: Tables 1, A5, A6 | F6: A | G6: 09 Jul 2026 | H6: EMS_Transports, Cross_Source_Recon
A7: S03 | B7: AHRQ (HCUP) | C7: Introduction to the NEDS, 2023 | D7: Published 14 Jan 2026 | E7: Tables A6, A7, D4, p.7 | F7: A | G7: 09 Jul 2026 | H7: Acute_IFT_Series, Data_Quality_Register
A8: S04 | B8: AHRQ (HCUP) | C8: NIS Weighted Summary Statistics, Core File | D8: Data years 2007-2023 | E8: DISPUNIFORM, TRAN_IN, TRAN_OUT, I10_BIRTH | F8: A | G8: 09 Jul 2026 | H8: Acute_IFT_Series, Receiving_Side, Code_Crosswalks
A9: S05 | B9: American Hospital Association | C9: TrendWatch Chartbook 2020, Appendix | D9: Covers 1995-2018 | E9: Appendix Table 3.1 | F9: A | G9: 09 Jul 2026 | H9: Demand_Drivers
A10: S06 | B10: American Hospital Association | C10: Fast Facts on U.S. Hospitals, 2021 ed. | D10: FY2019 survey | E10: Admissions line items | F10: A | G10: 09 Jul 2026 | H10: Demand_Drivers
A11: S07 | B11: American Hospital Association | C11: Fast Facts on U.S. Hospitals, 2022 ed. | D11: 2020 survey | E11: Admissions line items | F11: A | G11: 09 Jul 2026 | H11: Demand_Drivers
A12: S08 | B12: American Hospital Association | C12: Fast Facts on U.S. Hospitals, 2023 ed. | D12: 2021 survey | E12: Admissions line items | F12: A | G12: 09 Jul 2026 | H12: Demand_Drivers
A13: S09 | B13: American Hospital Association | C13: Fast Facts on U.S. Hospitals, 2024 ed. | D13: 2022 survey | E13: Admissions line items | F13: A | G13: 09 Jul 2026 | H13: Demand_Drivers
A14: S10 | B14: American Hospital Association | C14: Fast Facts on U.S. Hospitals, 2025 ed. | D14: 2023 survey | E14: Admissions line items | F14: A | G14: 09 Jul 2026 | H14: Demand_Drivers
A15: S11 | B15: American Hospital Association | C15: Fast Facts on U.S. Hospitals, 2026 ed. | D15: 2024 survey | E15: Admissions line items | F15: A | G15: 09 Jul 2026 | H15: Demand_Drivers
... A65: S61 | B65: CMS | C65: Ambulance Fee Schedule Public Use Files page | D65: Read 10 Jul 2026 | E65: CAA 2026 sec. 6203; add-ons through 31 Dec 2027 | F65: A | G65: 10 Jul 2026 | H65: Payment_Rules
A67: Tier counts: 65 Tier A, 8 Tier B, 2 SOURCED (vendored, not reopened), 1 PENDING (S70, registered but unread; nothing rests on it). Fifteen sources are peer-reviewed journal articles with identifiers recorded. Twenty-nine are CMS documents or datasets. Nothing rests on a trade press article, a vendor white paper without published data, or an unnamed industry estimate. Counts recomputed programmatically, 10 July 2026.
A69: How to audit any figure in three steps. Find the Fact ID on the tab. Look it up on the Fact_Ledger to get the Source ID and locator. Find the Source ID here and on Source_Register for the full citation and URL. If the fact is DERIVED, the Fact_Ledger names the inputs and the cell on the tab shows the formula.
A70: S62 | B70: CMS | C70: MUP-PHY, data years 2014-2023 + 2024 geo fields | D70: Pulled 10 Jul 2026 | E70: Six ground base HCPCS; UUIDs on Verification_Log Panel H | F70: A | G70: 10 Jul 2026 | H70: Supplier_Series_Raw, State_Saturation_Raw, MSA_Landscape
A71: S63 | B71: JAMA Network Open | C71: Leuchter RK et al. Health Care Staffing Shortages and Potential National Hospital Bed Shortage | D71: 2025 | E71: doi:10.1001/jamanetworkopen.2024.60645 | F71: A | G71: 10 Jul 2026 | H71: Demand_Stack, Supply_Stack
A72: S64 | B72: CMS / US Congress | C72: CY2026 OPPS final rule fact sheet; CAA 2026 sec. 6210; 42 U.S.C. 1395cc-7; QualityNet AHCAH page | D72: Nov 2025-Feb 2026 | E72: OP-18 sunset; ECAT eCQM; H@H to 30 Sep 2030 | F72: A | G72: 10 Jul 2026 | H72: Fault_Audit, Demand_Stack, Payment_Rules
A73: S65 | B73: Maine Rural Health Research Center (USM) | C73: Jonk Y et al. Ambulance Deserts chartbook | D73: May 2023; data 2021-22 | E73: 4.5M in deserts; 82% of counties; 41 states measured | F73: A | G73: 10 Jul 2026 | H73: Imbalance_Ledger, Supply_Stack
A74: S66 | B74: USRDS / NIDDK | C74: 2024 Annual Data Report (AJKD summary); 2023 ADR release | D74: Data through 2022-23 | E74: In-center HD decline; ESRD MA 18.3 to 24.5% (2021); clinics +10% | F74: A | G74: 10 Jul 2026 | H74: Demand_Stack, Dialysis_ESRD_Channel
A75: S67 | B75: BLS | C75: OEWS May 2019, occupation 29-2040 | D75: May 2019 | E75: 260,600 jobs; median $35,400; state and industry tables | F75: A | G75: 10 Jul 2026 | H75: Workforce_Supply
A76: S68 | B76: BLS | C76: Occupational Outlook Handbook, EMTs and Paramedics | D76: May 2024 OEWS base | E76: 181,000 + 101,900 jobs; medians; +5% 2024-34 | F76: A | G76: 10 Jul 2026 | H76: Workforce_Supply
A77: S69 | B77: National Rural Health Association | C77: EMS Services in Rural America (citing Patterson et al.) | D77: 2019 | E77: 53% of isolated rural agencies all-volunteer vs 14% urban | F77: B | G77: 10 Jul 2026 | H77: Workforce_Supply
A78: S70 | B78: NASEMSO | C78: 2020 National EMS Assessment | D78: 2020 | E78: PENDING retrieval; no figure in this workbook rests on it | F78: PENDING | G78: Blocked | H78: Pending register P6
A79: S71 | B79: California EMS Authority | C79: Report to the Commission: Ambulance Patient Offload Delays (CEMSIS) | D79: Dec 2024; data Apr-Sep 2024 | E79: 19.1% over 30 min; 13,365 cumulative delay hours | F79: A | G79: 10 Jul 2026 | H79: Imbalance_Ledger, Supply_Stack
A80: S72 | B80: JAMA Network Open | C80: Patterns in California Ambulance Patient Offload Times by LEMSA | D80: 2024 (PMC11650417) | E80: 5.9M offloads; mean 42.8 min; 16 of 34 LEMSAs over standard | F80: A | G80: 10 Jul 2026 | H80: Supply_Stack
A81: S73 | B81: CMS | C81: MUP by Geography and Service, state level | D81: Data year 2024 | E81: Six ground base HCPCS; national 9,637,009 | F81: A | G81: 10 Jul 2026 | H81: State_Saturation_Raw, State_Saturation
... A85: S77 | B85: KFF / Census ACS | C85: Health coverage of the total population; uninsured analysis | D85: 2023-2024 | E85: Coverage shares; 26M uninsured; 3M private ED rides | F85: A | G85: 10 Jul 2026 | H85: TAM_Model_National

Sheet Demand_Drivers
A1: What actually drives demand for interfacility transport
A2: The question: what forces move interfacility transport demand inside the hospital walls? This tab carries the measured drivers: admissions, throughput, transfer delay, and the clinical evidence on what delay costs patients. Everything here is a published series or a peer-reviewed estimate.
A4: Panel A. Consolidation. Hospitals are disappearing into systems, and independents are the ones vanishing. | L4: Chart staging (OP-18d hospital distribution)
A5: Measure | B5: 2018 | C5: 2023 | D5: 2024 | E5: Change 2018 to 2024 | F5: Basis | G5: Source | L5: Minutes band | M5: Hospitals
A6: Total US hospitals | B6: 6146 | C6: 6093 | D6: 6100 | E6: =D6/B6-1 -> -0.0074845428 | F6: INDUSTRY-A | G6: AHA Fast Facts, 2020 / 2025 / 2026 editions | L6: 0-120 | M6: 11
A7: Community hospitals | B7: 5198 | C7: 5112 | D7: 5121 | E7: =D7/B7-1 -> -0.01481339 | F7: INDUSTRY-A | G7: AHA Fast Facts, 2020 / 2025 / 2026 editions | L7: 120-180 | M7: 149
A8: Community hospitals in a system | B8: 3491 | C8: 3525 | D8: 3567 | E8: =D8/B8-1 -> 0.021770266 | F8: INDUSTRY-A | G8: AHA Fast Facts, 2020 / 2025 / 2026 editions | L8: 180-240 | M8: 452
A9: Independent community hospitals | B9: =B7-B8 -> 1707 | C9: =C7-C8 -> 1587 | D9: =D7-D8 -> 1554 | E9: =D9/B9-1 -> -0.089630931 | F9: INDUSTRY-A | G9: AHA Fast Facts, 2020 / 2025 / 2026 editions | L9: 240-300 | M9: 625
A10: System share of community hospitals | B10: =B8/B7 -> 0.67160446 | C10: =C8/C7 -> 0.68955399 | D10: =D8/D7 -> 0.69654364 | E10: =D10/B10-1 -> 0.037133733 | F10: INDUSTRY-A | G10: AHA Fast Facts, 2020 / 2025 / 2026 editions | L10: 300-360 | M10: 492
A11: Staffed beds, community hospitals | B11: 792417 | C11: 781148 | D11: 775297 | E11: =D11/B11-1 -> -0.021604786 | F11: INDUSTRY-A | G11: AHA Fast Facts, 2020 / 2025 / 2026 editions | L11: 360-420 | M11: 304
A12: Admissions, community hospitals | B12: 34251159 | C12: 32345846 | D12: 33553725 | E12: =D12/B12-1 -> -0.020362347 | F12: GOV-A | G12: AHA Fast Facts, 2020 / 2025 / 2026 editions | L12: 420-480 | M12: 154
L13: 480-600 | M13: 109
A14: Over six years the United States lost 77 community hospitals and gained 76 system-affiliated ones. Independent community hospitals fell from 1,707 to 1,554, a 9.0% decline. Staffed beds fell 2.2% while admissions fell 2.0%. This is the structural engine of interfacility transport: fewer, larger, more specialised receiving centres, and a shrinking set of independent hospitals that must send patients out rather than keep them. | L14: 600-720 | M14: 25
A15: Caveat. AHA defines 'system' broadly enough that a single freestanding hospital can qualify by acquiring three or more pre-acute or post-acute organisations. System membership is therefore an upper bound on multi-hospital affiliation, and the count says nothing about whether the hospitals within a system are specialising. | L15: 720-10000 | M15: 19
A16: What this does NOT show. There is no public national time series on service-line concentration within systems. The claim that system hospitals are 'increasingly specialising' is plausible and widely asserted, but it is not measured by any source in this workbook. To measure it you need the AHA Annual Survey service-line file (paid) or the AHRQ Compendium hospital linkage files.
A19: Panel B. ED transfer delay. CMS measures it directly, and transfer patients wait longer than anyone else.
A20: CMS measure | B20: What it counts | C20: National median (minutes) | D20: Top-decile hospitals (minutes) | E20: Penalty vs discharged patients (minutes) | F20: Basis
A21: OP-18b | B21: Median time in the ED before leaving, for patients who are discharged. Excludes transfers and psychiatric patients. | C21: 161 | D21: 101 | F21: GOV-A
A22: OP-18a | B22: Median time in the ED before leaving, all patients, including psychiatric and transferred. | C22: 167 | E22: =C22-C$21 -> 6 | F22: GOV-A
A23: OP-18c | B23: Median time in the ED before leaving, psychiatric and mental health patients. | C23: 259 | D23: 130 | E23: =C23-C$21 -> 98 | F23: GOV-A
A24: OP-18d | B24: Median time in the ED before being TRANSFERRED TO ANOTHER FACILITY. | C24: 287 | D24: 187 | E24: =C24-C$21 -> 126 | F24: GOV-A
A25: OP-22 | B25: Percentage of patients who left the ED before being seen. | C25: 0.02 | F25: GOV-A
A27: An ED patient who is going to be transferred to another facility sits in the ED for a median of 287 minutes, 4 hours and 47 minutes. That is 126 minutes, or 78%, longer than a patient who is simply discharged. Transfer patients are the slowest-moving population in the American emergency department, slower even than psychiatric boarders. The top-decile hospital does it in 187 minutes, so 100 minutes of the median delay is addressable.
A28: Source: CMS Timely and Effective Care, national file, measurement period 01 July 2024 to 30 June 2025. Retrieved from the CMS provider-data API on 09 July 2026. OP-22 covers calendar year 2024.
A31: Panel C. How wide is the spread? Hospital-level distribution of ED transfer delay (OP-18d).
A32: Statistic | B32: Minutes | C32: Hours | D32: Read
A33: Hospitals reporting | B33: 2340 | D33: Every hospital reporting OP-18d in the current CMS release.
A34: 10th percentile | B34: 194 | C34: =B34/60 -> 3.2333333 | D34: The fastest tenth.
A35: 25th percentile | B35: 236 | C35: =B35/60 -> 3.9333333
A36: Median | B36: 294 | C36: =B36/60 -> 4.9 | D36: The hospital-level median. The patient-weighted national median is 287.
A37: 75th percentile | B37: 363 | C37: =B37/60 -> 6.05
A38: 90th percentile | B38: 443 | C38: =B38/60 -> 7.3833333
A39: 95th percentile | B39: 504 | C39: =B39/60 -> 8.4 | D39: Eight and a half hours to move a patient out of the ED.
A40: 99th percentile | B40: 676 | C40: =B40/60 -> 11.266667
A41: Maximum | B41: 1597 | C41: =B41/60 -> 26.616667 | D41: Twenty-six and a half hours. One hospital.
A42: Hospitals at or above 8 hours | B42: 153 | D42: 6.5% of reporting hospitals.
A43: Hospitals at or above 12 hours | B43: 19 | D43: 0.8%.
A44: Hospitals under 3 hours | B44: 160 | D44: 6.8%.
A46: State medians, OP-18d. Fifty-two jurisdictions.
A47: Rank | B47: State | C47: ED transfer delay (minutes) | D47: Discharged patients (minutes) | E47: Transfer penalty (minutes) | F47: Read
A48: 1 | B48: DC | C48: 649 | D48: 310 | E48: =C48-D48 -> 339 | F48: Worst six above, best six below. National spread is 3.8x.
A49: 2 | B49: PR | C49: 603 | D49: 300 | E49: =C49-D49 -> 303
A50: 3 | B50: MD | C50: 514 | D50: 246 | E50: =C50-D50 -> 268
A51: 4 | B51: ME | C51: 436 | D51: 161 | E51: =C51-D51 -> 275
A52: 5 | B52: NC | C52: 417 | D52: 187 | E52: =C52-D52 -> 230
A53: 6 | B53: NM | C53: 412 | D53: 162 | E53: =C53-D53 -> 250
A54: 47 | B54: WY | C54: 231 | D54: 132 | E54: =C54-D54 -> 99 | F54: The best states move transfer patients out in under four hours.
A55: 48 | B55: UT | C55: 223 | D55: 131 | E55: =C55-D55 -> 92
A56: 49 | B56: MT | C56: 215 | D56: 123 | E56: =C56-D56 -> 92
A57: 50 | B57: SD | C57: 213 | D57: 115 | E57: =C57-D57 -> 98
A58: 51 | B58: NE | C58: 205 | D58: 112 | E58: =C58-D58 -> 93
A59: 52 | B59: ND | C59: 170 | D59: 110 | E59: =C59-D59 -> 60
A60: Median | B60: of 52 | C60: 306 | E60: 152 | F60: Median state transfer penalty is 152 minutes.
A62: Panel D. Acuity mix. Answering 'what share of transports are BLS, ALS or CCT'.
A63: Population | B63: BLS non-emergency | C63: ALS1 non-emergency | D63: BLS emergency | E63: ALS1 emergency | F63: ALS2 | G63: Specialty Care Transport | H63: Source and caveat
A64: Medicare FFS carrier-billed, hospital-to-hospital, 2024, share of transports | B64: =Medicare_PSPS!G46 -> 0.38808699 | C64: =Medicare_PSPS!G47 -> 0.23527192 | D64: =Medicare_PSPS!G49 -> 0.10514446 | E64: =Medicare_PSPS!G48 -> 0.19824423 | F64: =Medicare_PSPS!G51 -> 0.006827622 | G64: =Medicare_PSPS!G50 -> 0.066424779 | H64: CMS PSPS. Carrier claims only. Hospital-owned departments bill institutionally and never appear.
A65: Same book, share of base-rate ALLOWED DOLLARS | B65: =Medicare_PSPS!H46 -> 0.2637189 | C65: =Medicare_PSPS!H47 -> 0.19704855 | D65: =Medicare_PSPS!H49 -> 0.11067296 | E65: =Medicare_PSPS!H48 -> 0.25939718 | F65: =Medicare_PSPS!H51 -> 0.013266683 | G65: =Medicare_PSPS!H50 -> 0.15589572 | H65: Price weighting lifts SCT from 6.6% of transports to 15.6% of dollars. It does not make the book high-acuity.
A66: Same book, 2010 | B66: 0.3853 | G66: 0.0737 | H66: Fifteen years earlier. Non-emergency BLS 38.5%, SCT 7.4%. The mix has not moved.
A68: All-payer acuity mix is NOT measurable from any source in this workbook. NEMSIS changed its level-of-care element in 2024 (eResponse.15 to eDisposition.32), which cut the reported denominator from 36.4M to 31.3M and made the ALS-Paramedic share appear to fall from 75.1% to 59.6%. That is an element change, not a staffing change. See Data_Quality_Register #15. NEMSIS level of care is excluded from this workbook.
A69: So the honest answer to 'what share is BLS, ALS, CCT' is: for the Medicare fee-for-service interfacility book it is 62% non-emergency BLS and ALS1, 30% emergent, 6.6% specialty care transport, and it has been within a point of that for fifteen years. For the commercial book, nobody in this evidence base knows.
A72: Panel E. What the peer-reviewed literature actually supports, and what it does not.
A73: Claim | B73: What the evidence says | C73: Strength | D73: Citation
A74: Travel time to emergency care increases the probability of interfacility transfer | B74: In 190,311 adults presenting to an ED with one of five emergency general surgery conditions in Florida and California in 2021, travel time of 60 minutes or more was associated with an adjusted odds ratio of 1.32 (95% CI 1.15 to 1.51) for interfacility transfer, 1.41 for inpatient admission, and an adjusted mean $8,284 in additional charges. Travel time above 120 minutes raised the odds of complex disease presentation to 1.28. | C74: STRONG. Large, multistate, adjusted. | D74: Clark et al., JAMA Network Open, 2025. doi:10.1001/jamanetworkopen.2024.55258. PMID 39836423.
A75: ED boarding harms patients | B75: Contested. A systematic review of 34 studies (2.3 million patients) found variable associations between ED length of stay and mortality, inpatient length of stay and adverse events, with the clearest signal in older patients. A systematic review focused on frail patients found prolonged boarding associated with adverse outcomes and higher mortality. | C75: MODERATE, and heterogeneous. | D75: Burgess et al., Res Nurs Health, 2022. doi:10.1002/nur.22201. Iozzo et al., J Clin Med, 2024. doi:10.3390/jcm13051269.
A76: Longer ED stay before transfer means worse outcomes | B76: The opposite is repeatedly observed, because of confounding by indication. In 1,535 elderly blunt-trauma transfers, SHORTER dwell time was associated with higher injury severity, lower Glasgow Coma Scale and higher mortality: the sickest patients are moved fastest. A study of 5,859 ED-ICU patients found no significant association between ED length of stay and mortality after adjustment. | C76: The naive correlation runs BACKWARDS. Never use dwell time as an outcome proxy. | D76: Quinn et al., Am Surg, 2022. doi:10.1177/00031348221082278. Puls et al., JACEP Open, 2022. doi:10.1002/emp2.12684.
A77: ED boarding raises hospital cost per day | B77: The source market study cited roughly $1,856 against $993 per day for boarded acute stroke patients. The citation was never pinned and this workbook excludes it. See Excluded_Not_Sourced #29. | C77: UNPINNED. Never quote. | D77: Not verifiable from the sources provided.
A79: Literature retrieved from PubMed on 09 July 2026. Digital object identifiers are given so every claim can be checked at source.
A82: Panel F. The demand equation, assembled from the measured pieces.
A83: Driver | B83: Direction | C83: Measured? | D83: What the evidence in this workbook says
A84: Hospital admissions (the denominator) | B84: Falling | C84: YES | D84: -0.67% per year, 2012 to 2023, AHA census. IFT grows as its own denominator shrinks.
A85: Acute-to-acute transfer episodes | B85: Flat to slightly up | C85: YES | D85: +0.86% per year, 2012 to 2023, and NOT demonstrably different from zero without standard errors.
A86: Channel shift, inpatient bed to ED | B86: Strongly toward the ED | C86: YES | D86: ED-origin share of episodes 74.4% to 80.2%, 2012 to 2023. The single clearest structural trend in the data.
A87: Consolidation into systems | B87: Rising | C87: YES | D87: Independent community hospitals down 9.0%, 2018 to 2024. Fewer places able to keep a complex patient.
A88: Specialisation within systems | B88: Asserted | C88: NO | D88: Not measured by any public national source. Needs the AHA Annual Survey service-line file.
A89: Travel time and regionalisation | B89: Rising | C89: YES, externally | D89: Travel time of 60 minutes or more raises the odds of interfacility transfer by 32%. Clark 2025.
A90: ED throughput and transfer delay | B90: Poor and highly variable | C90: YES | D90: 287-minute national median for transfer patients, a 78% penalty over discharged patients, and a 3.8x spread across states.
A91: Acuity escalation | B91: Not happening in Medicare | C91: YES | D91: SCT held between 6.5% and 7.4% of the Medicare interfacility book every year from 2010 to 2024.
A92: Payer mix migration to Medicare Advantage | B92: Rising | C92: INDIRECTLY | D92: Carrier-billed Medicare FFS interfacility transports fell -3.75% per year from the 2017 peak. Demand did not fall; the fee-for-service window narrowed.
A93: Post-acute capacity | B93: Large and separate | C93: PARTLY | D93: 6.5 million transfers to other facility types in 2022, 2.2 times the acute-to-acute count. Not all move by ambulance.
A95: The synthesis. Interfacility transport demand is not a volume growth story. Episodes are flat. What is changing is WHERE the transfer originates (the ED, not the ward), WHO can receive it (fewer, larger, system-affiliated centres), HOW FAR the patient has to go (travel time is now a measurable predictor of transfer), and HOW LONG it takes (287 minutes, with a 100-minute addressable gap to the top decile). The value is in throughput and network position, not in a rising tide of patients.

Sheet Macro_Demand_Drivers
A1: The measured macro drivers. Census, payer mix, supply exits, and the coordination lever.
A2: The question: what moves demand from outside the hospital? Four measured forces, each pinned to a primary document: the aging population (Census projections), the payer-mix migration that shrinks every fee-for-service series, rural hospital closures and their measured effect on transport times, and the final external anchor for how often patients arrive by ambulance.
A4: Panel A. The population that rides. Census Bureau 2023 National Population Projections, Table NP2023-T2, main series (S50). Thousands.
A5: Measure | B5: 2022 | C5: 2025 | D5: 2030 | E5: 2035 | F5: 2040 | G5: 2050 | H5: CAGR 2025-2030 | I5: CAGR 2030-2040
A6: Population 65 and over | B6: 57795 | C6: 63327 | D6: 71183 | E6: 75828 | F6: 78294 | G6: 82130 | H6: =(D6/C6)^(1/5)-1 -> 0.023664104 | I6: =(F6/D6)^(1/10)-1 -> 0.0095671701
A7: Total resident population | B7: 333288 | C7: 338016 | D7: 345074 | E7: 350861 | F7: 355309 | G7: 360639
A8: 65+ share of population | B8: =B6/B7 -> 0.17340858 | C8: =C6/C7 -> 0.18734912 | D8: =D6/D7 -> 0.20628329 | E8: =E6/E7 -> 0.21611977 | F8: =F6/F7 -> 0.22035468 | G8: =G6/G7 -> 0.22773466
A10: The 65+ population adds 7.9 million people between 2025 and 2030, a 2.4% per year compounding rate, then decelerates to 1.0% per year in the 2030s. NHAMCS puts the 65+ ambulance-arrival share at 33.4% against 17.0% for all ages (Panel E), so the riding population grows roughly twice as fast as total ED demand through 2030. This is the only measured tailwind in the demand equation; the Acute_IFT_Series episode CAGR of +0.86% already contains its past effect.
A12: Panel B. The payer-mix migration that shrinks every fee-for-service series in this workbook. KFF from CMS enrollment files (S51).
A13: Year | B13: MA share of eligible beneficiaries | C13: Enrolled (millions) | D13: Eligible (millions) | E13: Note
A14: 2007 | B14: 0.19 | E14: Series start as published by KFF
A15: 2025 | B15: 0.54 | C15: 34.1 | D15: 62.8
A16: 2026 | B16: 0.55 | C16: 35.2 | D16: 64.2 | E16: Current
A17: 2034 | B17: 0.63 | E17: CBO projection as cited by KFF
A18: Read together with Medicare_IFT_Series: carrier-billed FFS hospital-to-hospital transports peaked in 2017 and are 23.5% smaller, while MA crossed half of beneficiaries. The demand did not leave; the measurable window narrowed, and it will keep narrowing toward the CBO 63%. Every PSPS series in this workbook must be deflated mentally by this migration before being read as demand.
A20: Panel C. Supply exits on the sending side. Sheps Center rural closure tracker, accessed 10 July 2026 (S52), and the measured transport-time mechanism (S53).
A21: Measure | B21: Value | C21: Detail
A22: Rural hospital closures and conversions since January 2005 | B22: 197 | C22: 109 complete closures plus 88 converted closures (inpatient services ended, some services remain)
A23: Closures and conversions since 2010 | B23: 154 | C23: 86 complete plus 68 converted. Rural Emergency Hospital conversions are excluded and tracked separately
A24: Convention warning | C24: The Chartis Center for Rural Health counts 182 since 2010 under a broader convention that treats REH conversion differently. The two counts are not interchangeable; cite one tracker and its convention.
A25: Mechanism, measured. Rural hospital closures raised mean EMS transport time by 2.6 minutes (P=.09) and total activation time by 7.2 minutes (P=.02), with no change in response time: the ambulance reaches the patient as fast, then drives farther. Miller et al., Health Services Research 2020;55(2):288-300, doi:10.1111/1475-6773.13254, PMID 31989591, NEMSIS 2010-2016 (S53). Retrieved from PubMed 10 July 2026.
A27: Panel D. Coordination is a measured lever, not a slide claim.
A28: State medical operations coordination centers (SMOCCs), stood up in eight states during the pandemic, were associated with an IMMEDIATE 35% increase in interhospital transfer rates (rate ratio 1.35, 95% CI 1.05 to 1.74) followed by a long-term rate ratio of 0.94, across 441,709 NEMSIS transfers, June 2020 to December 2022. Transfer throughput responds to coordination infrastructure on a measurable scale. Richert et al., JAMA Network Open 2025;8(12):e2546002, doi:10.1001/jamanetworkopen.2025.46002, PMID 41324958 (S54). Retrieved from PubMed 10 July 2026. Read with Demand_Drivers Panel B: the 287-minute median transfer delay is the friction this lever attacks.
A30: Panel E. The final external anchor. NHAMCS 2022 was the last vintage of the survey.
A31: Measure | B31: Value | C31: Standard error | D31: Source
A32: ED visits, 2022 (thousands) | B32: 155398 | D32: NHAMCS 2022 ED Summary Tables, Table 4 (S55)
A33: Ambulance arrival share, all ages | B33: 0.17 | C33: 0.009 | D33: NHAMCS 2022 ED Summary Tables, Table 4 (S55)
A34: Ambulance arrival share, 65 and over | B34: 0.334 | C34: 0.016 | D34: NHAMCS 2022 ED Summary Tables, Table 4 (S55)
A35: Ambulance arrival share, 75 and over | B35: 0.396 | C35: 0.02 | D35: NHAMCS 2022 ED Summary Tables, Table 4 (S55)
A36: Ambulance arrival share, under 15 | B36: 0.05 | C36: 0.008 | D36: NHAMCS 2022 ED Summary Tables, Table 4 (S55)
A37: The 2016 anchor of 16.2% carried on EMS_Transports updates to 17.0% with a standard error of 0.9 points. NEMSIS 2022 coverage of EMS-to-ED transport (17.5% of NEDS visits) sits INSIDE the 95% interval of this final anchor: at full state participation, NEMSIS captures effectively all EMS-to-ED transport. NCHS discontinued NHAMCS after 2022 (successor: National Hospital Care Survey), so this anchor is frozen. Logged as Data_Quality_Register #30.
A39: Table metrics
A40: CAGR of 65+ population per five-year interval (from the projection row above) | C40: =(C6/B6)^(1/5)-1 -> 0.018450039 | D40: =(D6/C6)^(1/5)-1 -> 0.023664104 | E40: =(E6/D6)^(1/5)-1 -> 0.012722975 | F40: =(F6/E6)^(1/5)-1 -> 0.0064211989 | G40: =(G6/F6)^(1/5)-1 -> 0.0096123822

Sheet Demand_Stack
A1: Demand, as a stack of measured components. Every row a published series with a direction.
A2: The question: what does the whole demand side look like on one page? Each row is one measured demand component with its latest value, its direction over its own window, and its source. Nothing is weighted or combined; the components are read side by side on Imbalance_Ledger. The offsetting series is stated at the bottom.
A4: Component | B4: Latest measured value | C4: Window and direction | D4: Source | E4: Lives on
A5: Population 65 and over | B5: 71.2M projected 2030; 63.3M in 2025 | C5: +2.4%/yr 2025-2030, then +1.0%/yr (Census main series) | D5: S50 | E5: Macro_Demand_Drivers
A6: Ambulance-arrival intensity by age | B6: 17.0% all ages; 33.4% at 65+; 39.6% at 75+ | C6: Frozen final anchor (survey ended 2022) | D6: S55 | E6: Macro_Demand_Drivers
A7: ED transfer channel (DISP_ED = 2) | B7: Series through 2023 on the sending side | C7: Slow growth per episode series; 2023 carries a series break | D7: S01, S03 | E7: Acute_IFT_Series
A8: SNF interface transports (NH + HN) | B8: 2,398,253 Medicare FFS, 2024 | C8: NH leg growing +3.6%/yr 2022-2024; HN shrinking | D8: S39 | E8: Medicare_OD_Matrix
A9: Hospital occupancy | B9: 75.3% post-PHE steady state vs 63.9% pre-pandemic | C9: +11.4 points; driven by minus 16% staffed beds, census flat | D9: S63 | E9: Supply_Stack (dual-listed)
A10: ED boarding and throughput | B10: OP-18d median transfer delay 287 minutes (Finding 22) | C10: Measure sunsets CY2028; successor ECAT eCQM measures boarding directly | D10: S33, S64 | E10: Payment_Rules note
A11: Hospital-at-home census | B11: 366 approved programs, 139 systems, 37 states (AMA, Mar 2026); 419/147/39 per AHA Sep 2025 | C11: Waiver extended to 30 Sep 2030 (CAA 2026 sec. 6210); every H@H day creates home transport legs and mandated EMS coordination | D11: S64 | E11: Demand_Stack
A12: Dialysis demand denominators | B12: In-center HD prevalence declining since 2020; ESRD MA share 18.3% to 24.5% in 2021 alone; dialysis clinics +10% 2017-2022 | C12: Patient census and payer migration both shrink the FFS dialysis book independent of RSNAT | D12: S66 | E12: Dialysis_ESRD_Channel companion
A13: Medicare Advantage share (the demand this book cannot see) | B13: 55% of eligibles, 2026; CBO 63% by 2034 | C13: Rising; the measurable FFS window shrinks correspondingly | D13: S51, S60 | E13: Imbalance_Ledger Panel C
A14: Coordination-released demand | B14: SMOCC rate ratio 1.35 immediate on 441,709 transfers | C14: Throughput responds to coordination infrastructure | D14: S54 | E14: Macro_Demand_Drivers
A16: The offsetting series: Per-beneficiary Medicare FFS ground utilization FELL 11.9% from 2019 to 2024 (Utilization_Normalized). The demand stack does not claim volume is booming; it claims need per unit of capacity is rising while the measurable window shrinks. Both statements are computed on Imbalance_Ledger.

Sheet Acute_IFT_Series
A1: Acute-to-acute interfacility transfer episodes, sending side, 2007 to 2023
A2: The question: how many acute-to-acute hospital transfers happen each year? Answered from HCUP, the only national all-payer census of hospital discharges, using its two mutually exclusive origin channels: transfers out of the emergency department and transfers out of inpatient beds. The two are added, never averaged.
A4: Year | B4: ED-origin episodes NEDS DISP_ED = 2 | C4: Inpatient-origin episodes NIS DISPUNIFORM = 2 | D4: Total acute-to-acute episodes | E4: AHA community hospital inpatient admissions | F4: IFT % of admissions | G4: ED-origin share of episodes | H4: NIS total weighted discharges | I4: Episodes per 1,000 admissions | J4: Trend-eligible? | K4: Reason | L4: ED-origin as % of admissions (the ED channel) | M4: Inpatient-origin as % of admissions
A5: 2007 | B5: 1383929 | C5: 837154 | D5: =B5+C5 -> 2221083 | E5: 35983022 | F5: =D5/E5 -> 0.061725861 | G5: =B5/D5 -> 0.62308748 | H5: 39525405 | I5: =D5/E5*1000 -> 61.725861 | J5: No | K5: Pre-2012 NIS sample redesign; needs AHRQ trend weights | L5: =B5/E5 -> 0.038460611 | M5: =C5/E5 -> 0.02326525
A6: 2008 | B6: 1639779 | C6: 877693 | D6: =B6+C6 -> 2517472 | E6: 36334496 | F6: =D6/E6 -> 0.069286003 | G6: =B6/D6 -> 0.65135938 | H6: 39885120 | I6: =D6/E6*1000 -> 69.286003 | J6: No | K6: Pre-2012 NIS sample redesign; needs AHRQ trend weights | L6: =B6/E6 -> 0.045130088 | M6: =C6/E6 -> 0.024155915
A7: 2009 | B7: 1877016 | C7: 864489 | D7: =B7+C7 -> 2741505 | E7: 35986320 | F7: =D7/E7 -> 0.076181866 | G7: =B7/D7 -> 0.68466627 | H7: 39434956 | I7: =D7/E7*1000 -> 76.181866 | J7: No | K7: Pre-2012 NIS sample redesign; needs AHRQ trend weights | L7: =B7/E7 -> 0.052159154 | M7: =C7/E7 -> 0.024022712
A8: 2010 | B8: 1942692 | C8: 835417 | D8: =B8+C8 -> 2778109 | E8: 35672276 | F8: =D8/E8 -> 0.077878658 | G8: =B8/D8 -> 0.69928574 | H8: 39008298 | I8: =D8/E8*1000 -> 77.878658 | J8: No | K8: Pre-2012 NIS sample redesign; needs AHRQ trend weights | L8: =B8/E8 -> 0.054459435 | M8: =C8/E8 -> 0.023419223
A9: 2011 | B9: 2005324 | C9: 821658 | D9: =B9+C9 -> 2826982 | E9: 35350087 | F9: =D9/E9 -> 0.079971005 | G9: =B9/D9 -> 0.70935153 | H9: 38590732 | I9: =D9/E9*1000 -> 79.971005 | J9: No | K9: Pre-2012 NIS sample redesign; needs AHRQ trend weights | L9: =B9/E9 -> 0.056727555 | M9: =C9/E9 -> 0.023243451
A10: 2012 | B10: 2156598 | C10: 743295 | D10: =B10+C10 -> 2899893 | E10: 34828778 | F10: =D10/E10 -> 0.083261405 | G10: =B10/D10 -> 0.74368192 | H10: 36484846 | I10: =D10/E10*1000 -> 83.261405 | J10: Yes | K10: First year of the redesigned NIS discharge sample | L10: =B10/E10 -> 0.061920002 | M10: =C10/E10 -> 0.021341403
A11: 2013 | B11: 2043418 | C11: 711364 | D11: =B11+C11 -> 2754782 | E11: 34062869 | F11: =D11/E11 -> 0.080873458 | G11: =B11/D11 -> 0.74177122 | H11: 35597792 | I11: =D11/E11*1000 -> 80.873458 | J11: Yes | L11: =B11/E11 -> 0.059989603 | M11: =C11/E11 -> 0.020883854
A12: 2014 | B12: 2051283 | C12: 703140 | D12: =B12+C12 -> 2754423 | E12: 33516951 | F12: =D12/E12 -> 0.082179999 | G12: =B12/D12 -> 0.74472331 | H12: 35358817 | I12: =D12/E12*1000 -> 82.179999 | J12: Yes | L12: =B12/E12 -> 0.06120136 | M12: =C12/E12 -> 0.020978639
A13: 2015 | B13: 2044315 | C13: 697105 | D13: =B13+C13 -> 2741420 | E13: 33817285 | F13: =D13/E13 -> 0.081065644 | G13: =B13/D13 -> 0.7457139 | H13: 35769942 | I13: =D13/E13*1000 -> 81.065644 | J13: Yes | K13: Use with caution: NEDS destination-unknown spikes to 7.89% of visits in the ICD-9 to ICD-10 transition | L13: =B13/E13 -> 0.060451778 | M13: =C13/E13 -> 0.020613867
A14: 2016 | B14: 2363592 | C14: 695409 | D14: =B14+C14 -> 3059001 | E14: 34031587 | F14: =D14/E14 -> 0.08988711 | G14: =B14/D14 -> 0.77266794 | H14: 35675421 | I14: =D14/E14*1000 -> 89.88711 | J14: Yes | L14: =B14/E14 -> 0.069452888 | M14: =C14/E14 -> 0.020434222
A15: 2017 | B15: 2333630 | C15: 705669 | D15: =B15+C15 -> 3039299 | E15: 34305620 | F15: =D15/E15 -> 0.088594784 | G15: =B15/D15 -> 0.7678185 | H15: 35798453 | I15: =D15/E15*1000 -> 88.594784 | J15: Yes | L15: =B15/E15 -> 0.068024714 | M15: =C15/E15 -> 0.02057007
A16: 2018 | B16: 2292546 | C16: 704629 | D16: =B16+C16 -> 2997175 | E16: 34251159 | F16: =D16/E16 -> 0.087505798 | G16: =B16/D16 -> 0.76490228 | H16: 35527481 | I16: =D16/E16*1000 -> 87.505798 | J16: Yes | L16: =B16/E16 -> 0.066933385 | M16: =C16/E16 -> 0.020572413
A17: 2019 | B17: 2532807 | C17: 701459 | D17: =B17+C17 -> 3234266 | E17: 34078100 | F17: =D17/E17 -> 0.094907463 | G17: =B17/D17 -> 0.78311648 | H17: 35419022 | I17: =D17/E17*1000 -> 94.907463 | J17: Yes | L17: =B17/E17 -> 0.074323598 | M17: =C17/E17 -> 0.020583865
A18: 2020 | B18: 2359079 | C18: 643490 | D18: =B18+C18 -> 3002569 | E18: 31393318 | F18: =D18/E18 -> 0.09564357 | G18: =B18/D18 -> 0.78568686 | H18: 32355826 | I18: =D18/E18*1000 -> 95.64357 | J18: Yes | K18: COVID year | L18: =B18/E18 -> 0.075145896 | M18: =C18/E18 -> 0.020497674
A19: 2021 | B19: 2305329 | C19: 649198 | D19: =B19+C19 -> 2954527 | E19: 31967073 | F19: =D19/E19 -> 0.09242407 | G19: =B19/D19 -> 0.78027007 | H19: 33333721 | I19: =D19/E19*1000 -> 92.42407 | J19: Yes | K19: COVID year | L19: =B19/E19 -> 0.072115736 | M19: =C19/E19 -> 0.020308334
A20: 2022 | B20: 2311549 | C20: 617724 | D20: =B20+C20 -> 2929273 | E20: 31555807 | F20: =D20/E20 -> 0.092828334 | G20: =B20/D20 -> 0.78912037 | H20: 32891848 | I20: =D20/E20*1000 -> 92.828334 | J20: Yes | L20: =B20/E20 -> 0.07325273 | M20: =C20/E20 -> 0.019575605
A21: 2023 | B21: 2554379 | C21: 630765 | D21: =B21+C21 -> 3185144 | E21: 32345846 | F21: =D21/E21 -> 0.098471501 | G21: =B21/D21 -> 0.80196657 | H21: 33718585 | I21: =D21/E21*1000 -> 98.471501 | J21: Memo | K21: NEDS break in series: CA, NV, VT drop out, OK added; frame population coverage falls to 74.1% | L21: =B21/E21 -> 0.078970851 | M21: =C21/E21 -> 0.019500649
A23: Growth on the comparable window (2012 to 2023). 11 compounding years.
A24: Measure | B24: 2012 | C24: 2023 | D24: Total change | E24: CAGR | F24: Basis
A25: ED-origin transfer episodes | B25: =B10 -> 2156598 | C25: =B21 -> 2554379 | D25: =C25/B25-1 -> 0.18444838 | E25: =(C25/B25)^(1/11)-1 -> 0.015507851 | F25: GOV-A
A26: Inpatient-origin transfer episodes | B26: =C10 -> 743295 | C26: =C21 -> 630765 | D26: =C26/B26-1 -> -0.15139346 | E26: =(C26/B26)^(1/11)-1 -> -0.014812798 | F26: GOV-A
A27: Total acute-to-acute episodes | B27: =D10 -> 2899893 | C27: =D21 -> 3185144 | D27: =C27/B27-1 -> 0.098366043 | E27: =(C27/B27)^(1/11)-1 -> 0.0085659028 | F27: GOV-A
A28: AHA community hospital admissions | B28: =E10 -> 34828778 | C28: =E21 -> 32345846 | D28: =C28/B28-1 -> -0.071289667 | E28: =(C28/B28)^(1/11)-1 -> -0.0067009383 | F28: GOV-A
A29: NIS total weighted discharges | B29: =H10 -> 36484846 | C29: =H21 -> 33718585 | D29: =C29/B29-1 -> -0.075819451 | E29: =(C29/B29)^(1/11)-1 -> -0.0071423556 | F29: GOV-A
A30: IFT as % of admissions (the ratio) | B30: =F10 -> 0.083261405 | C30: =F21 -> 0.098471501 | D30: =C30/B30-1 -> 0.18267882 | E30: =(C30/B30)^(1/11)-1 -> 0.015369833 | F30: DERIVED
A32: Level statistics on the clean window (2019 to 2023)
A33: Measure | B33: Value | C33: Basis
A34: Mean acute-to-acute episodes per year | B34: =AVERAGE(D17:D21) -> 3061155.8 | C34: DERIVED
A35: Low of the annual range | B35: =MIN(D17:D21) -> 2929273 | C35: DERIVED
A36: High of the annual range | B36: =MAX(D17:D21) -> 3234266 | C36: DERIVED
A37: Mean IFT % of admissions | B37: =AVERAGE(F17:F21) -> 0.094854988 | C37: DERIVED
A38: Standard deviation of the ratio | B38: =STDEV(F17:F21) -> 0.0024351831 | C38: DERIVED
A39: Low of the ratio band | B39: =MIN(F17:F21) -> 0.09242407 | C39: DERIVED
A40: High of the ratio band | B40: =MAX(F17:F21) -> 0.098471501 | C40: DERIVED
A41: ED-origin share of episodes, 2012 | B41: =G10 -> 0.74368192 | C41: DERIVED
A42: ED-origin share of episodes, 2022 | B42: =G20 -> 0.78912037 | C42: DERIVED
A43: ED-origin share of episodes, 2023 | B43: =G21 -> 0.80196657 | C43: DERIVED
A45: Definition. ED-origin = NEDS DISP_ED = 2, transfer out of the ED to another short-term hospital. Inpatient-origin = NIS DISPUNIFORM = 2, admitted first, then transferred out. The two are mutually exclusive: an ED transfer-out is never also an inpatient discharge.
A46: Excluded from this table by design: NEDS DISP_ED = 5 and NIS DISPUNIFORM = 5, transfer to another TYPE of facility (SNF, intermediate care, psychiatric, rehabilitation). Those are interfacility ambulance demand but they are not acute to acute. They are carried on the Cross_Source_Recon tab.
A47: Counts are transfer LEGS recorded at the sending facility. One transfer episode produces one leg.
A48: The 2023 ED-origin figure is the Weighted Summary Statistics value. The NEDS Introduction 2023, Table A7, prints 2,552,895 for the same quantity. See Cross_Source_Recon.
A50: The ED channel in isolation, 2007 to 2022. This is the series behind the widely quoted near-doubling.
A51: Measure | B51: 2007 | C51: 2022 | D51: Total change | E51: CAGR | F51: Basis
A52: ED-origin transfers as % of community hospital admissions | B52: =L5 -> 0.038460611 | C52: =L20 -> 0.07325273 | D52: =C52/B52-1 -> 0.90461692 | E52: =(C52/B52)^(1/15)-1 -> 0.043887849 | F52: DERIVED
A53: ED-origin transfer volume | B53: =B5 -> 1383929 | C53: =B20 -> 2311549 | D53: =C53/B53-1 -> 0.67028005 | E53: =(C53/B53)^(1/15)-1 -> 0.034790945 | F53: GOV-A
A54: AHA community hospital admissions | B54: =E5 -> 35983022 | C54: =E20 -> 31555807 | D54: =C54/B54-1 -> -0.12303622 | E54: =(C54/B54)^(1/15)-1 -> -0.0087144463 | F54: GOV-A
A55: Numerator contribution to ratio growth | E55: =E53/((1+E53)/(1+E54)-1) -> 0.79272385 | F55: DERIVED
A57: Read together with the complete build above. The ED channel nearly doubled as a share of admissions. Total acute-to-acute episodes, which include the shrinking inpatient-origin channel, grew 0.86% per year. Quoting the first as the second is the most common error in this literature.
A58: No confidence interval can be attached to any CAGR here. AHRQ publishes no standard errors in the weighted summary statistics, and NEDS clusters on emergency departments, where transfer propensity is a hospital-level attribute. That gives DISP_ED = 2 a large design effect. The 0.86% per year total-episode CAGR is NOT demonstrably different from zero on this evidence. The AHA denominator decline is a hospital census and is real. HCUPnet returns design-based standard errors for free and would settle this.
A60: Table metrics
A61: CAGR, combined acute transfers, 2007 to 2023 | B61: =(D21/D5)^(1/16)-1 -> 0.022787161
A62: CAGR, ED-origin channel | B62: =(B21/B5)^(1/16)-1 -> 0.039048262
A63: CAGR, inpatient-origin channel | B63: =(C21/C5)^(1/16)-1 -> -0.01753658
A64: Peak year, combined | B64: =INDEX(A5:A21,MATCH(MAX(D5:D21),D5:D21,0)) -> 2019
A65: 2023 carries a series break (Fault_Audit); the cross-break CAGRs above are directional and the pre-break window should be quoted for precision. The two channels move in opposite directions: growth lives in the ED-origin stream.

Sheet Condition_Transfer_Anchors
A1: Condition-level transfer anchors: the clinical crosswalk begins
A2: The question: which clinical conditions generate transfers, at what rate, and is that changing? The full condition-by-disposition census remains pending item P1, but the peer-reviewed layer now has its first three anchors, each a national NEDS analysis retrieved and pinned via the PubMed connector on 10 July 2026. Together they establish three things a sizing model needs: transfer propensity varies by an order of magnitude across conditions, the high-acuity transfer streams were growing before the pandemic, and a large, quantified share of up-transfers is clinically avoidable, which is the throughput-value story a transport platform sells.
A4: Condition stream | B4: What the study measured | C4: The numbers to carry | D4: Citation | E4: Tier
A5: Traumatic brain injury (moderate and severe) | B5: National TBI ED visits, dispositions, and interfacility transfers, 2016-2020, from the Nationwide Emergency Department Sample. | C5: 527,123 TBI ED visits in 2020. Transfers to short-term hospitals rose 16.0% and transfers to other facilities rose 18.2% from 2016 to 2019, and both sat higher again in 2020. Rural-hospital TBI mortality odds nearly double urban (OR 1.95), the clinical case for rapid up-transfer. | D5: Gilkey et al., BMJ Open, 2024. doi:10.1136/bmjopen-2024-090141 (S74) | E5: A
A6: Isolated facial trauma | B6: Potentially avoidable up-transfers from level III and non-trauma centers, benchmarked against level I discharge practice, NEDS 2022. | C6: 856,197 isolated facial-trauma ED patients; 2.4% of those at lower-level facilities transferred up; 43.2% of those transfers (95% CI 40.9 to 45.4) classified potentially avoidable. Avoidable-transfer share is now a measured quantity, not a talking point. | D6: Acharya et al., Journal of the American College of Surgeons, 2026. doi:10.1097/XCS.0000000000001700 (S75) | E6: A
A7: Burn injury | B7: All adult burn ED visits and interfacility transfers, 2009-2014, NEDS. | C7: 3,047,701 burn ED visits over six years; 3.6% transferred, about 18,097 interfacility transfers a year; burns more than twice as likely to transfer as the general ED population, and a burn above 10% body surface area carries ten times the transfer probability. | D7: Evans et al., BMC Emergency Medicine, 2022. doi:10.1186/s12873-022-00705-6 (S76) | E7: A
A9: How this feeds the sizing work. These three streams demonstrate the pattern the full crosswalk (P1) will generalize: transfer propensity is a condition attribute, ranging from under 2% of ED visits overall to 24% for major burns, and the avoidable share is measurable per condition. For the archetype analysis, condition mix maps to acuity mix, which maps to which business model wins the volume. The burn figure also supplies a useful implied baseline: if burns transfer at 3.6% and run more than twice the general ED rate, the general adult ED transfer rate sits near 1.5%, consistent with the transfer series on Acute_IFT_Series.

Sheet Other_Transfer_Channels
A1: The other transfer channels, and the ED-universe validation
A2: The question: what moves between facilities besides the acute hospital pair? The post-acute and specialty channels, sized from the certified-provider universe and the discharge-destination codes that route patients to them.
A4: Year | B4: ED transfer to other facility type DISP_ED = 5 | C4: Inpatient transfer to other facility type DISPUNIFORM = 5 | D4: Acute-to-acute episodes | E4: TOTAL transfers out, all destinations | F4: Total ED visits | G4: ED visits admitted to same hospital DISP_ED = 9 | H4: ED-originated share of AHA admissions | I4: Destination unknown (98 + 99) | J4: Unknown as % of ED visits
A5: 2007 | B5: 1423280 | D5: 2221083 | F5: 122331739 | G5: 19024006 | H5: =G5/35983022 -> 0.52869395 | I5: 2184371 | J5: =I5/F5 -> 0.017856126
A6: 2008 | B6: 1399043 | C6: 5025652 | D6: 2517472 | E6: =B6+C6+D6 -> 8942167 | F6: 124945264 | G6: 19406101 | H6: =G6/36334496 -> 0.53409578 | I6: 870772 | J6: =I6/F6 -> 0.0069692277
A7: 2009 | B7: 1495461 | C7: 4984031 | D7: 2741505 | E7: =B7+C7+D7 -> 9220997 | F7: 128885040 | G7: 19592545 | H7: =G7/35986320 -> 0.54444425 | I7: 575022 | J7: =I7/F7 -> 0.0044615108
A8: 2010 | B8: 1282799 | C8: 5091272 | D8: 2778109 | E8: =B8+C8+D8 -> 9152180 | F8: 128970364 | G8: 19733530 | H8: =G8/35672276 -> 0.55318954 | I8: 405898 | J8: =I8/F8 -> 0.0031472192
A9: 2011 | B9: 1405614 | C9: 5352595 | D9: 2826982 | E9: =B9+C9+D9 -> 9585191 | F9: 131048605 | G9: 19627277 | H9: =G9/35350087 -> 0.55522571 | I9: 225478 | J9: =I9/F9 -> 0.0017205677
A10: 2012 | B10: 1536770 | C10: 4855040 | D10: 2899893 | E10: =B10+C10+D10 -> 9291703 | F10: 134399179 | G10: 19070684 | H10: =G10/34828778 -> 0.54755536 | I10: 155409 | J10: =I10/F10 -> 0.001156324
A11: 2013 | B11: 1629264 | C11: 4864292 | D11: 2754782 | E11: =B11+C11+D11 -> 9248338 | F11: 134869015 | G11: 19255862 | H11: =G11/34062869 -> 0.56530359 | I11: 206925 | J11: =I11/F11 -> 0.0015342664
A12: 2014 | B12: 1757684 | C12: 4909462 | D12: 2754423 | E12: =B12+C12+D12 -> 9421569 | F12: 137807901 | G12: 19435011 | H12: =G12/33516951 -> 0.57985617 | I12: 208262 | J12: =I12/F12 -> 0.0015112486
A13: 2015 | B13: 1727535 | C13: 4994845 | D13: 2741420 | E13: =B13+C13+D13 -> 9463800 | F13: 143469670 | G13: 19523512 | H13: =G13/33817285 -> 0.57732346 | I13: 11319342 | J13: =I13/F13 -> 0.078897108
A14: 2016 | B14: 1783777 | C14: 4961066 | D14: 3059001 | E14: =B14+C14+D14 -> 9803844 | F14: 144842742 | G14: 18955851 | H14: =G14/34031587 -> 0.55700755 | I14: 236114 | J14: =I14/F14 -> 0.0016301404
A15: 2017 | B15: 1983706 | C15: 5009823 | D15: 3039299 | E15: =B15+C15+D15 -> 10032828 | F15: 144814803 | G15: 20241628 | H15: =G15/34305620 -> 0.59003825 | I15: 301722 | J15: =I15/F15 -> 0.0020835025
A16: 2018 | B16: 2070859 | C16: 4996799 | D16: 2997175 | E16: =B16+C16+D16 -> 10064833 | F16: 143454430 | G16: 20061853 | H16: =G16/34251159 -> 0.58572771 | I16: 162925 | J16: =I16/F16 -> 0.0011357265
A17: 2019 | B17: 2081843 | C17: 4969869 | D17: 3234266 | E17: =B17+C17+D17 -> 10285978 | F17: 143432284 | G17: 20373534 | H17: =G17/34078100 -> 0.5978483 | I17: 74489 | J17: =I17/F17 -> 0.00051933217
A18: 2020 | B18: 2007356 | C18: 4103765 | D18: 3002569 | E18: =B18+C18+D18 -> 9113690 | F18: 123278165 | G18: 20091310 | H18: =G18/31393318 -> 0.63998683 | I18: 72763 | J18: =I18/F18 -> 0.00059023429
A19: 2021 | B19: 1933319 | C19: 4292030 | D19: 2954527 | E19: =B19+C19+D19 -> 9179876 | F19: 126968321 | G19: 19607517 | H19: =G19/31967073 -> 0.61336604 | I19: 153421 | J19: =I19/F19 -> 0.0012083408
A20: 2022 | B20: 2108209 | C20: 4400844 | D20: 2929273 | E20: =B20+C20+D20 -> 9438326 | F20: 136974618 | G20: 20031450 | H20: =G20/31555807 -> 0.63479441 | I20: 232973 | J20: =I20/F20 -> 0.001700848
A21: 2023 | B21: 2226601 | C21: 4637691 | D21: 3185144 | E21: =B21+C21+D21 -> 10049436 | F21: 142193558 | G21: 20973122 | H21: =G21/32345846 -> 0.64840233 | I21: 238268 | J21: =I21/F21 -> 0.0016756596
A23: Measure | B23: Value | C23: Basis | D23: Read
A24: Transfers to other facility types, 2022 (ED plus inpatient origin) | B24: =B20+C20 -> 6509053 | C24: DERIVED | D24: SNF, intermediate care, psychiatric, rehabilitation and other. 2.2 times the acute-to-acute episode count. Not all move by ambulance: many post-acute discharges go by wheelchair van or private vehicle. This is why NEMSIS facility-to-facility counts and HCUP transfer counts cannot be reconciled by definition alone.
A25: Total transfers out, all destinations, 2022 | B25: =E20 -> 9438326 | C25: DERIVED | D25: The widest sending-side count HCUP supports.
A26: ED-originated share of all community hospital admissions, 2007 | B26: =H5 -> 0.52869395 | C26: DERIVED | D26: Universe validation. If NEDS and AHA describe the same hospitals, ED-originated admissions should be a plausible and rising share of all admissions.
A27: ED-originated share of all community hospital admissions, 2022 | B27: =H20 -> 0.63479441 | C27: DERIVED | D27: 52.9% rising to 63.5%, consistent with the published literature. The numerator and denominator describe the same hospital universe. This is the strongest available check that the ratio on Acute_IFT_Series is not comparing unlike things.
A29: 2015 destination-unknown is 7.89% of ED visits, against roughly 0.15% either side. That is the ICD-9 to ICD-10 transition. Never use 2015 or the 2015-to-2016 change.
A30: Sources. Columns B, C, D, G, I: HCUP NEDS and NIS weighted summary statistics (S01, S04). Column F: NEDS Introduction tables (S02, S03). Column H denominator: AHA (S05 to S10).
A31: 2007 inpatient-origin transfers to other facility types were not carried in any source workbook, so total transfers out begins in 2008.

Sheet Receiving_Side
A1: Independent validation from the receiving hospital's record, 2012 to 2023
A2: The question: does the receiving end of the ledger agree with the sending end? A transfer has two ends, and the inpatient file counts arrivals independently of departures. This tab runs that agreement test, which is the workbook's internal validity check.
A4: Year | B4: Sending-side episodes | C4: Transferred in from an acute hospital TRAN_IN = 1 | D4: Conversion rate | E4: Transferred in from another facility type TRAN_IN = 2 | F4: All transfers in | G4: NIS total discharges | H4: AHA community admissions | I4: TRAN_IN = 1 as % of NIS discharges | J4: TRAN_IN = 1 as % of AHA admissions | K4: Trend-eligible? | L4: Reason
A5: 2012 | B5: 2899893 | C5: 1657531 | D5: =C5/B5 -> 0.5715835 | E5: 860365 | F5: =C5+E5 -> 2517896 | G5: 36484846 | H5: 34828778 | I5: =C5/G5 -> 0.04543067 | J5: =C5/H5 -> 0.047590846 | K5: Yes
A6: 2013 | B6: 2754782 | C6: 1709539 | D6: =C6/B6 -> 0.62057143 | E6: 795145 | F6: =C6+E6 -> 2504684 | G6: 35597792 | H6: 34062869 | I6: =C6/G6 -> 0.048023737 | J6: =C6/H6 -> 0.050187757 | K6: Yes
A7: 2014 | B7: 2754423 | C7: 1772540 | D7: =C7/B7 -> 0.64352498 | E7: 768881 | F7: =C7+E7 -> 2541421 | G7: 35358817 | H7: 33516951 | I7: =C7/G7 -> 0.050130071 | J7: =C7/H7 -> 0.052884882 | K7: Yes
A8: 2015 | B8: 2741420 | C8: 1858455 | D8: =C8/B8 -> 0.67791692 | E8: 756605 | F8: =C8+E8 -> 2615060 | G8: 35769942 | H8: 33817285 | I8: =C8/G8 -> 0.051955773 | J8: =C8/H8 -> 0.054955772 | K8: Yes
A9: 2016 | B9: 3059001 | C9: 1938555 | D9: =C9/B9 -> 0.6337216 | E9: 754370 | F9: =C9+E9 -> 2692925 | G9: 35675421 | H9: 34031587 | I9: =C9/G9 -> 0.054338672 | J9: =C9/H9 -> 0.056963403 | K9: Yes
A10: 2017 | B10: 3039299 | C10: 2149544 | D10: =C10/B10 -> 0.70724993 | E10: 1218390 | F10: =C10+E10 -> 3367934 | G10: 35798453 | H10: 34305620 | I10: =C10/G10 -> 0.060045723 | J10: =C10/H10 -> 0.062658655 | K10: No | L10: AHRQ changed the Point of Origin derivation: TRAN_IN = 2 jumps 61.5% and TRAN_IN = 1 jumps 10.9% in one year. Never trend across the 2016 to 2017 boundary.
A11: 2018 | B11: 2997175 | C11: 2273770 | D11: =C11/B11 -> 0.75863772 | E11: 1218345 | F11: =C11+E11 -> 3492115 | G11: 35527481 | H11: 34251159 | I11: =C11/G11 -> 0.064000316 | J11: =C11/H11 -> 0.066385199 | K11: Yes
A12: 2019 | B12: 3234266 | C12: 2357650 | D12: =C12/B12 -> 0.72895983 | E12: 1261569 | F12: =C12+E12 -> 3619219 | G12: 35419022 | H12: 34078100 | I12: =C12/G12 -> 0.066564514 | J12: =C12/H12 -> 0.069183728 | K12: Yes
A13: 2020 | B13: 3002569 | C13: 2212964 | D13: =C13/B13 -> 0.73702353 | E13: 1212685 | F13: =C13+E13 -> 3425649 | G13: 32355826 | H13: 31393318 | I13: =C13/G13 -> 0.068394607 | J13: =C13/H13 -> 0.070491561 | K13: Yes | L13: COVID year
A14: 2021 | B14: 2954527 | C14: 2281228 | D14: =C14/B14 -> 0.77211276 | E14: 1216343 | F14: =C14+E14 -> 3497571 | G14: 33333721 | H14: 31967073 | I14: =C14/G14 -> 0.068436044 | J14: =C14/H14 -> 0.071361804 | K14: Yes | L14: COVID year
A15: 2022 | B15: 2929273 | C15: 2205490 | D15: =C15/B15 -> 0.75291378 | E15: 1251854 | F15: =C15+E15 -> 3457344 | G15: 32891848 | H15: 31555807 | I15: =C15/G15 -> 0.067052785 | J15: =C15/H15 -> 0.069891732 | K15: Yes
A16: 2023 | B16: 3185144 | C16: 2463771 | D16: =C16/B16 -> 0.7735195 | E16: 1287500 | F16: =C16+E16 -> 3751271 | G16: 33718585 | H16: 32345846 | I16: =C16/G16 -> 0.073068636 | J16: =C16/H16 -> 0.076169626 | K16: Memo | L16: The TRAN_IN column itself is clean for 2023. The sending-side column pulls a NEDS break year.
A18: Denominator sensitivity, 2022. One numerator, three defensible denominators.
A19: Denominator | B19: Value | C19: TRAN_IN = 1 share | D19: Sending-side episode share | E19: Note
A20: AHA community hospital admissions (excludes newborns, includes rehab and LTACH) | B20: 31555807 | C20: =2205490/B20 -> 0.069891732 | D20: =2929273/B20 -> 0.092828334 | E20: S09. This is the denominator used throughout the workbook.
A21: NIS total weighted discharges (includes newborns, excludes rehab and LTACH) | B21: 32891848 | C21: =2205490/B21 -> 0.067052785 | D21: =2929273/B21 -> 0.08905772 | E21: S04. NIS 2022 Core weighted summary statistics.
A22: NIS discharges excluding in-hospital births | B22: 29413783 | C22: =2205490/B22 -> 0.074981515 | D22: =2929273/B22 -> 0.099588448 | E22: S04. NIS 2022 total less I10_BIRTH = 1 (3,478,065). Closest match to the AHA admission definition, narrower hospital universe.
A23: Spread, high less low (percentage points) | C23: =MAX(C20:C22)-MIN(C20:C22) -> 0.00792873 | D23: =MAX(D20:D22)-MIN(D20:D22) -> 0.010530728
A25: Read the conversion rate as: of every 100 acute-to-acute transfers sent, roughly 75 become an inpatient admission at a NIS-universe hospital. The other 25 went to a psychiatric, rehabilitation or long-term acute care hospital (all outside the NIS universe), were treated and released at the receiving ED, were placed in observation, or were not coded as a transfer in.
A26: AHA admissions equal 1.07 times NIS ex-birth discharges in every year 2019 to 2023 (1.070, 1.086, 1.071, 1.073, 1.067). The gap is stable and is the rehabilitation, LTACH and specialty hospital universe. Denominator choice moves the answer by roughly 0.8 points. Pick one, disclose it, do not mix.

Sheet EMS_Transports
A1: EMS activations and transports, NEMSIS 2019 to 2024
A2: The question: how many ambulance legs exist, and what share are interfacility? Hospital data counts patients moved; EMS data counts the vehicles moving them. This tab carries the national EMS activation series, its interfacility categories, and the external anchor that validates its coverage.
A4: Coverage. Read every count against this.
A5: Metric | B5: 2019 | C5: 2020 | D5: 2021 | E5: 2022 | F5: 2023 | G5: 2024 | H5: Note
A6: Total activations (eResponse.05 table) | B6: 36119261 | C6: 44798443 | D6: 50192875 | E6: 53572097 | F6: 46040873 | G6: 60298684 | H6: Use the table total, not the cover box. The 2021 cover reprints the 2020 figures verbatim. The 2023 cover prints 54,190,579 against a table total of 46,040,873, a gap of 8.1M records.
A7: Participating states and territories | B7: 47 | C7: 50 | D7: 50 | E7: 54 | F7: 54 | G7: 54 | H7: 2021: DE, ID, American Samoa and Puerto Rico did not participate.
A8: Number of agencies | B8: 11025 | C8: 12319 | D8: 12319 | E8: 13778 | F8: 14369 | G8: 14756 | H8: The 2021 agency count repeats 2020.
A9: Data standard | B9: v3.4 | C9: v3.4 | D9: v3.4 | E9: v3.4 | F9: v3.5 | G9: v3.5 | H9: v3.3.4 retired August 2021.
A11: Activation growth over this window is part demand and part coverage expansion (47 states to 54, 11,025 agencies to 14,756). Never read the activation CAGR as EMS volume growth.
A13: Type of service requested. eResponse.05. The value set expands from 7 categories (v3.4) to 18 (v3.5) in 2024, so the two blocks are NOT one series.
A14: Category (v3.4) | B14: 2019 | C14: 2020 | D14: 2021 | E14: 2022 | F14: 2023 | G14: Share 2019 | H14: Share 2023 | I14: CAGR 2019-2023
A15: 911 Response (Scene) | B15: 27925669 | C15: 34718261 | D15: 39057108 | E15: 42302358 | F15: 36367261 | G15: =B15/B$22 -> 0.77315173 | H15: =F15/F$22 -> 0.78989078 | I15: =(F15/B15)^(1/4)-1 -> 0.068259471
A16: Medical Transport | B16: 4408022 | C16: 5430872 | D16: 5813908 | E16: 5758167 | F16: 4765743 | G16: =B16/B$22 -> 0.12204076 | H16: =F16/F$22 -> 0.10351113 | I16: =(F16/B16)^(1/4)-1 -> 0.019698349
A17: Interfacility Transport | B17: 3309316 | C17: 4070413 | D17: 4613080 | E17: 4697465 | F17: 4179580 | G17: =B17/B$22 -> 0.091621919 | H17: =F17/F$22 -> 0.090779773 | I17: =(F17/B17)^(1/4)-1 -> 0.060104312
A18: Public Assistance / Other Not Listed | B18: 182470 | C18: 238734 | D18: 266525 | E18: 278152 | F18: 243225 | G18: =B18/B$22 -> 0.0050518752 | H18: =F18/F$22 -> 0.005282806 | I18: =(F18/B18)^(1/4)-1 -> 0.074494471
A19: Standby | B19: 140532 | C19: 139488 | D19: 176882 | E19: 204649 | F19: 137636 | G19: =B19/B$22 -> 0.0038907773 | H19: =F19/F$22 -> 0.0029894307 | I19: =(F19/B19)^(1/4)-1 -> -0.0051921494
A20: Intercept | B20: 90829 | C20: 112426 | D20: 130416 | E20: 158524 | F20: 151884 | G20: =B20/B$22 -> 0.0025146971 | H20: =F20/F$22 -> 0.0032988949 | I20: =(F20/B20)^(1/4)-1 -> 0.13716078
A21: Mutual Aid | B21: 62423 | C21: 88249 | D21: 134956 | E21: 172782 | F21: 195544 | G21: =B21/B$22 -> 0.0017282469 | H21: =F21/F$22 -> 0.0042471827 | I21: =(F21/B21)^(1/4)-1 -> 0.33037772
A22: TOTAL | B22: =SUM(B15:B21) -> 36119261 | C22: =SUM(C15:C21) -> 44798443 | D22: =SUM(D15:D21) -> 50192875 | E22: =SUM(E15:E21) -> 53572097 | F22: =SUM(F15:F21) -> 46040873
A24: Type of service requested. v3.5 value set, 2024 only.
A25: Category (v3.5) | B25: 2024 | C25: Implied share | D25: Facility-to-facility?
A26: Emergency Response (Primary Response Area) | B26: 46733668 | C26: =B26/B$44 -> 0.77503628 | D26: No
A27: Hospital-to-Hospital Transfer | B27: 5510664 | C27: =B27/B$44 -> 0.091389457 | D27: Yes
A28: Other Routine Medical Transport | B28: 4467204 | C28: =B28/B$44 -> 0.074084602 | D28: No
A29: Hospital to Non-Hospital Facility Transfer | B29: 1418924 | C29: =B29/B$44 -> 0.023531592 | D29: Yes
A30: Public Assistance | B30: 630530 | C30: =B30/B$44 -> 0.010456779 | D30: No
A31: Non-Hospital Facility to Non-Hospital Facility Transfer | B31: 335432 | C31: =B31/B$44 -> 0.0055628411 | D31: Yes
A32: Emergency Response (Mutual Aid) | B32: 310027 | C32: =B32/B$44 -> 0.0051415218 | D32: No
A33: Non-Hospital Facility to Hospital Transfer | B33: 247636 | C33: =B33/B$44 -> 0.0041068226 | D33: Yes
A34: Emergency Response (Intercept) | B34: 243105 | C34: =B34/B$44 -> 0.00403168 | D34: No
A35: Standby | B35: 240680 | C35: =B35/B$44 -> 0.0039914636 | D35: No
A36: Support Services | B36: 58179 | C36: =B36/B$44 -> 0.00096484693 | D36: No
A37: Crew Transport Only | B37: 53257 | C37: =B37/B$44 -> 0.00088321994 | D37: No
... A43: Mortuary Services | B43: 1950 | C43: =B43/B$44 -> 3.2339014e-05 | D43: No
A44: TOTAL | B44: =SUM(B26:B43) -> 60298684
A46: The 2024 interfacility book, isolated
A47: Measure | B47: 2024 activations | C47: % of all activations | D47: Basis
A48: Hospital-to-Hospital Transfer | B48: =B27 -> 5510664 | C48: =B48/B44 -> 0.091389457 | D48: GOV-A
A49: All facility-to-facility transfers (four categories) | B49: =B27+B29+B31+B33 -> 7512656 | C49: =B49/B44 -> 0.12459071 | D49: DERIVED
A50: Other Routine Medical Transport (dialysis, appointments, return home) | B50: =B28 -> 4467204 | C50: =B50/B44 -> 0.074084602 | D50: GOV-A
A51: Other Routine Medical Transport is not interfacility transfer and is excluded from every IFT figure in this workbook.
A52: NEMSIS Hospital-to-Hospital Transfer is acute-to-acute PLUS transfers to psychiatric, rehabilitation and long-term acute care hospitals, and it includes return legs. HCUP codes those destinations as DISP_ED = 5 or DISPUNIFORM = 5, not = 2. This is the largest single driver of the wedge on the Cross_Source_Recon tab.
A54: Type of destination. eDisposition.21. Stable value set across all six years, the cleanest series in the NEMSIS reports.
A55: Destination | B55: 2019 | C55: 2020 | D55: 2021 | E55: 2022 | F55: 2023 | G55: 2024 | H55: Share 2019 | I55: Share 2024 | J55: CAGR 2019-2024
A56: Hospital, Emergency Department | B56: 16267916 | C56: 19719180 | D56: 22054717 | E56: 24016095 | F56: 20914310 | G56: 27706728 | H56: =B56/B$68 -> 0.87943561 | I56: =G56/G$68 -> 0.91977811 | J56: =(G56/B56)^(1/5)-1 -> 0.11237358
A57: Hospital, Non-Emergency Department Bed | B57: 1682714 | C57: 1666293 | D57: 1736151 | E57: 1863294 | F57: 1502001 | G57: 1738980 | H57: =B57/B$68 -> 0.090966699 | I57: =G57/G$68 -> 0.057728785 | J57: =(G57/B57)^(1/5)-1 -> 0.0065998372
A58: Other EMS Responder (ground) | B58: 141030 | C58: 150330 | D58: 175514 | E58: 198770 | F58: 194664 | G58: 188683 | H58: =B58/B$68 -> 0.0076240131 | I58: =G58/G$68 -> 0.006263695 | J58: =(G58/B58)^(1/5)-1 -> 0.059947252
A59: Freestanding Emergency Department | B59: 43070 | C59: 70736 | D59: 104199 | E59: 130988 | F59: 117984 | G59: 156346 | H59: =B59/B$68 -> 0.0023283432 | I59: =G59/G$68 -> 0.0051902061 | J59: =(G59/B59)^(1/5)-1 -> 0.29414334
A60: Home | B60: 56731 | C60: 73593 | D60: 78952 | E60: 69811 | F60: 52980 | G60: 73293 | H60: =B60/B$68 -> 0.0030668502 | I60: =G60/G$68 -> 0.0024331021 | J60: =(G60/B60)^(1/5)-1 -> 0.052563757
A61: Other | B61: 116748 | C61: 134198 | D61: 161668 | E61: 188520 | F61: 189280 | G61: 69367 | H61: =B61/B$68 -> 0.00631134 | I61: =G61/G$68 -> 0.0023027709 | J61: =(G61/B61)^(1/5)-1 -> -0.098884017
A62: Nursing Home / Assisted Living Facility | B62: 90418 | C62: 65250 | D62: 60901 | E62: 51031 | F62: 44553 | G62: 66934 | H62: =B62/B$68 -> 0.004887953 | I62: =G62/G$68 -> 0.0022220028 | J62: =(G62/B62)^(1/5)-1 -> -0.058374141
A63: Morgue / Mortuary | B63: 12500 | C63: 19160 | D63: 19618 | E63: 19648 | F63: 15775 | G63: 48756 | H63: =B63/B$68 -> 0.00067574391 | I63: =G63/G$68 -> 0.0016185492 | J63: =(G63/B63)^(1/5)-1 -> 0.3128757
A64: Other EMS Responder (air) | B64: 25532 | C64: 37097 | D64: 44356 | E64: 45011 | F64: 39053 | G64: 40502 | H64: =B64/B$68 -> 0.0013802475 | I64: =G64/G$68 -> 0.0013445418 | J64: =(G64/B64)^(1/5)-1 -> 0.096675968
A65: Medical Office / Clinic | B65: 54281 | C65: 37921 | D65: 38829 | E65: 34223 | F65: 25436 | G65: 24752 | H65: =B65/B$68 -> 0.0029344044 | I65: =G65/G$68 -> 0.00082169023 | J65: =(G65/B65)^(1/5)-1 -> -0.14534175
A66: Urgent Care | B66: 3179 | C66: 2964 | D66: 4614 | E66: 5670 | F66: 4581 | G66: 6993 | H66: =B66/B$68 -> 0.00017185519 | I66: =G66/G$68 -> 0.00023214608 | J66: =(G66/B66)^(1/5)-1 -> 0.17077813
A67: Police / Jail | B67: 4013 | C67: 4264 | D67: 4432 | E67: 4523 | F67: 3772 | G67: 1940 | H67: =B67/B$68 -> 0.00021694082 | I67: =G67/G$68 -> 6.440203e-05 | J67: =(G67/B67)^(1/5)-1 -> -0.1352979
A68: TOTAL transports | B68: =SUM(B56:B67) -> 18498132 | C68: =SUM(C56:C67) -> 21980986 | D68: =SUM(D56:D67) -> 24483951 | E68: =SUM(E56:E67) -> 26627584 | F68: =SUM(F56:F67) -> 23104389 | G68: =SUM(G56:G67) -> 30123274
A70: NEMSIS coverage of EMS-to-ED transport, benchmarked against a probability sample
A71: Year | B71: NEMSIS transports to a hospital ED | C71: NEDS weighted US ED visits | D71: Ratio | E71: Participating states | F71: Read
A72: 2019 | B72: 16267916 | C72: 143432284 | D72: =B72/C72 -> 0.11341879 | E72: 47 | F72: Only 47 states participate. The gap is the missing seven.
A73: 2020 | B73: 19719180 | C73: 123278165 | D73: =B73/C73 -> 0.15995679 | E73: 50 | F73: Three states added. Ratio jumps 4.7 points.
A74: 2021 | B74: 22054717 | C74: 126968321 | D74: =B74/C74 -> 0.17370252 | E74: 50 | F74: Denominator falls with COVID. Ratio keeps climbing.
A75: 2022 | B75: 24016095 | C75: 136974618 | D75: =B75/C75 -> 0.17533245 | E75: 54 | F75: Full participation. Ratio lands on the independent NHAMCS anchor.
A76: 2023 | B76: 20914310 | C76: 142193558 | D76: =B76/C76 -> 0.14708339 | E76: 54 | F76: Ratio falls 2.8 points with no coverage change. This is the 2023 NEMSIS denominator defect, independently confirmed.
A77: 2024 | B77: 27706728 | E77: 54 | F77: NEDS 2024 is not yet released.
A78: NHAMCS anchor | B78: 22936000 | C78: 142006000 | D78: =B78/C78 -> 0.1615143 | F78: NEDS carries no arrival-mode element, so the anchor has to come from NHAMCS.
A80: Verdict. NEMSIS coverage of EMS-to-ED transport rises from roughly 11% to roughly 17.5% of US ED visits as participating states go from 47 to 54, then converges on the independent NHAMCS ambulance-arrival anchor of about 16%. The 2019 undercount is measurable, not hypothetical. The 2023 dip is a defect, not a market event.
A82: Transport mode from scene. eResponse.23. All EMS transports, not IFT-specific.
A83: Category | B83: 2019 | C83: 2020 | D83: 2021 | E83: 2022 | F83: 2023 | G83: 2024 | H83: Share 2019 | I83: Share 2024
A84: Non-Emergent | B84: 12514692 | C84: 15099744 | D84: 16331143 | E84: 17585742 | F84: 15203669 | G84: 18620902 | H84: =B84/B$88 -> 0.71710599 | I84: =G84/G$88 -> 0.65650263
A85: Emergent (Immediate Response) | B85: 4562512 | C85: 5399074 | D85: 6541606 | E85: 7190541 | F85: 6217885 | G85: 9350263 | H85: =B85/B$88 -> 0.26143709 | I85: =G85/G$88 -> 0.32965493
A86: Emergent Downgraded to Non-Emergent | B86: 290274 | C86: 297186 | D86: 353517 | E86: 345407 | F86: 259039 | G86: 277726 | H86: =B86/B$88 -> 0.016633028 | I86: =G86/G$88 -> 0.0097915691
A87: Non-Emergent Upgraded to Emergent | B87: 84185 | C87: 90818 | D87: 92328 | E87: 101260 | F87: 76794 | G87: 114898 | H87: =B87/B$88 -> 0.0048238956 | I87: =G87/G$88 -> 0.0040508692
A88: TOTAL | B88: =SUM(B84:B87) -> 17451663 | C88: =SUM(C84:C87) -> 20886822 | D88: =SUM(D84:D87) -> 23318594 | E88: =SUM(E84:E87) -> 25222950 | F88: =SUM(F84:F87) -> 21757387 | G88: =SUM(G84:G87) -> 28363789
A90: Roughly two thirds of all EMS transports run non-emergent. Non-emergent is the transport mode an interfacility book is built on, but this exhibit covers all EMS transports and cannot be cut to IFT alone in the public reports.
A92: Table metrics: withheld.
A93: No CAGR is computed on the activation series above: agency participation in the national EMS registry grew across the window, so a raw growth rate would measure reporting adoption, not demand (Fault_Audit item M). Coverage-adjusted reads only.

Sheet Medicare_PSPS
A1: Medicare fee-for-service ambulance transports by origin, destination and acuity, 2022 to 2024
A2: The question: what does Medicare fee-for-service actually pay for ambulance transport, at what acuity, between which endpoints? The Physician/Supplier Procedure Summary is the only public file carrying dollars, acuity, and origin-destination on the same row. This tab establishes the verified totals every later tab reconciles against.
A4: Panel A. Origin-destination pairs, all ambulance base-rate HCPCS (A0426, A0427, A0428, A0429, A0433, A0434)
A5: Modifier | B5: Origin and destination | C5: 2022 services | D5: 2023 services | E5: 2024 services | F5: 2024 share | G5: CAGR 2022-2024
A6: RH | B6: Residence to hospital | C6: 4205885 | D6: 3943393 | E6: 3898360 | F6: =E6/E$19 -> 0.36646551 | G6: =(E6/C6)^(1/2)-1 -> -0.037252778
A7: HN | B7: Hospital to SNF | C7: 1302158 | D7: 1264678 | E7: 1241883 | F7: =E7/E$19 -> 0.11674327 | G7: =(E7/C7)^(1/2)-1 -> -0.023418486
A8: NH | B8: SNF to hospital | C8: 1078203 | D8: 1125101 | E8: 1156363 | F8: =E8/E$19 -> 0.10870396 | G8: =(E8/C8)^(1/2)-1 -> 0.035611407
A9: SH | B9: Scene to hospital | C9: 931587 | D9: 908562 | E9: 903261 | F9: =E9/E$19 -> 0.08491109 | G9: =(E9/C9)^(1/2)-1 -> -0.015320447
A10: HH | B10: Hospital to hospital | C10: 825178 | D10: 837422 | E10: 871753 | F10: =E10/E$19 -> 0.08194918 | G10: =(E10/C10)^(1/2)-1 -> 0.027833823
A11: EH | B11: Residential or domiciliary to hospital | C11: 573302 | D11: 573609 | E11: 585441 | F11: =E11/E$19 -> 0.055034407 | G11: =(E11/C11)^(1/2)-1 -> 0.01053146
A12: HR | B12: Hospital to residence | C12: 506160 | D12: 474626 | E12: 480971 | F12: =E12/E$19 -> 0.0452137 | G12: =(E12/C12)^(1/2)-1 -> -0.025199967
A13: HE | B13: Hospital to residential or domiciliary | C13: 291045 | D13: 301141 | E13: 319041 | F13: =E13/E$19 -> 0.029991463 | G13: =(E13/C13)^(1/2)-1 -> 0.046991552
A14: RJ | B14: Residence to freestanding ESRD facility | C14: 314892 | D14: 224383 | E14: 214296 | F14: =E14/E$19 -> 0.020144905 | G14: =(E14/C14)^(1/2)-1 -> -0.17505267
A15: JR | B15: Freestanding ESRD facility to residence | C15: 312327 | D15: 221704 | E15: 210479 | F15: =E15/E$19 -> 0.019786088 | G15: =(E15/C15)^(1/2)-1 -> -0.1790823
A16: NJ | B16: SNF to freestanding ESRD facility | C16: 231910 | D16: 189813 | E16: 181501 | F16: =E16/E$19 -> 0.01706201 | G16: =(E16/C16)^(1/2)-1 -> -0.11533311
A17: JN | B17: Freestanding ESRD facility to SNF | C17: 227903 | D17: 186058 | E17: 177064 | F17: =E17/E$19 -> 0.016644909 | G17: =(E17/C17)^(1/2)-1 -> -0.11856536
B18: All other origin-destination pairs | C18: 458437 | D18: 420553 | E18: 397314 | F18: =E18/E$19 -> 0.03734952 | G18: =(E18/C18)^(1/2)-1 -> -0.069048399
B19: Total, origin-destination coded | C19: =SUM(C6:C18) -> 11258987 | D19: =SUM(D6:D18) -> 10671043 | E19: =SUM(E6:E18) -> 10637727 | G19: =(E19/C19)^(1/2)-1 -> -0.027980984
A20: The NJ and JN modifier labels are read from the CMS modifier convention (N = skilled nursing facility, J = freestanding ESRD facility). The source workbook left them unlabeled.
A22: Panel B. Hospital-to-hospital transports by acuity level. This is the only hard acuity evidence available for an interfacility book.
A23: HCPCS | B23: Acuity level | C23: RVU | D23: 2022 | E23: 2023 | F23: 2024 | G23: 2024 mix | H23: CAGR 2022-2024
A24: A0428 | B24: BLS, non-emergency | C24: 1 | D24: 332034 | E24: 328609 | F24: 338316 | G24: =F24/F$30 -> 0.38808699 | H24: =(F24/D24)^(1/2)-1 -> 0.0094155483
A25: A0426 | B25: ALS1, non-emergency | C25: 1.2 | D25: 203050 | E25: 199890 | F25: 205099 | G25: =F25/F$30 -> 0.23527192 | H25: =(F25/D25)^(1/2)-1 -> 0.0050328903
A26: A0427 | B26: ALS1, emergency | C26: 1.9 | D26: 152805 | E26: 163766 | F26: 172820 | G26: =F26/F$30 -> 0.19824423 | H26: =(F26/D26)^(1/2)-1 -> 0.063477284
A27: A0429 | B27: BLS, emergency | C27: 1.6 | D27: 76531 | E27: 83080 | F27: 91660 | G27: =F27/F$30 -> 0.10514446 | H27: =(F27/D27)^(1/2)-1 -> 0.094387773
A28: A0434 | B28: Specialty Care Transport | C28: 3.25 | D28: 53950 | E28: 55845 | F28: 57906 | G28: =F28/F$30 -> 0.066424779 | H28: =(F28/D28)^(1/2)-1 -> 0.036015036
A29: A0433 | B29: ALS2 | C29: 2.75 | D29: 6808 | E29: 6232 | F29: 5952 | G29: =F29/F$30 -> 0.006827622 | H29: =(F29/D29)^(1/2)-1 -> -0.064978305
B30: Total hospital-to-hospital | D30: =SUM(D24:D29) -> 825178 | E30: =SUM(E24:E29) -> 837422 | F30: =SUM(F24:F29) -> 871753 | H30: =(F30/D30)^(1/2)-1 -> 0.027833823
A32: Panel C. What Panel B settles
A33: Measure | B33: 2024 value | C33: Basis | D33: Why it matters
A34: Non-emergency BLS and ALS1 share of hospital-to-hospital transports | B34: =(F24+F25)/F30 -> 0.62335891 | C34: DERIVED | D34: Nearly two thirds of the Medicare interfacility book is scheduled, low-acuity work.
A35: Specialty Care Transport (A0434) share | B35: =F28/F30 -> 0.066424779 | C35: DERIVED | D35: Any unit-economics model that assumes an SCT-weighted rate mix is wrong on the Medicare book.
A36: ALS2 (A0433) share | B36: =F29/F30 -> 0.006827622 | C36: DERIVED | D36: ALS2 is the only hospital-to-hospital acuity tier shrinking in absolute terms.
A37: Emergent share (ALS1 emergency + BLS emergency) | B37: =(F26+F27)/F30 -> 0.30338869 | C37: DERIVED | D37: Emergent interfacility work is growing fastest but is still under a third of volume.
A38: Volume-weighted RVU of the hospital-to-hospital book | B38: =SUMPRODUCT(C24:C29,F24:F29)/F30 -> 1.449965 | C38: DERIVED | D38: Expressed as multiples of a BLS run (RVU 1.00). The Medicare interfacility book prices at roughly 1.45 BLS units, not 3.25.
A39: Hospital-to-hospital CAGR, 2022 to 2024 | B39: =(F30/D30)^(1/2)-1 -> 0.027833823 | C39: DERIVED | D39: Interfacility is gaining share of a shrinking Medicare fee-for-service book.
A40: All Medicare FFS ambulance CAGR, 2022 to 2024 | B40: =(E19/C19)^(1/2)-1 -> -0.027980984 | C40: DERIVED | D40: Total fee-for-service ambulance volume falls as enrollment shifts to Medicare Advantage.
A42: Limits. Carrier claims only. Hospital-owned ambulance departments bill institutionally and do not appear. Medicare fee-for-service only, a shrinking share as Medicare Advantage grows. Denied service counts are suppressed. The RVU column is Source S14 and is shown to weight the mix, not to compute dollars.
A44: Panel D. Real dollars. Allowed charges and Medicare payments on the hospital-to-hospital book, straight from the claims.
A45: HCPCS | B45: Acuity level | C45: RVU | D45: 2024 transports | E45: 2024 allowed charges | F45: Allowed per transport | G45: % of transports | H45: % of allowed $ | I45: Implied $ per RVU
A46: A0428 | B46: BLS, non-emergency | C46: 1 | D46: 338316 | E46: 84341334 | F46: =E46/D46 -> 249.2975 | G46: =D46/D$52 -> 0.38808699 | H46: =E46/E$52 -> 0.2637189 | I46: =E46/(D46*C46) -> 249.2975
A47: A0426 | B47: ALS1, non-emergency | C47: 1.2 | D47: 205099 | E47: 63019137 | F47: =E47/D47 -> 307.26204 | G47: =D47/D$52 -> 0.23527192 | H47: =E47/E$52 -> 0.19704855 | I47: =E47/(D47*C47) -> 256.0517
A48: A0427 | B48: ALS1, emergency | C48: 1.9 | D48: 172820 | E48: 82959184 | F48: =E48/D48 -> 480.03231 | G48: =D48/D$52 -> 0.19824423 | H48: =E48/E$52 -> 0.25939718 | I48: =E48/(D48*C48) -> 252.64859
A49: A0429 | B49: BLS, emergency | C49: 1.6 | D49: 91660 | E49: 35394905 | F49: =E49/D49 -> 386.15432 | G49: =D49/D$52 -> 0.10514446 | H49: =E49/E$52 -> 0.11067296 | I49: =E49/(D49*C49) -> 241.34645
A50: A0434 | B50: Specialty Care Transport | C50: 3.25 | D50: 57906 | E50: 49857835 | F50: =E50/D50 -> 861.01328 | G50: =D50/D$52 -> 0.066424779 | H50: =E50/E$52 -> 0.15589572 | I50: =E50/(D50*C50) -> 264.92716
A51: A0433 | B51: ALS2 | C51: 2.75 | D51: 5952 | E51: 4242888 | F51: =E51/D51 -> 712.85081 | G51: =D51/D$52 -> 0.006827622 | H51: =E51/E$52 -> 0.013266683 | I51: =E51/(D51*C51) -> 259.21848
B52: Total hospital-to-hospital base rate | D52: =SUM(D46:D51) -> 871753 | E52: =SUM(E46:E51) -> 3.1981528e+08 | F52: =E52/D52 -> 366.86456 | I52: =E52/SUMPRODUCT(C46:C51,D46:D51) -> 253.01616
A53: Allowed charges are for SUBMITTED services, which include denied lines carrying $0 allowed. Implied dollars per RVU therefore sit below the published conversion factor.
A55: Panel E. The complete hospital-to-hospital book: base rate plus mileage.
A56: Measure | B56: 2022 | C56: 2023 | D56: 2024 | E56: CAGR 2022-24 | F56: Basis | G56: Note
A57: Transports (submitted services) | B57: 825178 | C57: 837422 | D57: 871753 | E57: =(D57/B57)^(1/2)-1 -> 0.027833823 | F57: GOV-A | G57: Modifier HH, six ground base-rate HCPCS.
A58: Base-rate allowed charges | B58: 2.6703107e+08 | C58: 3.0139542e+08 | D58: 3.1981528e+08 | E58: =(D58/B58)^(1/2)-1 -> 0.094381413 | F58: GOV-A | G58: PSPS_ALLOWED_CHARGE_AMT.
A59: Ground mileage allowed charges (A0425) | B59: 2.2112537e+08 | C59: 2.4615002e+08 | D59: 2.5741304e+08 | E59: =(D59/B59)^(1/2)-1 -> 0.078936747 | F59: GOV-A | G59: Mileage is billed separately from the base rate.
A60: Loaded mileage units | B60: 28365136 | C60: 28610745 | D60: 29276711 | E60: =(D60/B60)^(1/2)-1 -> 0.015941516 | F60: GOV-A | G60: One unit is one loaded statute mile.
A61: TOTAL allowed charges | B61: =B58+B59 -> 4.8815644e+08 | C61: =C58+C59 -> 5.4754544e+08 | D61: =D58+D59 -> 5.7722832e+08 | E61: =(D61/B61)^(1/2)-1 -> 0.087412458 | F61: DERIVED | G61: The complete Medicare fee-for-service, carrier-billed, hospital-to-hospital ambulance book.
A62: Allowed per transport | B62: =B61/B57 -> 591.57714 | C62: =C61/C57 -> 653.8465 | D62: =D61/D57 -> 662.14664 | F62: DERIVED | G62: The single most useful unit-economics number in this workbook.
A63: Loaded miles per transport | B63: =B60/B57 -> 34.374566 | C63: =C60/C57 -> 34.165266 | D63: =D60/D57 -> 33.583723 | F63: DERIVED | G63: Interfacility transports run roughly three times the distance of a typical 911 scene run. This is the structural reason mileage is such a large share of the revenue.
A64: Allowed per loaded mile | B64: =B59/B60 -> 7.7956746 | C64: =C59/C60 -> 8.6034118 | D64: =D59/D60 -> 8.7924166 | F64: DERIVED | G64: CY2024 comes to $8.79 against the published CY2024 ground mileage rate of $8.76. An independent confirmation that this extraction and the published fee schedule agree.
A65: Mileage as a share of allowed dollars | B65: =B59/B61 -> 0.45298054 | C65: =C59/C61 -> 0.44955176 | D65: =D59/D61 -> 0.44594665 | F65: DERIVED | G65: Nearly half the Medicare revenue on an interfacility transport is mileage, not the base rate. Any model that prices only the base rate misses 45% of the revenue.
A66: Medicare payment as a share of allowed (base rate) | B66: =208324461.83/B58 -> 0.78015064 | C66: =234121042.06/C58 -> 0.7767903 | D66: =248559413.99/D58 -> 0.7771968 | F66: DERIVED | G66: Statute sets Part B at 80% of the approved amount after the deductible. The realized 77.7% is the deductible and secondary-payer drag. A clean internal validation of the claims pull.
A68: Panel F. Where the hospital-to-hospital book sits inside all Medicare carrier-billed ground ambulance.
A69: Measure | B69: 2022 | C69: 2023 | D69: 2024 | E69: Basis | F69: Note
A70: All ground ambulance allowed charges (base + mileage, all origin-destination pairs) | B70: 4753662348 | C70: 4992692676 | D70: 5073090003 | E70: GOV-A | F70: Six ground base-rate HCPCS plus A0425. Carrier claims only.
A71: All ground ambulance Medicare payments (NCH) | B71: 3722057066 | C71: 3892079508 | D71: 3957457371 | E71: GOV-A | F71: MedPAC reports $3.9B of Medicare FFS ambulance program spending in 2022 (Payment Basics, excluding beneficiary cost sharing) and $5.3B of total Medicare payments for AFS-covered transports in 2024 (June 2026 mandated report). The claims say carrier-billed GROUND program payments were $3.72B in 2022 and $3.96B in 2024; adding air ambulance takes 2022 to $4.20B. So the 2022 figure cannot be all-ambulance program payments. MedPAC does not state the scope of either measure. See Panel G.
A72: Hospital-to-hospital share of all ground allowed dollars | B72: =B61/B70 -> 0.1026906 | C72: =C61/C70 -> 0.10966937 | D72: =D61/D70 -> 0.11378239 | E72: DERIVED | F72: Interfacility is roughly one ninth of the Medicare fee-for-service carrier ground ambulance dollar, and it is growing while the whole is flat.
A73: Hospital-to-hospital share of all origin-destination-coded transports | B73: =C10/C19 -> 0.073290608 | C73: =D10/D19 -> 0.078476115 | D73: =E10/E19 -> 0.08194918 | E73: DERIVED | F73: Higher dollar share than volume share: interfacility transports are longer and higher acuity than the average Medicare ambulance run.
A75: The two MedPAC spend figures do NOT reconcile cleanly against the claims, and an earlier version of this workbook said they did. That claim is withdrawn. What the claims support is stated in Panel G below.
A76: Suppression. CMS masks any cell with fewer than 11 services. In 2024, 24,781 of the origin-destination-coded rows are suppressed. The maximum hidden volume is therefore about 263,000 services, or 2.5% of the 10,637,727 counted. Every figure on this tab is a floor by that margin.
A77: Reproduce: GET https://data.cms.gov/data-api/revision 1/dataset/164fc736-4179-4100-9f79-592b69e41975/data?filter[HCPCS_CD]=A0428 (2024). Dataset UUIDs: 2022 e4786716-10e9-40f2-b936-7444177474d5, 2023 b72adfb6-22cf-4241-9c64-050ad9061e03, 2024 164fc736-4179-4100-9f79-592b69e41975.
A79: Panel G. Reconciling MedPAC's published spend figures against the raw claims. Stated honestly.
A80: Measure | B80: 2022 | C80: 2024 | D80: What it covers
A81: Carrier-billed GROUND ambulance, Medicare paid | B81: 3722057066 | C81: 3957457371 | D81: Six ground base HCPCS plus A0425 mileage, all modifiers. PSPS.
A82: Carrier-billed AIR ambulance and paramedic intercept, Medicare paid | B82: 475678985 | C82: 510451782 | D82: A0430, A0431, A0435, A0436, A0432. PSPS.
A83: All AFS-covered carrier claims, Medicare paid | B83: =B81+B82 -> 4197736051 | C83: =C81+C82 -> 4467909153 | D83: Sum of the two rows above. Institutionally billed ambulance is NOT in PSPS and is therefore excluded.
A84: All AFS-covered carrier claims, allowed charges | B84: 5345638073 | C84: 5712334320 | D84: Program payment plus beneficiary cost sharing, plus non-covered allowed amounts.
A85: MedPAC published figure | B85: 3900000000 | C85: 5300000000 | D85: 2022: 'program spending, not including beneficiary cost sharing' (Payment Basics). 2024: 'total Medicare payments for AFS-covered transports' (June 2026 Ch.6). Different measures, different years.
A86: MedPAC transports | C86: 11300000 | D86: 2024. Carrier-billed base-rate transports in PSPS total about 10.76M, or 95% of this.
A87: MedPAC implied payment per transport | C87: =C85/C86 -> 469.02655 | D87: 2024. Sits between the claims-derived $415 program payment and $531 allowed charge per transport.
A89: Conclusion. MedPAC's 2024 figure of $5.3B lies between the carrier-claims program payment of $4.47B and the allowed charge of $5.71B, consistent with a payment measure that includes institutionally billed ambulance (absent from PSPS) or some beneficiary cost sharing. MedPAC's 2022 figure of $3.9B lies BELOW the carrier-claims ground-plus-air program payment of $4.20B, so it cannot be all-ambulance program spending on the same basis; it is consistent with ground-only. Neither document states its scope. Quote each figure with its own label and do not combine them.

Sheet Medicare_IFT_Series
A1: Medicare interfacility ambulance, 2010 to 2024. Fifteen years, rebuilt from raw CMS claims.
A2: The question: is the Medicare hospital-to-hospital book growing or shrinking? No published table contains this series, so it was built by pulling fifteen annual claim files and filtering the hospital-to-hospital modifier. The overlap years reproduce the verified totals exactly.
A4: Year | B4: Transports | C4: Base-rate allowed $ | D4: Mileage allowed $ | E4: TOTAL allowed $ | F4: Medicare paid $ | G4: Allowed per transport | H4: Loaded miles per transport | I4: Allowed per loaded mile | J4: Volume-weighted RVU | K4: SCT share of transports | L4: Non-emergency BLS share of transports
A5: 2010 | B5: 937317 | C5: 2.7151222e+08 | D5: 2.0520989e+08 | E5: =C5+D5 -> 4.7672211e+08 | F5: 3.7780025e+08 | G5: =E5/B5 -> 508.60286 | H5: =29644494/B5 -> 31.626967 | I5: =D5/29644494 -> 6.9223611 | J5: =1379672.2/B5 -> 1.4719377 | K5: =68529/B5 -> 0.073111871 | L5: =361191/B5 -> 0.38534562
A6: 2011 | B6: 978653 | C6: 2.8575113e+08 | D6: 2.1543794e+08 | E6: =C6+D6 -> 5.0118908e+08 | F6: 3.9746225e+08 | G6: =E6/B6 -> 512.12133 | H6: =31074806/B6 -> 31.752629 | I6: =D6/31074806 -> 6.9328814 | J6: =1441030.9/B6 -> 1.4724636 | K6: =72106/B6 -> 0.073678822 | L6: =376923/B6 -> 0.38514468
A7: 2012 | B7: 1017527 | C7: 2.933744e+08 | D7: 2.2798949e+08 | E7: =C7+D7 -> 5.2136389e+08 | F7: 4.1392031e+08 | G7: =E7/B7 -> 512.38335 | H7: =32452094/B7 -> 31.893104 | I7: =D7/32452094 -> 7.025417 | J7: =1495763.8/B7 -> 1.4699991 | K7: =73595/B7 -> 0.072327319 | L7: =387619/B7 -> 0.38094223
A8: 2013 | B8: 1027279 | C8: 3.0281176e+08 | D8: 2.3605461e+08 | E8: =C8+D8 -> 5.3886637e+08 | F8: 4.2110414e+08 | G8: =E8/B8 -> 524.55698 | H8: =33300724/B8 -> 32.416436 | I8: =D8/33300724 -> 7.088573 | J8: =1506968.9/B8 -> 1.4669519 | K8: =74238/B8 -> 0.072266638 | L8: =390732/B8 -> 0.38035626
A9: 2014 | B9: 1059917 | C9: 3.1570798e+08 | D9: 2.4925909e+08 | E9: =C9+D9 -> 5.6496707e+08 | F9: 4.3957317e+08 | G9: =E9/B9 -> 533.02954 | H9: =34674222/B9 -> 32.714092 | I9: =D9/34674222 -> 7.1885992 | J9: =1550865.8/B9 -> 1.4631955 | K9: =74877/B9 -> 0.070644211 | L9: =399221/B9 -> 0.37665308
A10: 2015 | B10: 1092979 | C10: 3.2774262e+08 | D10: 2.6366431e+08 | E10: =C10+D10 -> 5.9140693e+08 | F10: 4.6041689e+08 | G10: =E10/B10 -> 541.09634 | H10: =36424053/B10 -> 33.325483 | I10: =D10/36424053 -> 7.2387416 | J10: =1595229.5/B10 -> 1.4595244 | K10: =74817/B10 -> 0.068452367 | L10: =401982/B10 -> 0.36778566
A11: 2016 | B11: 1118830 | C11: 3.3327841e+08 | D11: 2.7447582e+08 | E11: =C11+D11 -> 6.0775423e+08 | F11: 4.7273613e+08 | G11: =E11/B11 -> 543.20516 | H11: =38038343/B11 -> 33.998322 | I11: =D11/38038343 -> 7.2157671 | J11: =1626320.6/B11 -> 1.4535904 | K11: =74944/B11 -> 0.06698426 | L11: =412563/B11 -> 0.36874503
A12: 2017 | B12: 1139524 | C12: 3.4134014e+08 | D12: 2.8629178e+08 | E12: =C12+D12 -> 6.2763192e+08 | F12: 4.8816254e+08 | G12: =E12/B12 -> 550.78429 | H12: =39229705/B12 -> 34.426396 | I12: =D12/39229705 -> 7.2978316 | J12: =1659634.1/B12 -> 1.4564275 | K12: =77956/B12 -> 0.068411021 | L12: =411088/B12 -> 0.36075414
A13: 2018 | B13: 1126991 | C13: 3.4267142e+08 | D13: 2.9147183e+08 | E13: =C13+D13 -> 6.3414326e+08 | F13: 4.9328862e+08 | G13: =E13/B13 -> 562.68706 | H13: =39487791/B13 -> 35.038249 | I13: =D13/39487791 -> 7.3813152 | J13: =1638666.7/B13 -> 1.4540193 | K13: =76337/B13 -> 0.067735235 | L13: =406725/B13 -> 0.36089463
A14: 2019 | B14: 1121589 | C14: 3.4748435e+08 | D14: 2.9826351e+08 | E14: =C14+D14 -> 6.4574786e+08 | F14: 5.0256693e+08 | G14: =E14/B14 -> 575.74375 | H14: =39448551/B14 -> 35.17202 | I14: =D14/39448551 -> 7.5608229 | J14: =1630111.3/B14 -> 1.4533945 | K14: =77375/B14 -> 0.068986946 | L14: =405665/B14 -> 0.36168775
A15: 2020 | B15: 968422 | C15: 3.0447881e+08 | D15: 2.6181546e+08 | E15: =C15+D15 -> 5.6629427e+08 | F15: 4.4625298e+08 | G15: =E15/B15 -> 584.75982 | H15: =34356468/B15 -> 35.476753 | I15: =D15/34356468 -> 7.6205581 | J15: =1408637.5/B15 -> 1.4545699 | K15: =69269/B15 -> 0.071527702 | L15: =355880/B15 -> 0.36748442
A16: 2021 | B16: 887312 | C16: 2.7357205e+08 | D16: 2.3353083e+08 | E16: =C16+D16 -> 5.0710288e+08 | F16: 4.0220926e+08 | G16: =E16/B16 -> 571.50459 | H16: =31226720/B16 -> 35.192491 | I16: =D16/31226720 -> 7.4785578 | J16: =1277688.1/B16 -> 1.4399536 | K16: =61471/B16 -> 0.069277774 | L16: =343085/B16 -> 0.38665655
A17: 2022 | B17: 825178 | C17: 2.6703107e+08 | D17: 2.2112537e+08 | E17: =C17+D17 -> 4.8815644e+08 | F17: 3.8251813e+08 | G17: =E17/B17 -> 591.57714 | H17: =28365136/B17 -> 34.374566 | I17: =D17/28365136 -> 7.7956746 | J17: =1182532.6/B17 -> 1.4330637 | K17: =53950/B17 -> 0.065379833 | L17: =332034/B17 -> 0.40237864
A18: 2023 | B18: 837422 | C18: 3.0139542e+08 | D18: 2.4615002e+08 | E18: =C18+D18 -> 5.4754544e+08 | F18: 4.2665499e+08 | G18: =E18/B18 -> 653.8465 | H18: =28610745/B18 -> 34.165266 | I18: =D18/28610745 -> 8.6034118 | J18: =1211194.6/B18 -> 1.4463372 | K18: =55845/B18 -> 0.066686808 | L18: =328609/B18 -> 0.3924055
A19: 2024 | B19: 871753 | C19: 3.1981528e+08 | D19: 2.5741304e+08 | E19: =C19+D19 -> 5.7722832e+08 | F19: 4.4993599e+08 | G19: =E19/B19 -> 662.14664 | H19: =29276711/B19 -> 33.583723 | I19: =D19/29276711 -> 8.7924166 | J19: =1264011.3/B19 -> 1.449965 | K19: =57906/B19 -> 0.066424779 | L19: =338316/B19 -> 0.38808699
A21: What the fifteen-year view says that the three-year view does not.
A22: Measure | B22: Value | C22: Basis | D22: Read
A23: Peak year for Medicare FFS interfacility transports | B23: 2017 | C23: DERIVED | D23: 1,139,524 transports. Every year since has been lower.
A24: Transports, 2024 against the 2017 peak | B24: =B19/B12-1 -> -0.23498496 | C24: DERIVED | D24: The Medicare fee-for-service interfacility book is a quarter smaller than it was in 2017.
A25: Transport CAGR, 2010 to 2017 | B25: =(B12/B5)^(1/7)-1 -> 0.028299368 | C25: DERIVED | D25: Real growth in the pre-COVID, pre-Medicare-Advantage-surge era.
A26: Transport CAGR, 2017 to 2024 | B26: =(B19/B12)^(1/7)-1 -> -0.037542802 | C26: DERIVED | D26: The reversal. Medicare Advantage enrolment crossing 50% is the dominant driver, not demand.
A27: Transport CAGR, 2022 to 2024 | B27: =(B19/B17)^(1/2)-1 -> 0.027833823 | C27: DERIVED | D27: CAUTION. This is the recovery off the 2022 trough, not a growth rate. Quoting it as trend is the single easiest mistake to make with this series.
A28: Total allowed CAGR, 2010 to 2024 | B28: =(E19/E5)^(1/14)-1 -> 0.01375837 | C28: DERIVED | D28: Dollars grew while transports shrank.
A29: Total allowed CAGR, 2022 to 2024 | B29: =(E19/E17)^(1/2)-1 -> 0.087412458 | C29: DERIVED | D29: Again a trough-to-peak artefact. Never annualise it forward.
A30: Allowed per transport CAGR, 2010 to 2024 | B30: =(G19/G5)^(1/14)-1 -> 0.019022929 | C30: DERIVED | D30: Below the 3.0% average Ambulance Inflation Factor over the same window. Realised rate growth lags the statutory update.
A31: Allowed per loaded mile CAGR, 2010 to 2024 | B31: =(I19/I5)^(1/14)-1 -> 0.017227619 | C31: DERIVED | D31: $6.92 in 2010 to $8.79 in 2024.
A32: Mileage as a share of allowed dollars, 2010 | B32: =D5/E5 -> 0.4304602 | C32: DERIVED | D32: Mileage has been roughly 43-45% of Medicare interfacility revenue for fifteen straight years.
A33: Mileage as a share of allowed dollars, 2024 | B33: =D19/E19 -> 0.44594665 | C33: DERIVED | D33: Stable. Any model that prices only the base rate has been wrong for fifteen years, not just recently.
A34: Volume-weighted RVU, 2010 | B34: =J5 -> 1.4719377 | C34: DERIVED | D34: 1.472.
A35: Volume-weighted RVU, 2024 | B35: =J19 -> 1.449965 | C35: DERIVED | D35: 1.450. The Medicare interfacility acuity mix has moved by 1.5% in fifteen years.
A36: SCT share of transports, range 2010 to 2024 | B36: 6.5% to 7.4% | C36: DERIVED | D36: A 0.9 point band across fifteen years. There is no acuity escalation in the Medicare interfacility book, and there never was.
A37: Medicare paid as a share of allowed, 2024 | B37: =F19/E19 -> 0.77947663 | C37: DERIVED | D37: Statute sets Part B at 80% after the deductible. 77.9% realised. Stable across the whole series.
A39: Suppression. CMS masks any cell with fewer than 11 services. Suppressed rows were excluded from the sums, not imputed, so every figure here is a floor. The masked share of hospital-to-hospital volume is on the order of 2%.
A40: Scope. Carrier claims only. Hospital-owned ambulance departments bill institutionally and never enter PSPS. Medicare Advantage is entirely absent. The commercial book is not measured.
A41: Reproduce: GET https://data.cms.gov/data-api/revision 1/dataset/{uuid}/data?filter[HCPCS_INITIAL_MODIFIER_CD]=HH, one dataset per year, then aggregate A0426, A0427, A0428, A0429, A0433, A0434 (base) and A0425 (mileage). Pre-2021 files drop the PSPS_ prefix on the amount fields.
A43: Table metrics
A44: CAGR, transports, 2010 to 2024 | B44: =(B19/B5)^(1/14)-1 -> -0.0051662809
A45: CAGR, transports, 2019 to 2024 | B45: =(B19/B14)^(1/5)-1 -> -0.049150151
A46: CAGR, allowed dollars, 2010 to 2024 | B46: =(G19/G5)^(1/14)-1 -> 0.019022929
A47: Peak year, transports | B47: =INDEX(A5:A19,MATCH(MAX(B5:B19),B5:B19,0)) -> 2017
A48: Decline from peak to 2024 | B48: =B19/MAX(B5:B19)-1 -> -0.23498496
A49: HH share of ground, change 2010 to 2024 (points) | B49: =(K19-K5)*100 -> -0.66870929
A50: All figures computed from the series above. Book-level CAGRs are payer-window figures: the per-beneficiary rates on Utilization_Normalized carry the demand signal.

Sheet Medicare_OD_Matrix
A1: The complete Medicare origin-destination dollar map, 2019 to 2024
A2: The question: where does the entire Medicare ambulance dollar go, pair by pair? The complete origin-destination map, rebuilt from 392,409 raw claim-summary rows and reconciling to the prior extraction to the cent. The headline surprise: the nursing-facility interface, not the hospital pair, is the largest facility-to-facility channel.
A4: Panel A. 2024, all origin-destination pairs with at least 20,000 transports, ranked by volume. Ground base HCPCS (A0426-A0434) plus A0425 mileage.
A5: Pair | B5: Origin and destination | C5: Transports 2024 | D5: Base allowed $ 2024 | E5: Mileage allowed $ 2024 | F5: Total allowed $ 2024 | G5: % of transports | H5: % of total allowed $ | I5: Allowed per transport | J5: Transports 2019 | K5: CAGR 2019-2024 | L5: Allowed dollars per transport | M5: Share of top-pairs volume shown
A6: RH | B6: Residence to hospital | C6: 3898371.1 | D6: 1.7992955e+09 | E6: 2.9542346e+08 | F6: =D6+E6 -> 2.094719e+09 | G6: =C6/$C$23 -> 0.3664652 | H6: =F6/$F$23 -> 0.4142871 | I6: =F6/C6 -> 537.33186 | J6: 4718340.5 | K6: =(C6/J6)^(1/5)-1 -> -0.037460014 | L6: =D6/C6 -> 461.5506 | M6: =C6/SUM(C$6:C$15) -> 0.39449698
A7: HN | B7: Hospital to SNF | C7: 1241885.3 | D7: 3.2247721e+08 | E7: 1.1193705e+08 | F7: =D7+E7 -> 4.3441426e+08 | G7: =C7/$C$23 -> 0.11674305 | H7: =F7/$F$23 -> 0.08591712 | I7: =F7/C7 -> 349.80224 | J7: 1580733.3 | K7: =(C7/J7)^(1/5)-1 -> -0.047106034 | L7: =D7/C7 -> 259.66746 | M7: =C7/SUM(C$6:C$15) -> 0.125673
A8: NH | B8: SNF to hospital | C8: 1156367.8 | D8: 5.1577992e+08 | E8: 69140892 | F8: =D8+E8 -> 5.8492081e+08 | G8: =C8/$C$23 -> 0.10870401 | H8: =F8/$F$23 -> 0.11568384 | I8: =F8/C8 -> 505.82592 | J8: 1294036.2 | K8: =(C8/J8)^(1/5)-1 -> -0.022245299 | L8: =D8/C8 -> 446.03449 | M8: =C8/SUM(C$6:C$15) -> 0.11701903
A9: SH | B9: Scene to hospital | C9: 903261.9 | D9: 4.1225031e+08 | E9: 57977015 | F9: =D9+E9 -> 4.7022733e+08 | G9: =C9/$C$23 -> 0.084910862 | H9: =F9/$F$23 -> 0.09300012 | I9: =F9/C9 -> 520.58803 | J9: 1256939.4 | K9: =(C9/J9)^(1/5)-1 -> -0.063948227 | L9: =D9/C9 -> 456.40175 | M9: =C9/SUM(C$6:C$15) -> 0.091405892
A10: HH | B10: Hospital to hospital | C10: 871758.5 | D10: 3.1981528e+08 | E10: 2.5741304e+08 | F10: =D10+E10 -> 5.7722832e+08 | G10: =C10/$C$23 -> 0.081949395 | H10: =F10/$F$23 -> 0.11416245 | I10: =F10/C10 -> 662.14247 | J10: 1121595.8 | K10: =(C10/J10)^(1/5)-1 -> -0.049150104 | L10: =D10/C10 -> 366.86225 | M10: =C10/SUM(C$6:C$15) -> 0.088217895
A11: EH | B11: Residential/domiciliary to hospital | C11: 585443.5 | D11: 2.6392229e+08 | E11: 31651727 | F11: =D11+E11 -> 2.9557402e+08 | G11: =C11/$C$23 -> 0.055034439 | H11: =F11/$F$23 -> 0.058457723 | I11: =F11/C11 -> 504.87198 | J11: 678822.4 | K11: =(C11/J11)^(1/5)-1 -> -0.02916424 | L11: =D11/C11 -> 450.80745 | M11: =C11/SUM(C$6:C$15) -> 0.059244152
A12: HR | B12: Hospital to residence | C12: 480973.3 | D12: 1.1933414e+08 | E12: 45741567 | F12: =D12+E12 -> 1.6507571e+08 | G12: =C12/$C$23 -> 0.04521375 | H12: =F12/$F$23 -> 0.032648167 | I12: =F12/C12 -> 343.21179 | J12: 530997.3 | K12: =(C12/J12)^(1/5)-1 -> -0.019594518 | L12: =D12/C12 -> 248.1097 | M12: =C12/SUM(C$6:C$15) -> 0.048672255
