Workbook

Sheet ReadMe
A1: Komodo Calibration v1 - the licensed extract read against the public evidence base
A2: Purpose: calibrate the Komodo Health ambulance claims extract (calendar 2025) against the verified public benchmarks in the IFT master, and package what the extract is good for - the Medicare capture / gross-up factor, the commercial realized-price multiples, the estimated-allowed disclosure, the institutional-lines verdict, and the payer mix - for the sizing team. Every test panel is live: it computes now from the transcribed inputs, and recomputes the moment the raw file overwrites Observed_Inputs.
A4: Firewall - read this before anything else
A5: The Komodo extract is LICENSED, commercial engagement data. It NEVER enters IFT_Sourced_Evidence_Master and is never cited by, linked from, or merged into it. The flow is one-way and permanent: master -> calibration. This workbook IMPORTS public benchmark values from the master (as values, each carrying its fact ID or source tab) and returns nothing. A leak check logged on Run_Log confirms zero Komodo-derived values exist anywhere in the master or its repo. Keep it that way.
A7: The three extract caveats - preserved on every output panel
A8: 1 | B8: Members without a listed line of business or state were excluded from the extract (under 1 percent of claims).
A9: 2 | B9: Codes are not mutually exclusive to claim status (Open / Closed / Combined); a code can appear across statuses.
A10: 3 | B10: Multiple codes can appear on one claim, so grand totals may not align to the code breakdown. T10 defines the counting rule that removes this ambiguity downstream.
A12: How to read the tabs
A13: Benchmarks_Public | B13: The public pack imported from the master: volume floors and wedges, price benchmarks, and calibrators - each with its fact ID / source tab. Values only; nothing computed from Komodo.
A14: Observed_Inputs (T1) | B14: The extract headline and per-code values. Currently the visual transcription, flagged PROVISIONAL and bordered; T1 re-derives every one from the raw file. All test panels reference these cells, so overwriting them here recomputes everything.
A15: T2 - T10 | B15: One panel per test. Live formulas, the interpretation and the caveat printed in-row. Bordered PENDING marks a value that needs the raw file (an obscured transcription cell, a payer/code split, a geographic filter, or a metadata field).
A16: GrossUp_Factors | B16: The T2 Medicare capture rate packaged as the candidate gross-up for the sizing team, every assumption listed.
A17: Commercial_Rate_Table | B17: The T3 commercial multiples packaged - the measured replacement for the interim FAIR bound and statutory pegs.
A18: Calibration_Memo | B18: One page for Ray: what the extract is good for and the three things it cannot see. Also shipped as a standalone .md.
A19: Run_Log | B19: Build metadata, the raw-file hash slot, and the master-untouched leak-check result.

Sheet Benchmarks_Public
A1: Public benchmark pack - imported from the master as values, with fact IDs
A2: Every value here is a verified public figure carried from IFT_Sourced_Evidence_Master v4.2. Nothing on this tab is computed from Komodo. The test panels reference these cells; they are the fixed side of every calibration.
A4: Volume floors and wedges
A5: Benchmark | B5: Value | C5: Unit | D5: Master source (fact ID / tab) | E5: Note
A6: Medicare FFS carrier ground base-code transports, 2023 | B6: 10718468 | C6: transports | D6: Medicare_OD_Matrix; Modifier_QM_QN_Series | E6: The QM/QN carrier denominator (base codes, O-D coded).
A7: Medicare FFS carrier ground base-code transports, 2024 | B7: 10637766 | C7: transports | D7: F111 (Medicare_OD_Matrix) | E7: The carrier-visible FFS floor used in the T2 reconstruction.
A8: MedPAC all-AFS Medicare transports, 2023 | B8: 11300000 | C8: transports | D8: F88 (MedPAC_2026_Mandated) | E8: Use the master 11.3M, not the 11.4M preliminary. Payments $5.3B.
A9: Institutional (hospital-outpatient) wedge, 2023 | B9: 581532 | C9: transports | D9: F620 (Institutional_Ambulance_Wedge) | E9: 5.15 percent of the Medicare AFS book; off-carrier FFS.
A10: Dark share (beneficiaries outside carrier-visible FFS), 2024 | B10: 0.593 | C10: share | D10: F558 (Imbalance_Ledger) | E10: MA and other. FFS carrier-visible share = 1 - this = 0.407.
A11: NEMSIS hospital-to-hospital activations, 2024 | B11: 5510664 | C11: activations | D11: EMS_Transports; Service_Level_Economics | E11: Activations, not Medicare claims; a demand-side ceiling.
A12: NEMSIS all facility-to-facility activations, 2024 | B12: 7512656 | C12: activations | D12: Service_Level_Economics; Cross_Source_Recon | E12: The widest facility-to-facility activation count.
A13: Hospital-to-hospital Medicare FFS carrier transports, 2024 | B13: 871753 | C13: transports | D13: Medicare_PSPS | E13: The carrier-visible H2H slice; a floor for the IFT subset.
A15: Price benchmarks
A16: Benchmark | B16: Value | C16: Unit | D16: Master source (fact ID / tab) | E16: Note
A17: Ground ambulance conversion factor, CY2024 | B17: 272.44 | C17: $ | D17: Payment_Rules B32 (GOV-A) | E17: Multiplies the RVU to produce the base allowed, pre-geography.
A18: Ground ambulance conversion factor, CY2026 | B18: 284.56 | C18: $ | D18: Payment_Rules (GOV-A) | E18: Published CY2026 CF.
A19: Ambulance Inflation Factor, CY2025 | B19: 0.024 | C19: per yr | D19: Payment_Rules (GOV-A) | E19: CY2025 CF = CY2024 x (1 + this); see the per-code table.
A20: Ground mileage rate (A0425), CY2024 | B20: 8.76 | C20: $/mile | D20: Payment_Rules B33 (GOV-A) | E20: Paid separately from the base rate.
A21: Ground ambulance conversion factor, CY2025 (AIF-stepped) | B21: =Benchmarks_Public!B17*(1+Benchmarks_Public!B19) -> 278.97856 | C21: $ | D21: DERIVED from Payment_Rules | E21: CY2024 CF stepped by the CY2025 AIF.
A23: Per-code fee-schedule and realized-allowed benchmarks (2024)
A24: HCPCS (level of service) | B24: RVU | C24: Fee-schedule allowed (CF2024 x RVU) | D24: Realized national allowed | E24: Source / note
A25: A0426 ALS1 non-emergency | B25: 1.2 | C25: =Benchmarks_Public!B17*B25 -> 326.928 | D25: 327.72 | E25: CMS AFS RVU (Payment_Rules); realized = MUP_Ambulance_National avg allowed 2024
A26: A0427 ALS1 emergency | B26: 1.9 | C26: =Benchmarks_Public!B17*B26 -> 517.636 | D26: 522.51 | E26: CMS AFS RVU (Payment_Rules); realized = MUP_Ambulance_National avg allowed 2024
A27: A0428 BLS non-emergency | B27: 1 | C27: =Benchmarks_Public!B17*B27 -> 272.44 | D27: 260.65 | E27: CMS AFS RVU (Payment_Rules); realized = MUP_Ambulance_National avg allowed 2024
A28: A0429 BLS emergency | B28: 1.6 | C28: =Benchmarks_Public!B17*B28 -> 435.904 | D28: 446.94 | E28: CMS AFS RVU (Payment_Rules); realized = MUP_Ambulance_National avg allowed 2024
A29: A0433 ALS2 | B29: 2.75 | C29: =Benchmarks_Public!B17*B29 -> 749.21 | D29: 753.58 | E29: CMS AFS RVU (Payment_Rules); realized = MUP_Ambulance_National avg allowed 2024
A30: A0434 Specialty Care Transport | B30: 3.25 | C30: =Benchmarks_Public!B17*B30 -> 885.43 | D30: 918.36 | E30: CMS AFS RVU (Payment_Rules); realized = MUP_Ambulance_National avg allowed 2024
A31: RVU note: A0426 (ALS1 non-emergency) = 1.20 per the master Payment_Rules (GOV-A). The calibration order lists 1.75 for A0426; that is the A0432 paramedic-intercept RVU and is not used here. The master governs. A0433 = 2.75 and A0434 = 3.25 are the CMS AFS ALS2 and SCT values.
A33: Calibrators and quality references
A34: Benchmark | B34: Value | C34: Unit | D34: Master source (fact ID / tab) | E34: Note
A35: Measured BLS-NE avg Medicare allowed, 2024, largest subject NPI | B35: 265.34 | C35: $/claim | D35: MUP_Providers_2024 (live CMS API verified) | E35: A sanity point against A0428 realized allowed ($260.65 national).
A36: MA-to-FFS ambulance revenue ratio per organization | B36: 1.038 | C36: x | D36: F557 (MA_Book_Calibrator; GADCS 2.30) | E36: MA rev/org $1,238,482 vs FFS $1,193,046. A pricing calibrator, not a volume ratio.
A37: GADCS cost per transport, mean | B37: 2673 | C37: $/transport | D37: GADCS (Cost_and_Capacity) | E37: Median $1,340. Cost, not price.
A38: GADCS cost per transport, median | B38: 1340 | C38: $/transport | D38: GADCS (Cost_and_Capacity) | E38: Skewed mean vs median.
A39: BLS-NE Medicare denial rate, 2024 | B39: 0.129 | C39: share | D39: PSPS_Denial_Series; Throughput_Economics_Public | E39: Context for closed-claim behavior.
A40: Ambulance organizations reporting facility-pay revenue | B40: 0.186 | C40: share | D40: F443 (Facility_Pay_Layer) | E40: Volume that NO claims dataset contains; a reminder, not an input.
A41: Also carried as qualitative reminders (no single value): the one-in-five did-not-always-bill incidence, the FAIR-derived ~1.6x commercial bound and the statutory balance-billing pegs being SUPERSEDED by T3, and the footprint-state Medicaid fee-schedule base rates (NE A0428 $154.89 / A0426 $387.24 / A0434 $387.24; IA $84.67 / $101.60 / $232.84) on the master Medicaid_Rate_Card. No national Medicaid benchmark exists.

Sheet Observed_Inputs
A1: Observed inputs (T1 parser fidelity) - the extract as transcribed, PROVISIONAL until the raw file confirms it
A2: Every value below is a visual transcription from the shared view, flagged PROVISIONAL and bordered. T1 re-derives each one from the raw file: on landing, overwrite these cells and hash the file on Run_Log. Every test panel references these cells, so the whole workbook recomputes from here. Cells marked PENDING were obscured in the view and must come from the raw file.
A4: Grand totals
A5: Metric | B5: Claims | C5: Reported $ | D5: Estimated $ | E5: Combined $
A6: All codes, all payers | B6: 47061988 | C6: 9435317565 | D6: 12536776941 | E6: 14320080327
A8: Payer totals (all codes)
A9: Payer | B9: Claims | C9: Combined $
A10: Commercial | B10: 8044685 | C10: 4019680332
A11: Medicare | B11: 28660137 | C11: 7885341451
A12: Medicaid | B12: 10357334 | C12: 2415058544
A14: Claim maturity (all codes, all payers)
A15: Status | B15: Claims | C15: Combined $
A16: Open | B16: 37710269 | C16: 11410000000
A17: Closed | B17: 9351749 | C17: 2910000000
A18: Open/Closed combined dollars ($11.41B / $2.91B) were rounded in the shared view; T1 takes exact figures from the raw file.
A20: Per-code grid (Combined $ unless noted; PENDING = obscured in the view, from raw file)
A21: HCPCS | B21: Total claims | C21: Total combined $ | D21: Comm claims | E21: Comm combined $ | F21: Mcare claims | G21: Mcare combined $ | H21: Mcaid claims | I21: Mcaid combined $
A22: A0425 | B22: 24881351 | C22: PENDING | D22: PENDING | E22: PENDING | F22: 14723330 | G22: PENDING | H22: PENDING | I22: PENDING
A23: A0426 | B23: 632029 | C23: 259868460 | D23: 153934 | E23: 96400641 | F23: 388782 | G23: 132434413 | H23: PENDING | I23: PENDING
A24: A0427 | B24: 8919408 | C24: 5250804433 | D24: PENDING | E24: PENDING | F24: 5376326 | G24: 2841911845 | H24: PENDING | I24: PENDING
A25: A0428 | B25: 5409977 | C25: 1826100921 | D25: 539246 | E25: 287519936 | F25: 4178527 | G25: 1327883745 | H25: 692218 | I25: 210697240
A26: A0429 | B26: PENDING | C26: PENDING | D26: PENDING | E26: PENDING | F26: PENDING | G26: PENDING | H26: PENDING | I26: PENDING
A27: A0433 | B27: PENDING | C27: PENDING | D27: PENDING | E27: PENDING | F27: PENDING | G27: PENDING | H27: PENDING | I27: PENDING
A28: A0434 | B28: 262139 | C28: 329191232 | D28: 69191 | E28: 152729421 | F28: 140010 | G28: 137165403 | H28: 52938 | I28: 39296408
A30: T1 re-derivation (raw file)
A31: Raw-file re-derivation status | B31: PENDING - Andrew delivers the raw extract; T1 recomputes every cell above and explains any discrepancy before downstream panels are trusted.
A32: Raw-file SHA-256 | B32: PENDING

Sheet T2_Medicare_Capture
A1: T2. Medicare capture decomposition - the gross-up factor everyone needs
A2: Komodo Medicare base-code claims against a reconstruction of the Medicare book (FFS carrier floor + institutional wedge + an MA bound). Output: the implied Komodo capture of the Medicare book, and how much of Komodo Medicare must be MA. This capture rate is the candidate gross-up for the commercial and Medicaid columns.
A4: Step | B4: Value | C4: Unit | D4: Interpretation / caveat (in-row)
A5: Komodo Medicare base-code claims, 2025 (Medicare total - A0425) | B5: =Observed_Inputs!B11-Observed_Inputs!F22 -> 13936807 | C5: claims | D5: Base codes only (mileage removed), per the T10 denominator rule.
A6: FFS carrier base transports, 2024 (benchmark floor) | B6: =Benchmarks_Public!B7 -> 10637766 | C6: transports | D6: Carrier-visible FFS; the floor of the reconstruction.
A7: Plus institutional wedge (benchmark) | B7: =Benchmarks_Public!B9 -> 581532 | C7: transports | D7: Off-carrier FFS, hospital-outpatient billed.
A8: Equals FFS AFS book (carrier plus institutional) | B8: =Benchmarks_Public!B7+Benchmarks_Public!B9 -> 11219298 | C8: transports | D8: Reconciles to the MedPAC 11.3M all-AFS book as a sanity check.
A9: Implied MA volume inside Komodo Medicare (assumes full FFS capture) | B9: =T2_Medicare_Capture!B5-(Benchmarks_Public!B7+Benchmarks_Public!B9) -> 2717509 | C9: claims | D9: Komodo Medicare base minus the FFS AFS book; the residual must be Medicare Advantage.
A10: MA volume upper bound (dark-share gross-up, per-capita equal) | B10: =(Benchmarks_Public!B7+Benchmarks_Public!B9)*(Benchmarks_Public!B10/(1-Benchmarks_Public!B10)) -> 16346545 | C10: transports | D10: FFS AFS book scaled by MA/FFS beneficiary ratio; an UPPER bound (MA per-capita use is typically lower than FFS).
A11: Implied Komodo MA capture (of the MA upper bound) | B11: =T2_Medicare_Capture!B9/((Benchmarks_Public!B7+Benchmarks_Public!B9)*(Benchmarks_Public!B10/(1-Benchmarks_Public!B10))) -> 0.16624363 | C11: share | D11: A LOWER bound on MA capture, because the denominator is an upper bound.
A12: Reconstructed full Medicare book (FFS AFS + MA upper bound) | B12: =(Benchmarks_Public!B7+Benchmarks_Public!B9)*(1+(Benchmarks_Public!B10/(1-Benchmarks_Public!B10))) -> 27565843 | C12: transports | D12: The widest Medicare universe for the capture ratio.
A13: Implied Komodo capture of the full Medicare book | B13: =T2_Medicare_Capture!B5/((Benchmarks_Public!B7+Benchmarks_Public!B9)*(1+(Benchmarks_Public!B10/(1-Benchmarks_Public!B10)))) -> 0.50558247 | C13: share | D13: The candidate gross-up = 1 / this capture. See GrossUp_Factors.
A15: Caveats (carried to every downstream exhibit)
A16: Vintage: Komodo is calendar 2025; the benchmarks are 2023-2024. Weakest link: the gross-up assumes capture is PAYER-UNIFORM, so the Medicare capture rate is applied to Commercial and Medicaid - stated, not proven. The MA bound assumes MA per-capita utilization equals FFS, which overstates MA volume, so the MA capture percent is a floor and the full-book capture percent is a floor. "Medicare" in Komodo mixes FFS and MA and (pending T7) possibly institutional lines; this decomposition is the tool for splitting them.

Sheet T3_Commercial_Rate
A1: T3. Commercial realized-price table - supersedes the interim anchors
A2: Per code: Commercial combined allowed per claim, and the Medicare-multiple against both benchmarks (fee schedule CF x RVU, and realized PSPS allowed), side by side with the FAIR ~1.6x bound and the statutory pegs this measurement replaces. Reported-only is the conservative column (PENDING per-code reported dollars from the raw file).
A4: HCPCS | B4: Comm combined $/claim | C4: Multiple vs fee schedule | D4: Multiple vs realized | E4: Reported-only $/claim (cons.) | F4: FAIR bound | G4: Statutory pegs | H4: Read / caveat
A5: A0426 ALS1 non-emergency | B5: =Observed_Inputs!E23/Observed_Inputs!D23 -> 626.24658 | C5: =Observed_Inputs!E23/Observed_Inputs!D23/Benchmarks_Public!C25 -> 1.9155489 | D5: =Observed_Inputs!E23/Observed_Inputs!D23/Benchmarks_Public!D25 -> 1.9109196 | E5: PENDING | F5: ~1.6x | G5: varies by state | H5: Combined = reported + Komodo-estimated; see T4 for the modeled share. Reported-only column fills from the raw file.
A6: A0427 ALS1 emergency | B6: PENDING | C6: PENDING | D6: PENDING | E6: PENDING | F6: ~1.6x | G6: varies by state | H6: Commercial split obscured in the view; from raw file.
A7: A0428 BLS non-emergency | B7: =Observed_Inputs!E25/Observed_Inputs!D25 -> 533.18882 | C7: =Observed_Inputs!E25/Observed_Inputs!D25/Benchmarks_Public!C27 -> 1.9570871 | D7: =Observed_Inputs!E25/Observed_Inputs!D25/Benchmarks_Public!D27 -> 2.0456122 | E7: PENDING | F7: ~1.6x | G7: varies by state | H7: Combined = reported + Komodo-estimated; see T4 for the modeled share. Reported-only column fills from the raw file.
A8: A0429 BLS emergency | B8: PENDING | C8: PENDING | D8: PENDING | E8: PENDING | F8: ~1.6x | G8: varies by state | H8: Commercial split obscured in the view; from raw file.
A9: A0433 ALS2 | B9: PENDING | C9: PENDING | D9: PENDING | E9: PENDING | F9: ~1.6x | G9: varies by state | H9: Commercial split obscured in the view; from raw file.
A10: A0434 Specialty Care Transport | B10: =Observed_Inputs!E28/Observed_Inputs!D28 -> 2207.3596 | C10: =Observed_Inputs!E28/Observed_Inputs!D28/Benchmarks_Public!C30 -> 2.4929804 | D10: =Observed_Inputs!E28/Observed_Inputs!D28/Benchmarks_Public!D30 -> 2.4035886 | E10: PENDING | F10: ~1.6x | G10: varies by state | H10: Combined = reported + Komodo-estimated; see T4 for the modeled share. Reported-only column fills from the raw file.
A12: Transcription check: A0428 computes to about $533 combined per claim (~2.0x fee schedule, ~2.0x realized); A0434 to about $2,208 (~2.5x fee schedule, ~2.4x realized). These recompute from the raw file. The measured multiples replace the FAIR-derived ~1.6x bound and the statutory balance-billing pegs carried on the master Balance_Billing_States; both are shown for continuity.

Sheet T4_Estimated_Allowed
A1: T4. Estimated-allowed disclosure
A2: (Combined minus Reported) / Combined - the share of dollars that are Komodo-modeled rather than payer-reported. Every exhibit built on Combined carries this share as a printed caveat; T3 keeps a Reported-only column for exactly this reason.
A4: Scope | B4: Estimated share of $ | C4: Basis | D4: Interpretation
A5: Grand total (all payers, all codes) | B5: =(Observed_Inputs!E6-Observed_Inputs!C6)/Observed_Inputs!E6 -> 0.3411128 | C5: Combined vs Reported | D5: About a third of all dollars are Komodo-estimated where the payer did not report an allowed amount.
A6: Commercial (all codes) | B6: PENDING | C6: needs per-payer Reported $ | D6: Payer-level Reported dollars are not in the transcription; from the raw file.
A7: Medicare (all codes) | B7: PENDING | C7: needs per-payer Reported $ | D7: Payer-level Reported dollars are not in the transcription; from the raw file.
A8: Medicaid (all codes) | B8: PENDING | C8: needs per-payer Reported $ | D8: Payer-level Reported dollars are not in the transcription; from the raw file.
A9: Rule: any downstream number built on Combined dollars prints this estimated share beside it. The Reported-only figures are the conservative floor.

Sheet T5_Claim_Maturity
A1: T5. Claim maturity (Open vs Closed)
A2: Open versus Closed shares, the unit-price comparison closed vs combined, and a stated completion-factor method for how 2025 volumes will drift as claims close. No projected number - the method and the current bias direction only.
A4: Metric | B4: Value | C4: Unit | D4: Interpretation / caveat
A5: Open share of claims | B5: =Observed_Inputs!B16/Observed_Inputs!B6 -> 0.80128933 | C5: share | D5: 2025 is early: about four in five claims are still open.
A6: Closed share of claims | B6: =Observed_Inputs!B17/Observed_Inputs!B6 -> 0.1987113 | C6: share | D6: The mature slice usable for realized pricing.
A7: Closed combined $/claim | B7: =Observed_Inputs!C17/Observed_Inputs!B17 -> 311.17174 | C7: $/claim | D7: Compare to the all-status figure below.
A8: All-status combined $/claim | B8: =Observed_Inputs!E6/Observed_Inputs!B6 -> 304.28125 | C8: $/claim | D8: Closed-vs-all gap is the maturity price bias.
A10: Completion-factor method (no projected number)
A11: 2025 volumes are understated because ~80 percent of claims are still open. Method: once a mature prior year is available, compute a completion factor = final claims / claims-at-equivalent-age, and divide 2025 volumes by it to estimate the run-out. Current bias: 2025 counts and dollars will RISE as claims close. State the factor and the direction; do not print a projected total until the mature-year ratio is in hand.

Sheet T6_Payer_Mix
A1: T6. Payer mix of the scheduled book
A2: Per IFT code (A0426 / A0428 / A0434), payer shares of claims and dollars. Feeds the TAM pricing weights; compared against the master enrollment-based expectations (the dark share).
A4: HCPCS | B4: Comm % claims | C4: Mcare % claims | D4: Mcaid % claims | E4: Comm % $ | F4: Mcare % $ | G4: Mcaid % $ | H4: Read / caveat
A5: A0426 ALS1 non-emergency | B5: =Observed_Inputs!D23/Observed_Inputs!B23 -> 0.24355528 | C5: =Observed_Inputs!F23/Observed_Inputs!B23 -> 0.61513317 | D5: PENDING | E5: =Observed_Inputs!E23/Observed_Inputs!C23 -> 0.37095937 | F5: =Observed_Inputs!G23/Observed_Inputs!C23 -> 0.50962096 | G5: PENDING | H5: A0428 is ~77 percent Medicare by claims - the scheduled BLS book skews Medicare, as the dark share predicts. PENDING = split obscured in the view.
A6: A0428 BLS non-emergency | B6: =Observed_Inputs!D25/Observed_Inputs!B25 -> 0.099676209 | C6: =Observed_Inputs!F25/Observed_Inputs!B25 -> 0.77237426 | D6: =Observed_Inputs!H25/Observed_Inputs!B25 -> 0.12795212 | E6: =Observed_Inputs!E25/Observed_Inputs!C25 -> 0.15745019 | F6: =Observed_Inputs!G25/Observed_Inputs!C25 -> 0.72716887 | G6: =Observed_Inputs!I25/Observed_Inputs!C25 -> 0.11538094 | H6: A0428 is ~77 percent Medicare by claims - the scheduled BLS book skews Medicare, as the dark share predicts. PENDING = split obscured in the view.
A7: A0434 Specialty Care Transport | B7: =Observed_Inputs!D28/Observed_Inputs!B28 -> 0.26394775 | C7: =Observed_Inputs!F28/Observed_Inputs!B28 -> 0.53410595 | D7: =Observed_Inputs!H28/Observed_Inputs!B28 -> 0.2019463 | E7: =Observed_Inputs!E28/Observed_Inputs!C28 -> 0.46395349 | F7: =Observed_Inputs!G28/Observed_Inputs!C28 -> 0.41667393 | G7: =Observed_Inputs!I28/Observed_Inputs!C28 -> 0.11937258 | H7: A0428 is ~77 percent Medicare by claims - the scheduled BLS book skews Medicare, as the dark share predicts. PENDING = split obscured in the view.
A8: Compare Medicare claim shares here against the 59.3 percent dark share: Komodo Medicare includes MA, so a high Medicare share is consistent with MA being captured (see T2).

Sheet T7_Institutional_Lines
A1: T7. Institutional-lines presence test (answered empirically)
A2: Does the extract contain institutional (UB-04) claims? First from metadata (claim form / bill type / revenue-center fields), and if absent, by inference from whether the T2 Medicare reconstruction closes without room for the 581,532 institutional transports. One-cell verdict.
A4: Verdict
A5: Institutional lines in extract | B5: INDETERMINATE | C5: Metadata fields (claim form type / bill type / revenue center) are not in the transcription; the raw file decides. By inference, Komodo Medicare base already exceeds the FFS carrier floor, but the excess cannot be split between MA and institutional from volume alone - so the volume test is INDETERMINATE and metadata governs.
A7: Evidence
A8: Metadata check | B8: PENDING (raw file) | C8: Look for claim_form_type / bill_type_code / revenue_center in the raw schema. Presence of rev centers 0540-0549 = INCLUDED.
A9: Inference from T2 | B9: INDETERMINATE | C9: T2 FFS AFS book (carrier + wedge) already embeds the 581,532; Komodo Medicare base exceeds it, but the surplus is MA and/or institutional - not separable without metadata.
A11: If EXCLUDED - the correction and the second-extract spec (ready to forward)
A12: If institutional lines are EXCLUDED, the bottoms-up must ADD the institutional wedge (581,532 Medicare transports) separately, and the commercial/Medicaid institutional volume is unmeasured. Second extract spec: all claim lines with revenue centers 0540-0549 and HCPCS A0425-A0436, returning billing entity, service units, service date, and payer type, by year 2019-2024, so the institutional slice is measured directly rather than inferred.

Sheet T8_Mileage_Structure
A1: T8. Mileage structure
A2: A0425 claims per base-code claim, by payer, against the master loading factor. Printed limitation: Komodo shows CLAIMS, not mileage units, so this is a structural check, not a loading measurement.
A4: Metric | B4: Value | C4: Unit | D4: Interpretation / caveat
A5: A0425 Medicare claims per Medicare base-code claim | B5: =Observed_Inputs!F22/T2_Medicare_Capture!B5 -> 1.0564349 | C5: ratio | D5: About 1.06 mileage claims per base transport for Medicare - a structural ratio, not miles.
A6: Master loading factor (A0425 units per base transport) | B6: import Derived_Rate_Card | C6: x | D6: The master computes a mileage-LOADED price ratio; not directly comparable to a claims-per-claim count.
A7: Commercial / Medicaid mileage ratios | B7: PENDING | C7: ratio | D7: A0425 payer splits were obscured in the view; from the raw file.
A8: Limitation: a claims-per-claim ratio is not a loaded-mileage measurement. Reading loaded price per transport needs mileage UNITS, which Komodo does not carry.

Sheet T9_Geography
A1: T9. Geography spot-checks
A2: Re-run T2 / T3 / T6 filtered to Nebraska and one footprint MSA; compare to the master state benchmarks. Flags any geographic capture skew before a state cut is built on this data.
A4: Check | B4: Nebraska | C4: Footprint MSA | D4: Master comparison
A5: T2 Medicare capture (state) | B5: PENDING | C5: PENDING | D5: Compare vs Medicaid_Rate_Card (NE base rates) and the master state enrollment mix.
A6: T3 commercial multiple (state) | B6: PENDING | C6: PENDING | D6: Compare vs Medicaid_Rate_Card (NE base rates) and the master state enrollment mix.
A7: T6 payer mix (state) | B7: PENDING | C7: PENDING | D7: Compare vs Medicaid_Rate_Card (NE base rates) and the master state enrollment mix.
A8: Needs the state/MSA-filtered extract. On landing, these fill from the same formulas as T2/T3/T6 with the geography filter applied; a large NE-vs-national capture gap means the national gross-up cannot be applied to a state cut without adjustment.

Sheet T10_Denominator
A1: T10. Denominator discipline (import this everywhere)
A2: One definition every downstream exhibit uses, so no two cuts count differently.
A4: The counting rule
A5: A transport = | B5: one base-code claim (A0426, A0427, A0428, A0429, A0433, A0434). Mileage (A0425) is EXCLUDED from transport counts - it is a per-mile add-on, not a transport.
A6: Dollars = | B6: Combined allowed (reported + estimated) unless a panel states Reported-only; the estimated share (T4) travels with any Combined figure.
A7: Status = | B7: Combined (Open + Closed) for volume; closed-only where a panel measures mature realized price (T5).
A8: Non-mutual-exclusivity = | B8: a claim carrying multiple codes is counted once per code it carries; grand totals may exceed the distinct-claim count. The multi-code overlap is quantified from the raw file (PENDING) and printed here.
A9: Multi-code overlap (raw file) | B9: PENDING
A10: Every panel in this workbook already follows this rule; it is stated here as the single import for the sizing model.

Sheet GrossUp_Factors
A1: Gross-up factors (packaged from T2 for the sizing team)
A2: The Medicare capture rate turned into the gross-up that converts Komodo-captured volume to the universe, with every assumption listed. Handle as a bounded estimate, not a point.
A4: Factor | B4: Value | C4: Assumption / caveat
A5: Implied Komodo capture of the full Medicare book | B5: =T2_Medicare_Capture!B13 -> 0.50558247 | C5: From T2. Denominator uses the MA upper bound, so this capture is a FLOOR.
A6: Candidate gross-up = 1 / capture | B6: =1/T2_Medicare_Capture!B13 -> 1.9779167 | C6: Multiply Komodo-captured volume by this to approach the universe; a CEILING because capture is a floor.
A8: Assumptions (all of them)
A9: Capture is PAYER-UNIFORM: the Medicare capture rate is applied to the Commercial and Medicaid columns. This is the weakest link - Komodo commercial capture may differ materially.
A10: MA per-capita utilization = FFS in the MA bound; this overstates MA volume, making the capture a floor and the gross-up a ceiling.
A11: Vintage mismatch: Komodo is 2025 (mostly open claims, T5); benchmarks are 2023-2024. The completion factor (T5) will lift 2025 volumes.
A12: "Medicare" in Komodo mixes FFS and MA and (pending T7) possibly institutional lines.
A13: Volume that NO claims dataset contains - the ~1-in-5 did-not-always-bill and the 18.6 percent facility-pay layer - sits outside every gross-up here.

Sheet Commercial_Rate_Table
A1: Commercial rate table (packaged from T3)
A2: The measured commercial realized price per code and its Medicare-multiples - the replacement for the interim FAIR bound and statutory pegs. Combined dollars; the T4 estimated share travels with each figure.
A4: HCPCS | B4: Comm $/claim (combined) | C4: x fee schedule | D4: x realized | E4: Note
A5: A0426 ALS1 non-emergency | B5: =Observed_Inputs!E23/Observed_Inputs!D23 -> 626.24658 | C5: =Observed_Inputs!E23/Observed_Inputs!D23/Benchmarks_Public!C25 -> 1.9155489 | D5: =Observed_Inputs!E23/Observed_Inputs!D23/Benchmarks_Public!D25 -> 1.9109196 | E5: Carries the T4 estimated-allowed share.
A6: A0427 ALS1 emergency | B6: PENDING | C6: PENDING | D6: PENDING | E6: Commercial split from the raw file.
A7: A0428 BLS non-emergency | B7: =Observed_Inputs!E25/Observed_Inputs!D25 -> 533.18882 | C7: =Observed_Inputs!E25/Observed_Inputs!D25/Benchmarks_Public!C27 -> 1.9570871 | D7: =Observed_Inputs!E25/Observed_Inputs!D25/Benchmarks_Public!D27 -> 2.0456122 | E7: Carries the T4 estimated-allowed share.
A8: A0429 BLS emergency | B8: PENDING | C8: PENDING | D8: PENDING | E8: Commercial split from the raw file.
A9: A0433 ALS2 | B9: PENDING | C9: PENDING | D9: PENDING | E9: Commercial split from the raw file.
A10: A0434 Specialty Care Transport | B10: =Observed_Inputs!E28/Observed_Inputs!D28 -> 2207.3596 | C10: =Observed_Inputs!E28/Observed_Inputs!D28/Benchmarks_Public!C30 -> 2.4929804 | D10: =Observed_Inputs!E28/Observed_Inputs!D28/Benchmarks_Public!D30 -> 2.4035886 | E10: Carries the T4 estimated-allowed share.
A11: Supersedes: the FAIR-derived ~1.6x commercial bound and the statutory balance-billing pegs on the master Balance_Billing_States. Those remain in the master untouched; this is the engagement-side measured replacement.

Sheet Calibration_Memo
A1: Calibration memo - one page for Ray
A2: What the Komodo extract is good for, and the three things it cannot see.
A4: What the extract is
A5: Komodo Health ambulance claims, calendar 2025, seven codes, split Commercial / Medicare / Medicaid, with Open / Closed / Combined status and four dollar columns (Total, Reported, Estimated, Combined). ~47.1M claims and ~$14.3B combined allowed as transcribed; T1 re-derives from the raw file. Three caveats travel with every number: <1 percent of claims excluded for missing line-of-business/state, codes not mutually exclusive to status, and multiple codes per claim.
A6: The capture / gross-up (T2)
A7: Komodo Medicare base-code volume (~13.9M claims) against the reconstructed Medicare book implies a capture of roughly half the full Medicare universe - a candidate gross-up near 2x. It is a bounded estimate: the capture is a floor (MA bound is an upper bound) and it assumes capture is payer-uniform (the weakest link). Use it to scale, not to pinpoint.
A8: The commercial multiples (T3)
A9: Measured commercial realized price runs well above Medicare: A0428 ~$533 per claim (~2x fee schedule), A0434 ~$2,208 (~2.4x realized). This replaces the interim FAIR ~1.6x bound with a per-code, measured multiple. The Reported-only column (from the raw file) is the conservative version.
A10: The estimated-allowed disclosure (T4)
A11: About a third of all dollars are Komodo-MODELED, not payer-reported. Any sizing built on Combined dollars must carry this share; the Reported-only figures are the floor.
A12: The institutional verdict (T7)
A13: INDETERMINATE until the raw file: metadata (claim form / bill type / revenue center) decides whether institutional UB-04 lines are in. If EXCLUDED, add the 581,532 Medicare institutional wedge separately and cut the second extract (rev centers 0540-0549).
... A15: (1) Unbilled transports - the ~1-in-5 did-not-always-bill incidence. (2) Facility-pay revenue - 18.6 percent of organizations take it, and no claims dataset contains it. (3) Bundled transports - Part A inpatient-bundled and SNF consolidated-billing rides that never surface as a claim. No gross-up recovers these; they are named, not modeled.

Sheet Run_Log
A1: Run log and firewall attestation
A2: Build metadata, the raw-file hash slot, and the master-untouched leak check.
A4: Build
A5: Workbook | B5: Komodo_Calibration_v1.xlsx
A6: Built | B6: 14 July 2026
A7: Benchmark source | B7: IFT_Sourced_Evidence_Master v4.2 (values imported one-way; fact IDs on Benchmarks_Public)
A8: Extract vintage | B8: Komodo Health ambulance claims, calendar 2025
A9: State | B9: SKELETON - benchmarks and all test panels live; awaiting the raw extract from Andrew to re-derive Observed_Inputs (T1).
A11: Raw extract
A12: Raw file delivered | B12: PENDING (Andrew)
A13: Raw file SHA-256 | B13: PENDING
A15: Firewall leak check (master must be untouched)
A16: Zero Komodo-derived values in the master | B16: CONFIRMED at build - see leak_check_master.json; the extract signature figures (47,061,988 claims; $14,320,080,327 combined; the payer and code totals) appear nowhere in IFT_Sourced_Evidence_Master v4.2 or its repo.
A17: Direction | B17: One-way: master -> calibration. This workbook is never cited by, linked from, or merged into the master.
